Workbook
Name _B471721: #REF!
Name _B471721: #REF!
Name A: #REF!
Name A: #REF!
Name A: #REF!
Name A: #REF!
Name A: #REF!
Name A: #REF!
Name A: #REF!
Name A: #REF!
Name A: #REF!
Name A: #REF!
Name A: #REF!
Name A: #REF!
Name A: #REF!
Name A: #REF!
Name A: #REF!
Name A: #REF!
Name A: #REF!
Name A: #REF!
Name A: #REF!
Name A: #REF!
Name A: #REF!
Name A: #REF!
Name A: #REF!
Name A: #REF!
Name A: #REF!
Name A: #REF!
Name A: #REF!
Name A: #REF!
Name A: #REF!
Name A: #REF!
Name A: #REF!
Name A: #REF!
Name A: #REF!
Name A: #REF!
Name A: #REF!
Name A: #REF!
Name A: #REF!
Name combo_1_1_data: #REF!
Name combo_1_1_data: #REF!
Name CompanyType: #REF!
Name CompanyType: #REF!
Name dadadadadad: #REF!
Name dadadadadad: #REF!
Name date: #REF!
Name date: #REF!
Name didi: #REF!
Name didi: #REF!
Name didi: #REF!
Name didi: #REF!
Name didi: #REF!
Name didi: #REF!
Name didi: #REF!
Name didi: #REF!
Name didi: #REF!
Name didi: #REF!
Name didi: #REF!
Name didi: #REF!
Name didi: #REF!

Sheet 目录
A1: 序号 | B1: 预算模块 | C1: 工作表名称 | D1: 报表内容 | E1: 报表类型 | F1: 部门 | G1: 顺序 | H1: 填写顺序 | I1: 填写依赖 | J1: 负责人
A2: 1 | B2: 经营指标 | C2: 总体指标 | D2: 总体指标 | E2: 查阅 | G2: 3 | J2: 黎星宇 | K2: 查询表需要--集团，大区汇总 | N2: 营业收入（分内外销、产品系列）、营业成本（生产成本、销售成本、配方成本）、税金及附加、销售费用、管理费用、财务费用、营业外收支、所得税、利润总额、净利润
A3: 2 | B3: 利润表 | C3: 年度利润表 | D3: 年度指标 | E3: 查阅 | G3: 4 | J3: 黎星宇
A4: 3 | B4: 利润表 | C4: 月度利润表 | D4: 月度指标 | E4: 查阅 | G4: 5 | J4: 黎星宇
A5: 4 | B5: 产线贡献 | C5: 产线贡献表 | D5: 产线贡献 | E5: 查阅 | G5: 6 | J5: 邵苑君
A6: 5 | B6: 人效 | C6: 人效表 | D6: 人效 | E6: 查阅 | J6: 黎星宇
A7: 6 | B7: 预算主数据 | C7: 基础档案 | D7: 基础资料 | E7: 填写 | G7: 1 | H7: 0 | J7: 黎星宇
A8: 7 | B8: 预算主数据 | C8: 物料档案 | D8: 基础资料 | E8: 填写 | G8: 2 | H8: 0 | J8: 黎星宇
A9: 8 | B9: 销量毛利 | C9: A5 表样-聚焦镇量利（查阅） | D9: 聚焦镇指标 | E9: 查阅 | G9: 9 | J9: 邵苑君
A10: 9 | B10: 销量毛利 | C10: A6 表样-大类量利（查阅） | D10: 大类指标 | E10: 查阅 | G10: 7 | J10: 邵苑君
A11: 10 | B11: 销量毛利 | C11: A7 大类小类量利（查阅） | D11: 小类指标 | E11: 查阅 | G11: 8 | J11: 邵苑君
A12: 11 | B12: 销量毛利 | C12: 新增-产品系列配销差及吨毛利（查阅） | D12: 配销差吨毛利 | E12: 查阅 | G12: 12 | J12: 邵苑君
A13: 12 | B13: =D13 -> 毛利表（外销） | C13: A9-表样-客户产品毛利表（外销） | D13: 毛利表（外销） | E13: 查阅 | G13: 10 | J13: 邵苑君
A14: 13 | B14: =D14 -> 毛利表（内销） | C14: A9-表样-客户产品毛利表（内销） | D14: 毛利表（内销） | E14: 查阅 | G14: 11 | J14: 邵苑君
A15: 14 | B15: =D15 -> 生产成本 | C15: 查阅-产品生产成本 | D15: 生产成本 | E15: 查阅 | G15: 21 | J15: 黎星宇
A16: 15 | B16: 制造费用 | C16: 查阅-单吨制造费用-生产、财务 | D16: 制造费用 | E16: 查阅 | F16: 财务 | G16: 20 | H16: 3 | I16: 依赖产量（评审后）2 | J16: 黎星宇
A17: 16 | B17: =D17 -> 动保毛利 | C17: 查阅-动保产品大类毛利 | D17: 动保毛利 | E17: 查阅 | G17: 26 | J17: 邵苑君
A18: 17 | B18: =D18 -> 动保大类毛利 | C18: 查阅-动保产品大类毛利 (分月) | D18: 动保大类毛利 | E18: 查阅 | G18: 27 | J18: 邵苑君
A19: 18 | B19: =D19 -> 动保公司毛利 | C19: 查阅-动保产品公司毛利（分月） | D19: 动保公司毛利 | E19: 查阅 | G19: 28 | J19: 邵苑君
A20: 19 | B20: =D20 -> 动保产品毛利 | C20: 查阅-动保产品毛利表（明细） | D20: 动保产品毛利 | E20: 查阅 | G20: 29 | J20: 邵苑君
A21: 20 | B21: 销量 | C21: 填写-饲料销量-营销部 | D21: 饲料销量 | E21: 填写 | F21: 营销部（填）/营业部（审） | G21: 13 | H21: 1 | J21: 邵苑君
A22: 21 | B22: 动保销售额 | C22: 填写-动保销售额-营销部 | D22: 动保销售额 | E22: 填写 | F22: 营销部（填）/营业部（审） | G22: 22 | H22: 1 | J22: 邵苑君
A23: 22 | B23: 销量 | C23: 填写-动保发酵料-营销部 | D23: 动保销售额 | E23: 填写 | F23: 营销部（填）/营业部（审） | G23: 23 | H23: 1 | J23: 邵苑君
A24: 23 | B24: 动保销售额 | C24: 填写-动保销售额（除发酵料）-动保公司填写 | D24: 动保销售额 | E24: 填写 | F24: 营销部（填）/营业部（审） | H24: 1 | J24: 邵苑君 | K24: 应该可以与21合并，单位选择不一样
A25: 24 | B25: 销量 | C25: 填写-动保销量（发酵料）--动保公司填写 | D25: 动保销量 | E25: 填写 | F25: 营销部（填）/营业部（审） | H25: 1 | J25: 邵苑君 | K25: 应该可以与22合并，单位选择不一样
A26: 25 | B26: 动保成本 | C26: 填写-动保成本（除发酵料）--动保公司填写 | D26: 动保成本 | E26: 填写 | F26: 财务 | G26: 24 | H26: 3 | I26: 依赖销量（评审后）1 | J26: 黎星宇
A27: 26 | B27: 动保成本 | C27: 填写-动保成本（发酵料）--动保公司填写 | D27: 动保成本 | E27: 填写 | F27: 财务 | G27: 25 | H27: 3 | I27: 依赖销量（评审后）1 | J27: 黎星宇
A28: 27 | B28: 代工 | C28: 填写-内部代工（需求方）-营业部 | D28: 内部代工 | E28: 填写 | F28: 营业部/财务（代） | G28: 14 | H28: 2 | I28: 依赖销量1（销量评审后） | J28: 邵苑君
A29: 28 | B29: 代工 | C29: 填写-内部代工（生产方）-财务 | D29: 内部代工 | E29: 填写 | F29: 营业部/财务（代） | G29: 15 | H29: 2 | I29: 依赖销量1（销量评审后） | J29: 邵苑君
A30: 29 | B30: 产品价格 | C30: 填写-产品价目表-财务部 | D30: 产品价目表 | E30: 填写 | F30: 财务 | G30: 16 | H30: 2 | I30: 依赖销量1（销量评审后） | J30: 邵苑君
A31: 30 | B31: 配方成本 | C31: 填写-配方成本-配方师 | D31: 配方成本 | E31: 填写 | F31: 产品线（填）/财务（审）或（代） | G31: 18 | H31: 3 | I31: 依赖销量（评审后）1 | J31: 邵苑君
A32: 31 | B32: 产品折扣 | C32: 填写-产品折扣-财务部 | D32: 产品折扣 | E32: 填写 | F32: 财务 | G32: 17 | H32: 3 | I32: 依赖销量（评审后）1 | J32: 邵苑君
A33: 32 | B33: 包材成本 | C33: 填写-包材成本-采购、财务 | D33: 采购包材成本 | E33: 填写 | F33: 财务 | G33: 19 | H33: 3 | I33: 依赖销量（评审后）1 | J33: 邵苑君
A34: 33 | B34: 原料采购 | C34: 填写-主要原料价格-采购 | D34: 采购原料价格 | E34: 填写 | F34: 采购 | G34: 30 | H34: 3 | J34: 黎星宇
A35: 34 | B35: 产量 | C35: 表3 产量-生产产量填报表 | D35: 生产产量 | E35: 填写 | F35: 生产 | G35: 22 | H35: 2 | I35: 依赖销量1（销量评审后） | J35: 黎星宇
A36: 35 | B36: =D36 -> 生产产量 | C36: 表3 产量-汇总表（按大类） | D36: 生产产量 | E36: 查阅 | G36: 23 | J36: 黎星宇
A37: 36 | B37: 制造费用 | C37: 制造费用-填报生产部 | D37: 制造费用 | E37: 填写 | F37: 生产 | G37: 24 | H37: 3 | I37: 依赖产量（评审后）2 | J37: 黎星宇
A38: 37 | B38: =D38 -> 制造费用 | C38: 单吨制费计算表 | D38: 制造费用 | E38: 查阅 | G38: 25 | J38: 黎星宇
A39: 38 | B39: 人员编制 | C39: 表4.1 人员定编表（四定表）明细- 人资 | D39: 人资报表 | E39: 填写 | F39: 人资 | G39: 31 | H39: 3 | I39: 依赖销量产量（评审后）1、2 | J39: 朱勇金
A40: 39 | B40: 人员费用 | C40: 人工成本明细-人资 | D40: 人资报表 | E40: 填写 | F40: 人资 | G40: 32 | H40: 3 | I40: 依赖销量产量（评审后）1、2/依赖人员定编表 | J40: 朱勇金
A41: 40 | B41: =D41 -> 销售费用 | C41: 表7 表样-销费 | D41: 销售费用 | E41: 查阅 | G41: 33 | J41: 朱勇金
A42: 41 | B42: =D42 -> 销售费用 | C42: 表7.1 表样-销费科目明细 | D42: 销售费用 | E42: 查阅 | G42: 34 | J42: 朱勇金
A43: 42 | B43: 销售费用 | C43: 填写-职工福利费 | D43: 销售费用 | E43: 填写 | F43: 人资 | G43: 35 | H43: 3 | I43: 依赖销量（评审后）1/依赖人员定编表 | J43: 朱勇金
A44: 43 | B44: 销售费用 | C44: 填写-销售推广费 (广告) | D44: 销售费用 | E44: 填写 | F44: 营销部 | G44: 36 | H44: 3 | I44: 依赖销量（评审后）1 | J44: 朱勇金
A45: 44 | B45: 销售费用 | C45: 填写-业务招待费 | D45: 销售费用 | E45: 填写 | F45: 营销部 | G45: 37 | H45: 3 | I45: 依赖销量（评审后）1 | J45: 朱勇金
A46: 45 | B46: 销售费用 | C46: 填写-销售推广费 (物资推广) | D46: 销售费用 | E46: 填写 | F46: 营销部 | G46: 38 | H46: 3 | I46: 依赖销量（评审后）1 | J46: 朱勇金
A47: 46 | B47: 销售费用 | C47: 填写-会务费 | D47: 销售费用 | E47: 填写 | F47: 营销部 | G47: 39 | H47: 3 | I47: 依赖销量（评审后）1 | J47: 朱勇金
A48: 47 | B48: 销售费用 | C48: 填写-其他销售费用-财务 | D48: 销售费用 | E48: 填写 | F48: 财务 | G48: 40 | H48: 3 | I48: 依赖销量（评审后）1 | J48: 朱勇金
A49: 48 | B49: =D49 -> 管理费用 | C49: A8 表样-管费汇总-财务 | D49: 管理费用 | E49: 查阅 | G49: 41 | J49: 朱勇金
A50: 49 | B50: =D50 -> 管理费用 | C50: A8-1 表样-管费明细-财务 | D50: 管理费用 | E50: 查阅 | G50: 42 | J50: 朱勇金
A51: 50 | B51: 管理费用 | C51: 管-职工福利费-人资 | D51: 管理费用 | E51: 填写 | F51: 人资 | G51: 43 | H51: 3 | I51: 依赖人员定编表 | J51: 朱勇金
A52: 51 | B52: 管理费用 | C52: 管-差旅费-各部门 | D52: 管理费用 | E52: 填写 | F52: 各部门 | G52: 44 | H52: 3 | J52: 朱勇金
A53: 52 | B53: 管理费用 | C53: 管-业务招待费-各部门 | D53: 管理费用 | E53: 填写 | F53: 各部门 | G53: 45 | H53: 3 | J53: 朱勇金
A54: 53 | B54: 管理费用 | C54: 管-专业及政府费用-各部门 | D54: 管理费用 | E54: 填写 | F54: 财务/研究院 | G54: 46 | H54: 3 | J54: 朱勇金
A55: 54 | B55: 管理费用 | C55: 管-员工培训 | D55: 管理费用 | E55: 填写 | F55: 人资 | G55: 47 | H55: 3 | J55: 朱勇金
A56: 55 | B56: 管理费用 | C56: 管-招聘费用 | D56: 管理费用 | E56: 填写 | F56: 人资 | G56: 48 | H56: 3 | J56: 朱勇金
A57: 56 | B57: 管理费用 | C57: 管-办公费用 | D57: 管理费用 | E57: 填写 | F57: 各部门 | G57: 49 | H57: 3 | J57: 朱勇金
A58: 57 | B58: 管理费用 | C58: 管-维修费 | D58: 管理费用 | E58: 填写 | F58: 行政（人资代） | G58: 50 | H58: 3 | J58: 朱勇金
A59: 58 | B59: 管理费用 | C59: 管-房屋租金 | D59: 管理费用 | E59: 填写 | F59: 财务 | G59: 51 | H59: 3 | J59: 朱勇金
A60: 59 | B60: 管理费用 | C60: 管-水电 | D60: 管理费用 | E60: 填写 | F60: 行政（人资代） | G60: 52 | H60: 3 | J60: 朱勇金
A61: 60 | B61: 管理费用 | C61: 管-检测费 | D61: 管理费用 | E61: 填写 | F61: 行政（人资代） | G61: 53 | H61: 3 | J61: 朱勇金
A62: 61 | B62: 管理费用 | C62: 管-运输费 | D62: 管理费用 | E62: 填写 | F62: 各部门 | G62: 54 | H62: 3 | J62: 朱勇金
A63: 62 | B63: 管理费用 | C63: 管-会务费 | D63: 管理费用 | E63: 填写 | F63: 各部门 | G63: 55 | H63: 3 | J63: 朱勇金
... A66: 65 | B66: 人员费用 | C66: 专项激励-填报-各部门 | D66: 专项激励 | E66: 填写 | F66: 各部门（填）/人资（审） | G66: 58 | H66: 4 | J66: 朱勇金
A67: 66 | B67: 税金 | C67: 营业税金及附加-财务 | D67: 税金 | E67: 填写 | F67: 财务 | G67: 59 | H67: 3 | I67: 依赖销量（评审后）1 | J67: 朱勇金
A68: 67 | B68: 其他业务收支 | C68: 其他业务收支 | D68: 其他业务收支 | E68: 填写 | F68: 财务 | G68: 60 | H68: 3 | J68: 黎星宇
A69: 68 | B69: 营业外收支 | C69: 营业外收支 | D69: 营业外收支 | E69: 填写 | F69: 财务 | G69: 61 | H69: 3 | J69: 黎星宇
A70: 69 | B70: 税金 | C70: 所得税-财务 | D70: 所得税 | E70: 填写 | F70: 财务 | G70: 62 | H70: 5 | J70: 朱勇金
A71: 70 | B71: 考核调整 | C71: 特殊考核调整总数 | D71: 特殊考核调整 | E71: 查阅 | F71: 财务 | G71: 63 | H71: 4 | J71: 朱勇金
A72: 71 | B72: 考核调整 | C72: 利润调整明细（填写） | D72: 特殊考核调整 | E72: 填写 | F72: 财务 | G72: 64 | H72: 4 | J72: 朱勇金
A73: 72 | B73: =D73 -> 养殖预算 | C73: 养殖基地汇总-查询 | D73: 养殖预算 | E73: 查阅 | G73: 65 | J73: 朱勇金
A74: 73 | B74: 研发费用 | C74: 填写-养殖基地-明细 | D74: 养殖预算 | E74: 填写 | F74: 研究院 | G74: 66 | H74: 3 | J74: 朱勇金
A75: 74 | B75: =D75 -> 折旧费 | C75: 固定资产折旧费汇总-查询 | D75: 折旧费 | E75: 查阅 | G75: 67 | J75: 黎星宇
A76: 75 | B76: 固定资产 | C76: 新增固定资产填报表(填报）各部门 | D76: 折旧费 | E76: 填写 | F76: 财务 | G76: 68 | H76: 3 | J76: 黎星宇
A77: 76 | B77: =D77 -> 折旧费 | C77: 固定资产折旧费明细-查询表 | D77: 折旧费 | E77: 查阅 | G77: 69 | J77: 黎星宇
A78: 77 | B78: =D78 -> 资金报表 | C78: 查阅-公司（聚焦镇、大客户）汇总 | D78: 资金报表 | E78: 查阅 | G78: 70 | J78: 邵苑君
A79: 78 | B79: =D79 -> 资金报表 | C79: 查阅-各产线汇总 | D79: 资金报表 | E79: 查阅 | G79: 71 | J79: 邵苑君
A80: 79 | B80: =D80 -> 资金报表 | C80: 饲料资金预算--查询表（财务部） | D80: 资金报表 | E80: 查阅 | J80: 邵苑君
A81: 80 | B81: =D81 -> 资金报表 | C81: 填写-公司汇总表 | D81: 资金报表 | E81: 填写 | F81: 财务 | G81: 72 | H81: 4 | J81: 邵苑君
A82: 81 | B82: =D82 -> 资金报表 | C82: 填写-饲料资金预算填报表 | D82: 资金报表 | E82: 填写 | F82: 营销部（填）/财务（审） | G82: 73 | H82: 4 | J82: 邵苑君
A83: 82 | B83: =D83 -> 资金报表 | C83: 填写-动保资金预算填报表 | D83: 资金报表 | E83: 填写 | F83: 营销部（填）/财务（审） | G83: 74 | H83: 4 | J83: 邵苑君
A84: 83 | B84: 财务费用 | C84: A9 表样-财务费用汇总-财务 | D84: 财务费用 | E84: 填写 | F84: 财务 | H84: 3 | J84: 朱勇金
A85: 84 | B85: 无形资产 | C85: 新增无形资产填报表(填报）财务部，信息部 | D85: 摊销费 | E85: 填写 | F85: 财务 | H85: 3 | J85: 黎星宇
A86: 85 | B86: =D86 -> 摊销费 | C86: 无形资产摊销查询 | D86: 摊销费 | E86: 查阅 | J86: 黎星宇
A87: 86 | B87: =D87 -> 摊销费 | C87: 无形资产摊销费查询 | D87: 摊销费 | E87: 查阅 | J87: 黎星宇

Sheet 总体指标
A1: ← 返回目录
A2: 财务指标审核表
A3: 大区 | B3: 公司 | C3: 指标 | D3: 2026年预算 | E3: 2025年全年 | F3: 2024年全年 | G3: 预算增长额 | H3: 预算增长率 | I3: 异常数据说明
A4: 华东一区 | B4: 福建公司 | C4: 外销销量(万吨） | D4: 计算 | E4: 计算 | F4: 计算 | G4: 本表计算 | H4: 本表计算 | I4: 单位填写
A5: =A4 -> 华东一区 | B5: 福建公司 | C5: 主营业务收入(万元） | D5: 计算 | E5: 计算 | F5: 计算 | G5: 本表计算 | H5: 本表计算 | I5: 单位填写
A6: =A5 -> 华东一区 | B6: 福建公司 | C6: 毛利(万元） | D6: 计算 | E6: 计算 | F6: 计算 | G6: 本表计算 | H6: 本表计算 | I6: 单位填写
A7: =A6 -> 华东一区 | B7: 福建公司 | C7: 毛利率 | D7: 计算 | E7: 计算 | F7: 计算 | G7: 本表计算 | H7: 本表计算 | I7: 单位填写
A8: =A7 -> 华东一区 | B8: 福建公司 | C8: NC利润 | D8: 计算 | E8: 计算 | F8: 计算 | G8: 本表计算 | H8: 本表计算 | I8: 单位填写
A9: =A8 -> 华东一区 | B9: 福建公司 | C9: 特殊考核调整 | D9: 计算 | E9: 计算 | F9: 计算 | G9: 本表计算 | H9: 本表计算 | I9: 单位填写
A10: =A9 -> 华东一区 | B10: 福建公司 | C10: 考核利润(万元） | D10: 计算 | E10: 计算 | F10: 计算 | G10: 本表计算 | H10: 本表计算 | I10: 单位填写
A11: =A10 -> 华东一区 | B11: 福建公司 | C11: 其他业务利润(万元） | D11: 计算 | E11: 计算 | F11: 计算 | G11: 本表计算 | H11: 本表计算 | I11: 单位填写
A12: =A11 -> 华东一区 | B12: 福建公司 | C12: 销售费用 | D12: 计算 | E12: 计算 | F12: 计算 | G12: 本表计算 | H12: 本表计算 | I12: 单位填写
A13: =A12 -> 华东一区 | B13: 福建公司 | C13: 管理费用 | D13: 计算 | E13: 计算 | F13: 计算 | G13: 本表计算 | H13: 本表计算 | I13: 单位填写
A14: =A13 -> 华东一区 | B14: 福建公司 | C14: 财务费用 | D14: 计算 | E14: 计算 | F14: 计算 | G14: 本表计算 | H14: 本表计算 | I14: 单位填写
A15: =A14 -> 华东一区 | B15: 福建公司 | C15: 销售E值(万元） | D15: 本表计算 | E15: 本表计算 | F15: 本表计算 | G15: 本表计算 | H15: 本表计算 | I15: 单位填写
A16: =A15 -> 华东一区 | B16: 福建公司 | C16: 管理E值(万元） | D16: 本表计算 | E16: 本表计算 | F16: 本表计算 | G16: 本表计算 | H16: 本表计算 | I16: 单位填写
... A21: =A20 -> 华东一区 | B21: 福建公司 | C21: 单吨销售费用(元/吨） | D21: 本表计算 | E21: 本表计算 | F21: 本表计算 | G21: 本表计算 | H21: 本表计算 | I21: 单位填写
A22: =A20 -> 华东一区 | B22: 福建公司 | C22: 销售费用率 | D22: 本表计算 | E22: 本表计算 | F22: 本表计算 | G22: 本表计算 | H22: 本表计算 | I22: 单位填写
A23: =A22 -> 华东一区 | B23: 福建公司 | C23: 管理费用率 | D23: 本表计算 | E23: 本表计算 | F23: 本表计算 | G23: 本表计算 | H23: 本表计算 | I23: 单位填写
A24: =A23 -> 华东一区 | B24: 福建公司 | C24: 销售E/M值 | D24: 本表计算 | E24: 本表计算 | F24: 本表计算 | G24: 本表计算 | H24: 本表计算 | I24: 单位填写
A25: =A24 -> 华东一区 | B25: 福建公司 | C25: 管理E/M值 | D25: 本表计算 | E25: 本表计算 | F25: 本表计算 | G25: 本表计算 | H25: 本表计算 | I25: 单位填写
A26: 说明：所有指标同比偏差±30%以上，请填报人员必须说明原因，财务复核其合理性。

Sheet 年度利润表
A1: ← 返回目录
A2: 大区 | B2: 公司 | C2: 报表项目 | D2: 序号 | E2: 科目名称 | F2: 2026年预算 | G2: 2025年全年 | H2: 2024年全年 | I2: 同比额 | J2: 同比率 | K2: 异常说明
A3: ='[3]A1 预算指标总览'!$A$3 -> 华东一区 | B3: ='[3]A1 预算指标总览'!$B$3 -> 福建公司 | C3: 损益总表 | D3: 1 | E3: 销售量 | F3: 标题 | G3: 标题 | H3: 标题
A4: ='[3]A1 预算指标总览'!$A$3 -> 华东一区 | B4: ='[3]A1 预算指标总览'!$B$3 -> 福建公司 | C4: 损益总表 | D4: 2 | E4: 普通膨化鱼料 | F4: 计算 | G4: 计算 | H4: 计算 | I4: 本表计算 | J4: 本表计算
A5: ='[3]A1 预算指标总览'!$A$3 -> 华东一区 | B5: ='[3]A1 预算指标总览'!$B$3 -> 福建公司 | C5: 损益总表 | D5: 3 | E5: 高档膨化鱼料 | F5: 计算 | G5: 计算 | H5: 计算 | I5: 本表计算 | J5: 本表计算
A6: ='[3]A1 预算指标总览'!$A$3 -> 华东一区 | B6: ='[3]A1 预算指标总览'!$B$3 -> 福建公司 | C6: 损益总表 | D6: 4 | E6: 沉水鱼料 | F6: 计算 | G6: 计算 | H6: 计算 | I6: 本表计算 | J6: 本表计算
A7: ='[3]A1 预算指标总览'!$A$3 -> 华东一区 | B7: ='[3]A1 预算指标总览'!$B$3 -> 福建公司 | C7: 损益总表 | D7: 5 | E7: 虾料 | F7: 计算 | G7: 计算 | H7: 计算 | I7: 本表计算 | J7: 本表计算
A8: ='[3]A1 预算指标总览'!$A$3 -> 华东一区 | B8: ='[3]A1 预算指标总览'!$B$3 -> 福建公司 | C8: 损益总表 | D8: A1 | E8: 龙虾料 | F8: 计算 | G8: 计算 | H8: 计算 | I8: 本表计算 | J8: 本表计算
A9: ='[3]A1 预算指标总览'!$A$3 -> 华东一区 | B9: ='[3]A1 预算指标总览'!$B$3 -> 福建公司 | C9: 损益总表 | D9: 6 | E9: 蟹料 | F9: 计算 | G9: 计算 | H9: 计算 | I9: 本表计算 | J9: 本表计算
A10: ='[3]A1 预算指标总览'!$A$3 -> 华东一区 | B10: ='[3]A1 预算指标总览'!$B$3 -> 福建公司 | C10: 损益总表 | D10: 7 | E10: 浓缩/预混料 | F10: 计算 | G10: 计算 | H10: 计算 | I10: 本表计算 | J10: 本表计算
A11: ='[3]A1 预算指标总览'!$A$3 -> 华东一区 | B11: ='[3]A1 预算指标总览'!$B$3 -> 福建公司 | C11: 损益总表 | D11: 8 | E11: 猪饲料 | F11: 计算 | G11: 计算 | H11: 计算 | I11: 本表计算 | J11: 本表计算
A12: ='[3]A1 预算指标总览'!$A$3 -> 华东一区 | B12: ='[3]A1 预算指标总览'!$B$3 -> 福建公司 | C12: 损益总表 | D12: 9 | E12: 禽料 | F12: 计算 | G12: 计算 | H12: 计算 | I12: 本表计算 | J12: 本表计算
A13: ='[3]A1 预算指标总览'!$A$3 -> 华东一区 | B13: ='[3]A1 预算指标总览'!$B$3 -> 福建公司 | C13: 损益总表 | D13: 10 | E13: 反刍料 | F13: 计算 | G13: 计算 | H13: 计算 | I13: 本表计算 | J13: 本表计算
A14: ='[3]A1 预算指标总览'!$A$3 -> 华东一区 | B14: ='[3]A1 预算指标总览'!$B$3 -> 福建公司 | C14: 损益总表 | D14: 11 | E14: 销售量合计(吨) | F14: 本表计算 | G14: 本表计算 | H14: 本表计算 | I14: 本表计算 | J14: 本表计算
A15: ='[3]A1 预算指标总览'!$A$3 -> 华东一区 | B15: ='[3]A1 预算指标总览'!$B$3 -> 福建公司 | C15: 损益总表 | D15: 12 | E15: 一、主营业务收入 | F15: 计算 | G15: 计算 | H15: 计算 | I15: 本表计算 | J15: 本表计算
A16: ='[3]A1 预算指标总览'!$A$3 -> 华东一区 | B16: ='[3]A1 预算指标总览'!$B$3 -> 福建公司 | C16: 损益总表 | D16: 13 | E16: 减：主营业务成本 | F16: 计算 | G16: 计算 | H16: 计算 | I16: 本表计算 | J16: 本表计算
A17: ='[3]A1 预算指标总览'!$A$3 -> 华东一区 | B17: ='[3]A1 预算指标总览'!$B$3 -> 福建公司 | C17: 损益总表 | D17: 14 | E17: 二、毛利 | F17: 本表计算 | G17: 本表计算 | H17: 本表计算 | I17: 本表计算 | J17: 本表计算
A18: ='[3]A1 预算指标总览'!$A$3 -> 华东一区 | B18: ='[3]A1 预算指标总览'!$B$3 -> 福建公司 | C18: 损益总表 | D18: 15 | E18: 加：其它业务收入（代加工收入净额） | F18: 计算 | G18: 计算 | H18: 计算 | I18: 本表计算 | J18: 本表计算
A19: ='[3]A1 预算指标总览'!$A$3 -> 华东一区 | B19: ='[3]A1 预算指标总览'!$B$3 -> 福建公司 | C19: 损益总表 | D19: 16 | E19: 减：其它业务成本（代加工成本） | F19: 计算 | G19: 计算 | H19: 计算 | I19: 本表计算 | J19: 本表计算
A20: ='[3]A1 预算指标总览'!$A$3 -> 华东一区 | B20: ='[3]A1 预算指标总览'!$B$3 -> 福建公司 | C20: 损益总表 | D20: 17 | E20: 加：其它业务收入（外卖原料收益） | F20: 计算 | G20: 计算 | H20: 计算 | I20: 本表计算 | J20: 本表计算
... A43: ='[3]A1 预算指标总览'!$A$3 -> 华东一区 | B43: ='[3]A1 预算指标总览'!$B$3 -> 福建公司 | C43: 损益总表 | D43: 40 | E43: 五、净利润 | F43: 本表计算 | G43: 本表计算 | H43: 本表计算 | I43: 本表计算 | J43: 本表计算
A44: ='[3]A1 预算指标总览'!$A$3 -> 华东一区 | B44: ='[3]A1 预算指标总览'!$B$3 -> 福建公司 | C44: 损益总表 | D44: 41
A45: ='[3]A1 预算指标总览'!$A$3 -> 华东一区 | B45: ='[3]A1 预算指标总览'!$B$3 -> 福建公司 | C45: 损益总表 | D45: 42 | E45: 科目名称
A46: ='[3]A1 预算指标总览'!$A$3 -> 华东一区 | B46: ='[3]A1 预算指标总览'!$B$3 -> 福建公司 | C46: 损益总表 | D46: 43
A47: ='[3]A1 预算指标总览'!$A$3 -> 华东一区 | B47: ='[3]A1 预算指标总览'!$B$3 -> 福建公司 | C47: 损益总表 | D47: 44 | E47: 服务中心费用 | F47: 计算 | G47: 计算 | H47: 计算 | I47: 本表计算 | J47: 本表计算 | L47: 考核调整事项
A48: ='[3]A1 预算指标总览'!$A$3 -> 华东一区 | B48: ='[3]A1 预算指标总览'!$B$3 -> 福建公司 | C48: 损益总表 | D48: 45 | E48: 服务中心费用NC入账额对冲 | F48: 计算 | G48: 计算 | H48: 计算 | I48: 本表计算 | J48: 本表计算
A49: ='[3]A1 预算指标总览'!$A$3 -> 华东一区 | B49: ='[3]A1 预算指标总览'!$B$3 -> 福建公司 | C49: 损益总表 | D49: 46 | E49: 资金占用费-应收 | F49: 计算 | G49: 计算 | H49: 计算 | I49: 本表计算 | J49: 本表计算
A50: ='[3]A1 预算指标总览'!$A$3 -> 华东一区 | B50: ='[3]A1 预算指标总览'!$B$3 -> 福建公司 | C50: 损益总表 | D50: 47 | E50: 资金占用费-应付 | F50: 计算 | G50: 计算 | H50: 计算 | I50: 本表计算 | J50: 本表计算
A51: ='[3]A1 预算指标总览'!$A$3 -> 华东一区 | B51: ='[3]A1 预算指标总览'!$B$3 -> 福建公司 | C51: 损益总表 | D51: 48 | E51: 大区费用分摊 | F51: 计算 | G51: 计算 | H51: 计算 | I51: 本表计算 | J51: 本表计算
A52: ='[3]A1 预算指标总览'!$A$3 -> 华东一区 | B52: ='[3]A1 预算指标总览'!$B$3 -> 福建公司 | C52: 损益总表 | D52: 49 | E52: 大区费用NC入账额对冲 | F52: 计算 | G52: 计算 | H52: 计算 | I52: 本表计算 | J52: 本表计算
A53: ='[3]A1 预算指标总览'!$A$3 -> 华东一区 | B53: ='[3]A1 预算指标总览'!$B$3 -> 福建公司 | C53: 损益总表 | D53: 50 | E53: 代偿逾期费用 | F53: 计算 | G53: 计算 | H53: 计算 | I53: 本表计算 | J53: 本表计算
A54: ='[3]A1 预算指标总览'!$A$3 -> 华东一区 | B54: ='[3]A1 预算指标总览'!$B$3 -> 福建公司 | C54: 损益总表 | D54: 51 | E54: 兄弟公司间的原料买卖收益 | F54: 计算 | G54: 计算 | H54: 计算 | I54: 本表计算 | J54: 本表计算
A55: ='[3]A1 预算指标总览'!$A$3 -> 华东一区 | B55: ='[3]A1 预算指标总览'!$B$3 -> 福建公司 | C55: 损益总表 | D55: 52 | E55: 合计 | F55: 本表计算 | G55: 本表计算 | H55: 本表计算 | I55: 本表计算 | J55: 本表计算
A56: ='[3]A1 预算指标总览'!$A$3 -> 华东一区 | B56: ='[3]A1 预算指标总览'!$B$3 -> 福建公司 | C56: 损益总表 | D56: 53
A57: ='[3]A1 预算指标总览'!$A$3 -> 华东一区 | B57: ='[3]A1 预算指标总览'!$B$3 -> 福建公司 | C57: 损益总表 | D57: 54 | E57: NC利润 | F57: 本表计算 | G57: 本表计算 | H57: 本表计算 | I57: 本表计算 | J57: 本表计算
A58: ='[3]A1 预算指标总览'!$A$3 -> 华东一区 | B58: ='[3]A1 预算指标总览'!$B$3 -> 福建公司 | C58: 损益总表 | D58: 55

Sheet 月度利润表
A1: ← 返回目录 | AF1: 待定
A2: 大区 | B2: 公司 | C2: 项目 | D2: 行号 | E2: 科目名称 | F2: 2026年预算 | S2: 2025年实际数 | AF2: 2025年实际数
F3: 1 | G3: 2 | H3: 3 | I3: 4 | J3: 5 | K3: 6 | L3: 7 | M3: 8 | N3: 9 | O3: 10 | P3: 11 | Q3: 12 | R3: 合计 | S3: 1 | T3: 2 | U3: 3 | V3: 4 | W3: 5 | X3: 6 | Y3: 7 | Z3: 8 | AA3: 9 | AB3: 10 | AC3: 11 | AD3: 12 | AE3: 合计 | AF3: 1 | AG3: 2 | AH3: 3 | AI3: 4 | AJ3: 5 | AK3: 6 | AL3: 7 | AM3: 8 | AN3: 9 | AO3: 10 | AP3: 11 | AQ3: 12 | AR3: 合计
A4: ='[3]A1 预算指标总览'!$A$3 -> 华东一区 | B4: ='[3]A1 预算指标总览'!$B$3 -> 福建公司 | C4: 损益总表 | D4: 1 | E4: 销售量 | F4: 标题 | G4: 标题 | H4: 标题 | I4: 标题 | J4: 标题 | K4: 标题 | L4: 标题 | M4: 标题 | N4: 标题 | O4: 标题 | P4: 标题 | Q4: 标题 | R4: 本表计算 | S4: 标题 | T4: 标题 | U4: 标题 | V4: 标题 | W4: 标题 | X4: 标题 | Y4: 标题 | Z4: 标题 | AA4: 标题 | AB4: 标题 | AC4: 标题 | AD4: 标题 | AE4: 本表计算 | AF4: 标题 | AG4: 标题 | AH4: 标题 | AI4: 标题 | AJ4: 标题 | AK4: 标题 | AL4: 标题 | AM4: 标题 | AN4: 标题 | AO4: 标题 | AP4: 标题 | AQ4: 标题 | AR4: 本表计算
A5: ='[3]A1 预算指标总览'!$A$3 -> 华东一区 | B5: ='[3]A1 预算指标总览'!$B$3 -> 福建公司 | C5: 损益总表 | D5: 2 | E5: 普通膨化鱼料 | F5: 计算 | G5: 计算 | H5: 计算 | I5: 计算 | J5: 计算 | K5: 计算 | L5: 计算 | M5: 计算 | N5: 计算 | O5: 计算 | P5: 计算 | Q5: 计算 | R5: 本表计算 | S5: 计算 | T5: 计算 | U5: 计算 | V5: 计算 | W5: 计算 | X5: 计算 | Y5: 计算 | Z5: 计算 | AA5: 计算 | AB5: 计算 | AC5: 计算 | AD5: 计算 | AE5: 本表计算 | AF5: 计算 | AG5: 计算 | AH5: 计算 | AI5: 计算 | AJ5: 计算 | AK5: 计算 | AL5: 计算 | AM5: 计算 | AN5: 计算 | AO5: 计算 | AP5: 计算 | AQ5: 计算 | AR5: 本表计算
A6: ='[3]A1 预算指标总览'!$A$3 -> 华东一区 | B6: ='[3]A1 预算指标总览'!$B$3 -> 福建公司 | C6: 损益总表 | D6: 3 | E6: 海特料 | F6: 计算 | G6: 计算 | H6: 计算 | I6: 计算 | J6: 计算 | K6: 计算 | L6: 计算 | M6: 计算 | N6: 计算 | O6: 计算 | P6: 计算 | Q6: 计算 | R6: 本表计算 | S6: 计算 | T6: 计算 | U6: 计算 | V6: 计算 | W6: 计算 | X6: 计算 | Y6: 计算 | Z6: 计算 | AA6: 计算 | AB6: 计算 | AC6: 计算 | AD6: 计算 | AE6: 本表计算 | AF6: 计算 | AG6: 计算 | AH6: 计算 | AI6: 计算 | AJ6: 计算 | AK6: 计算 | AL6: 计算 | AM6: 计算 | AN6: 计算 | AO6: 计算 | AP6: 计算 | AQ6: 计算 | AR6: 本表计算
A7: ='[3]A1 预算指标总览'!$A$3 -> 华东一区 | B7: ='[3]A1 预算指标总览'!$B$3 -> 福建公司 | C7: 损益总表 | D7: 4 | E7: 沉水鱼料 | F7: 计算 | G7: 计算 | H7: 计算 | I7: 计算 | J7: 计算 | K7: 计算 | L7: 计算 | M7: 计算 | N7: 计算 | O7: 计算 | P7: 计算 | Q7: 计算 | R7: 本表计算 | S7: 计算 | T7: 计算 | U7: 计算 | V7: 计算 | W7: 计算 | X7: 计算 | Y7: 计算 | Z7: 计算 | AA7: 计算 | AB7: 计算 | AC7: 计算 | AD7: 计算 | AE7: 本表计算 | AF7: 计算 | AG7: 计算 | AH7: 计算 | AI7: 计算 | AJ7: 计算 | AK7: 计算 | AL7: 计算 | AM7: 计算 | AN7: 计算 | AO7: 计算 | AP7: 计算 | AQ7: 计算 | AR7: 本表计算
A8: ='[3]A1 预算指标总览'!$A$3 -> 华东一区 | B8: ='[3]A1 预算指标总览'!$B$3 -> 福建公司 | C8: 损益总表 | D8: 5 | E8: 虾料 | F8: 计算 | G8: 计算 | H8: 计算 | I8: 计算 | J8: 计算 | K8: 计算 | L8: 计算 | M8: 计算 | N8: 计算 | O8: 计算 | P8: 计算 | Q8: 计算 | R8: 本表计算 | S8: 计算 | T8: 计算 | U8: 计算 | V8: 计算 | W8: 计算 | X8: 计算 | Y8: 计算 | Z8: 计算 | AA8: 计算 | AB8: 计算 | AC8: 计算 | AD8: 计算 | AE8: 本表计算 | AF8: 计算 | AG8: 计算 | AH8: 计算 | AI8: 计算 | AJ8: 计算 | AK8: 计算 | AL8: 计算 | AM8: 计算 | AN8: 计算 | AO8: 计算 | AP8: 计算 | AQ8: 计算 | AR8: 本表计算
A9: ='[3]A1 预算指标总览'!$A$3 -> 华东一区 | B9: ='[3]A1 预算指标总览'!$B$3 -> 福建公司 | C9: 损益总表 | D9: A1 | E9: 龙虾料 | F9: 计算 | G9: 计算 | H9: 计算 | I9: 计算 | J9: 计算 | K9: 计算 | L9: 计算 | M9: 计算 | N9: 计算 | O9: 计算 | P9: 计算 | Q9: 计算 | R9: 本表计算 | S9: 计算 | T9: 计算 | U9: 计算 | V9: 计算 | W9: 计算 | X9: 计算 | Y9: 计算 | Z9: 计算 | AA9: 计算 | AB9: 计算 | AC9: 计算 | AD9: 计算 | AE9: 本表计算 | AF9: 计算 | AG9: 计算 | AH9: 计算 | AI9: 计算 | AJ9: 计算 | AK9: 计算 | AL9: 计算 | AM9: 计算 | AN9: 计算 | AO9: 计算 | AP9: 计算 | AQ9: 计算 | AR9: 本表计算
A10: ='[3]A1 预算指标总览'!$A$3 -> 华东一区 | B10: ='[3]A1 预算指标总览'!$B$3 -> 福建公司 | C10: 损益总表 | D10: 6 | E10: 蟹料 | F10: 计算 | G10: 计算 | H10: 计算 | I10: 计算 | J10: 计算 | K10: 计算 | L10: 计算 | M10: 计算 | N10: 计算 | O10: 计算 | P10: 计算 | Q10: 计算 | R10: 本表计算 | S10: 计算 | T10: 计算 | U10: 计算 | V10: 计算 | W10: 计算 | X10: 计算 | Y10: 计算 | Z10: 计算 | AA10: 计算 | AB10: 计算 | AC10: 计算 | AD10: 计算 | AE10: 本表计算 | AF10: 计算 | AG10: 计算 | AH10: 计算 | AI10: 计算 | AJ10: 计算 | AK10: 计算 | AL10: 计算 | AM10: 计算 | AN10: 计算 | AO10: 计算 | AP10: 计算 | AQ10: 计算 | AR10: 本表计算
A11: ='[3]A1 预算指标总览'!$A$3 -> 华东一区 | B11: ='[3]A1 预算指标总览'!$B$3 -> 福建公司 | C11: 损益总表 | D11: 7 | E11: 浓缩/预混料 | F11: 计算 | G11: 计算 | H11: 计算 | I11: 计算 | J11: 计算 | K11: 计算 | L11: 计算 | M11: 计算 | N11: 计算 | O11: 计算 | P11: 计算 | Q11: 计算 | R11: 本表计算 | S11: 计算 | T11: 计算 | U11: 计算 | V11: 计算 | W11: 计算 | X11: 计算 | Y11: 计算 | Z11: 计算 | AA11: 计算 | AB11: 计算 | AC11: 计算 | AD11: 计算 | AE11: 本表计算 | AF11: 计算 | AG11: 计算 | AH11: 计算 | AI11: 计算 | AJ11: 计算 | AK11: 计算 | AL11: 计算 | AM11: 计算 | AN11: 计算 | AO11: 计算 | AP11: 计算 | AQ11: 计算 | AR11: 本表计算
A12: ='[3]A1 预算指标总览'!$A$3 -> 华东一区 | B12: ='[3]A1 预算指标总览'!$B$3 -> 福建公司 | C12: 损益总表 | D12: 8 | E12: 猪饲料 | F12: 计算 | G12: 计算 | H12: 计算 | I12: 计算 | J12: 计算 | K12: 计算 | L12: 计算 | M12: 计算 | N12: 计算 | O12: 计算 | P12: 计算 | Q12: 计算 | R12: 本表计算 | S12: 计算 | T12: 计算 | U12: 计算 | V12: 计算 | W12: 计算 | X12: 计算 | Y12: 计算 | Z12: 计算 | AA12: 计算 | AB12: 计算 | AC12: 计算 | AD12: 计算 | AE12: 本表计算 | AF12: 计算 | AG12: 计算 | AH12: 计算 | AI12: 计算 | AJ12: 计算 | AK12: 计算 | AL12: 计算 | AM12: 计算 | AN12: 计算 | AO12: 计算 | AP12: 计算 | AQ12: 计算 | AR12: 本表计算
A13: ='[3]A1 预算指标总览'!$A$3 -> 华东一区 | B13: ='[3]A1 预算指标总览'!$B$3 -> 福建公司 | C13: 损益总表 | D13: 9 | E13: 禽料 | F13: 计算 | G13: 计算 | H13: 计算 | I13: 计算 | J13: 计算 | K13: 计算 | L13: 计算 | M13: 计算 | N13: 计算 | O13: 计算 | P13: 计算 | Q13: 计算 | R13: 本表计算 | S13: 计算 | T13: 计算 | U13: 计算 | V13: 计算 | W13: 计算 | X13: 计算 | Y13: 计算 | Z13: 计算 | AA13: 计算 | AB13: 计算 | AC13: 计算 | AD13: 计算 | AE13: 本表计算 | AF13: 计算 | AG13: 计算 | AH13: 计算 | AI13: 计算 | AJ13: 计算 | AK13: 计算 | AL13: 计算 | AM13: 计算 | AN13: 计算 | AO13: 计算 | AP13: 计算 | AQ13: 计算 | AR13: 本表计算
A14: ='[3]A1 预算指标总览'!$A$3 -> 华东一区 | B14: ='[3]A1 预算指标总览'!$B$3 -> 福建公司 | C14: 损益总表 | D14: 10 | E14: 反刍料 | F14: 计算 | G14: 计算 | H14: 计算 | I14: 计算 | J14: 计算 | K14: 计算 | L14: 计算 | M14: 计算 | N14: 计算 | O14: 计算 | P14: 计算 | Q14: 计算 | R14: 本表计算 | S14: 计算 | T14: 计算 | U14: 计算 | V14: 计算 | W14: 计算 | X14: 计算 | Y14: 计算 | Z14: 计算 | AA14: 计算 | AB14: 计算 | AC14: 计算 | AD14: 计算 | AE14: 本表计算 | AF14: 计算 | AG14: 计算 | AH14: 计算 | AI14: 计算 | AJ14: 计算 | AK14: 计算 | AL14: 计算 | AM14: 计算 | AN14: 计算 | AO14: 计算 | AP14: 计算 | AQ14: 计算 | AR14: 本表计算
A15: ='[3]A1 预算指标总览'!$A$3 -> 华东一区 | B15: ='[3]A1 预算指标总览'!$B$3 -> 福建公司 | C15: 损益总表 | D15: 11 | E15: 销售量合计(吨) | F15: 本表计算 | G15: 本表计算 | H15: 本表计算 | I15: 本表计算 | J15: 本表计算 | K15: 本表计算 | L15: 本表计算 | M15: 本表计算 | N15: 本表计算 | O15: 本表计算 | P15: 本表计算 | Q15: 本表计算 | R15: 本表计算 | S15: 本表计算 | T15: 本表计算 | U15: 本表计算 | V15: 本表计算 | W15: 本表计算 | X15: 本表计算 | Y15: 本表计算 | Z15: 本表计算 | AA15: 本表计算 | AB15: 本表计算 | AC15: 本表计算 | AD15: 本表计算 | AE15: 本表计算 | AF15: 本表计算 | AG15: 本表计算 | AH15: 本表计算 | AI15: 本表计算 | AJ15: 本表计算 | AK15: 本表计算 | AL15: 本表计算 | AM15: 本表计算 | AN15: 本表计算 | AO15: 本表计算 | AP15: 本表计算 | AQ15: 本表计算 | AR15: 本表计算
A16: ='[3]A1 预算指标总览'!$A$3 -> 华东一区 | B16: ='[3]A1 预算指标总览'!$B$3 -> 福建公司 | C16: 损益总表 | D16: 12 | E16: 一、主营业务收入 | F16: 计算 | G16: 计算 | H16: 计算 | I16: 计算 | J16: 计算 | K16: 计算 | L16: 计算 | M16: 计算 | N16: 计算 | O16: 计算 | P16: 计算 | Q16: 计算 | R16: 本表计算 | S16: 计算 | T16: 计算 | U16: 计算 | V16: 计算 | W16: 计算 | X16: 计算 | Y16: 计算 | Z16: 计算 | AA16: 计算 | AB16: 计算 | AC16: 计算 | AD16: 计算 | AE16: 本表计算 | AF16: 计算 | AG16: 计算 | AH16: 计算 | AI16: 计算 | AJ16: 计算 | AK16: 计算 | AL16: 计算 | AM16: 计算 | AN16: 计算 | AO16: 计算 | AP16: 计算 | AQ16: 计算 | AR16: 本表计算
A17: ='[3]A1 预算指标总览'!$A$3 -> 华东一区 | B17: ='[3]A1 预算指标总览'!$B$3 -> 福建公司 | C17: 损益总表 | D17: 13 | E17: 减：主营业务成本 | F17: 计算 | G17: 计算 | H17: 计算 | I17: 计算 | J17: 计算 | K17: 计算 | L17: 计算 | M17: 计算 | N17: 计算 | O17: 计算 | P17: 计算 | Q17: 计算 | R17: 本表计算 | S17: 计算 | T17: 计算 | U17: 计算 | V17: 计算 | W17: 计算 | X17: 计算 | Y17: 计算 | Z17: 计算 | AA17: 计算 | AB17: 计算 | AC17: 计算 | AD17: 计算 | AE17: 本表计算 | AF17: 计算 | AG17: 计算 | AH17: 计算 | AI17: 计算 | AJ17: 计算 | AK17: 计算 | AL17: 计算 | AM17: 计算 | AN17: 计算 | AO17: 计算 | AP17: 计算 | AQ17: 计算 | AR17: 本表计算
A18: ='[3]A1 预算指标总览'!$A$3 -> 华东一区 | B18: ='[3]A1 预算指标总览'!$B$3 -> 福建公司 | C18: 损益总表 | D18: 14 | E18: 二、毛利 | F18: 本表计算 | G18: 本表计算 | H18: 本表计算 | I18: 本表计算 | J18: 本表计算 | K18: 本表计算 | L18: 本表计算 | M18: 本表计算 | N18: 本表计算 | O18: 本表计算 | P18: 本表计算 | Q18: 本表计算 | R18: 本表计算 | S18: 本表计算 | T18: 本表计算 | U18: 本表计算 | V18: 本表计算 | W18: 本表计算 | X18: 本表计算 | Y18: 本表计算 | Z18: 本表计算 | AA18: 本表计算 | AB18: 本表计算 | AC18: 本表计算 | AD18: 本表计算 | AE18: 本表计算 | AF18: 本表计算 | AG18: 本表计算 | AH18: 本表计算 | AI18: 本表计算 | AJ18: 本表计算 | AK18: 本表计算 | AL18: 本表计算 | AM18: 本表计算 | AN18: 本表计算 | AO18: 本表计算 | AP18: 本表计算 | AQ18: 本表计算 | AR18: 本表计算
A19: ='[3]A1 预算指标总览'!$A$3 -> 华东一区 | B19: ='[3]A1 预算指标总览'!$B$3 -> 福建公司 | C19: 损益总表 | D19: 15 | E19: 加：其它业务收入（代加工收入净额） | F19: 计算 | G19: 计算 | H19: 计算 | I19: 计算 | J19: 计算 | K19: 计算 | L19: 计算 | M19: 计算 | N19: 计算 | O19: 计算 | P19: 计算 | Q19: 计算 | R19: 本表计算 | S19: 计算 | T19: 计算 | U19: 计算 | V19: 计算 | W19: 计算 | X19: 计算 | Y19: 计算 | Z19: 计算 | AA19: 计算 | AB19: 计算 | AC19: 计算 | AD19: 计算 | AE19: 本表计算 | AF19: 计算 | AG19: 计算 | AH19: 计算 | AI19: 计算 | AJ19: 计算 | AK19: 计算 | AL19: 计算 | AM19: 计算 | AN19: 计算 | AO19: 计算 | AP19: 计算 | AQ19: 计算 | AR19: 本表计算
A20: ='[3]A1 预算指标总览'!$A$3 -> 华东一区 | B20: ='[3]A1 预算指标总览'!$B$3 -> 福建公司 | C20: 损益总表 | D20: 16 | E20: 减：其它业务成本（代加工成本） | F20: 计算 | G20: 计算 | H20: 计算 | I20: 计算 | J20: 计算 | K20: 计算 | L20: 计算 | M20: 计算 | N20: 计算 | O20: 计算 | P20: 计算 | Q20: 计算 | R20: 本表计算 | S20: 计算 | T20: 计算 | U20: 计算 | V20: 计算 | W20: 计算 | X20: 计算 | Y20: 计算 | Z20: 计算 | AA20: 计算 | AB20: 计算 | AC20: 计算 | AD20: 计算 | AE20: 本表计算 | AF20: 计算 | AG20: 计算 | AH20: 计算 | AI20: 计算 | AJ20: 计算 | AK20: 计算 | AL20: 计算 | AM20: 计算 | AN20: 计算 | AO20: 计算 | AP20: 计算 | AQ20: 计算 | AR20: 本表计算
A21: ='[3]A1 预算指标总览'!$A$3 -> 华东一区 | B21: ='[3]A1 预算指标总览'!$B$3 -> 福建公司 | C21: 损益总表 | D21: 17 | E21: 加：其它业务收入（外卖原料收益） | F21: 计算 | G21: 计算 | H21: 计算 | I21: 计算 | J21: 计算 | K21: 计算 | L21: 计算 | M21: 计算 | N21: 计算 | O21: 计算 | P21: 计算 | Q21: 计算 | R21: 本表计算 | S21: 计算 | T21: 计算 | U21: 计算 | V21: 计算 | W21: 计算 | X21: 计算 | Y21: 计算 | Z21: 计算 | AA21: 计算 | AB21: 计算 | AC21: 计算 | AD21: 计算 | AE21: 本表计算 | AF21: 计算 | AG21: 计算 | AH21: 计算 | AI21: 计算 | AJ21: 计算 | AK21: 计算 | AL21: 计算 | AM21: 计算 | AN21: 计算 | AO21: 计算 | AP21: 计算 | AQ21: 计算 | AR21: 本表计算
... A44: ='[3]A1 预算指标总览'!$A$3 -> 华东一区 | B44: ='[3]A1 预算指标总览'!$B$3 -> 福建公司 | C44: 损益总表 | D44: 40 | E44: 五、净利润 | F44: 本表计算 | G44: 本表计算 | H44: 本表计算 | I44: 本表计算 | J44: 本表计算 | K44: 本表计算 | L44: 本表计算 | M44: 本表计算 | N44: 本表计算 | O44: 本表计算 | P44: 本表计算 | Q44: 本表计算 | R44: 本表计算 | S44: 本表计算 | T44: 本表计算 | U44: 本表计算 | V44: 本表计算 | W44: 本表计算 | X44: 本表计算 | Y44: 本表计算 | Z44: 本表计算 | AA44: 本表计算 | AB44: 本表计算 | AC44: 本表计算 | AD44: 本表计算 | AE44: 本表计算 | AF44: 本表计算 | AG44: 本表计算 | AH44: 本表计算 | AI44: 本表计算 | AJ44: 本表计算 | AK44: 本表计算 | AL44: 本表计算 | AM44: 本表计算 | AN44: 本表计算 | AO44: 本表计算 | AP44: 本表计算 | AQ44: 本表计算 | AR44: 本表计算
A45: ='[3]A1 预算指标总览'!$A$3 -> 华东一区 | B45: ='[3]A1 预算指标总览'!$B$3 -> 福建公司 | C45: 损益总表 | D45: 41
A46: ='[3]A1 预算指标总览'!$A$3 -> 华东一区 | B46: ='[3]A1 预算指标总览'!$B$3 -> 福建公司 | C46: 损益总表 | D46: 42 | E46: 科目名称 | F46: 2026年预算 | S46: 2025年实际数 | AF46: 2024年实际数
A47: ='[3]A1 预算指标总览'!$A$3 -> 华东一区 | B47: ='[3]A1 预算指标总览'!$B$3 -> 福建公司 | C47: 损益总表 | D47: 43 | F47: 1 | G47: 2 | H47: 3 | I47: 4 | J47: 5 | K47: 6 | L47: 7 | M47: 8 | N47: 9 | O47: 10 | P47: 11 | Q47: 12 | R47: 合计 | S47: 1 | T47: 2 | U47: 3 | V47: 4 | W47: 5 | X47: 6 | Y47: 7 | Z47: 8 | AA47: 9 | AB47: 10 | AC47: 11 | AD47: 12 | AE47: 合计 | AF47: 1 | AG47: 2 | AH47: 3 | AI47: 4 | AJ47: 5 | AK47: 6 | AL47: 7 | AM47: 8 | AN47: 9 | AO47: 10 | AP47: 11 | AQ47: 12 | AR47: 合计
A48: ='[3]A1 预算指标总览'!$A$3 -> 华东一区 | B48: ='[3]A1 预算指标总览'!$B$3 -> 福建公司 | C48: 损益总表 | D48: 44 | E48: 服务中心费用 | F48: 计算 | G48: 计算 | H48: 计算 | I48: 计算 | J48: 计算 | K48: 计算 | L48: 计算 | M48: 计算 | N48: 计算 | O48: 计算 | P48: 计算 | Q48: 计算 | R48: 本表计算 | S48: 计算 | T48: 计算 | U48: 计算 | V48: 计算 | W48: 计算 | X48: 计算 | Y48: 计算 | Z48: 计算 | AA48: 计算 | AB48: 计算 | AC48: 计算 | AD48: 计算 | AE48: 本表计算 | AF48: 计算 | AG48: 计算 | AH48: 计算 | AI48: 计算 | AJ48: 计算 | AK48: 计算 | AL48: 计算 | AM48: 计算 | AN48: 计算 | AO48: 计算 | AP48: 计算 | AQ48: 计算 | AR48: 本表计算
A49: ='[3]A1 预算指标总览'!$A$3 -> 华东一区 | B49: ='[3]A1 预算指标总览'!$B$3 -> 福建公司 | C49: 损益总表 | D49: 45 | E49: 服务中心费用NC入账额对冲 | F49: 计算 | G49: 计算 | H49: 计算 | I49: 计算 | J49: 计算 | K49: 计算 | L49: 计算 | M49: 计算 | N49: 计算 | O49: 计算 | P49: 计算 | Q49: 计算 | R49: 本表计算 | S49: 计算 | T49: 计算 | U49: 计算 | V49: 计算 | W49: 计算 | X49: 计算 | Y49: 计算 | Z49: 计算 | AA49: 计算 | AB49: 计算 | AC49: 计算 | AD49: 计算 | AE49: 本表计算 | AF49: 计算 | AG49: 计算 | AH49: 计算 | AI49: 计算 | AJ49: 计算 | AK49: 计算 | AL49: 计算 | AM49: 计算 | AN49: 计算 | AO49: 计算 | AP49: 计算 | AQ49: 计算 | AR49: 本表计算
A50: ='[3]A1 预算指标总览'!$A$3 -> 华东一区 | B50: ='[3]A1 预算指标总览'!$B$3 -> 福建公司 | C50: 损益总表 | D50: 46 | E50: 资金占用费-应收 | F50: 计算 | G50: 计算 | H50: 计算 | I50: 计算 | J50: 计算 | K50: 计算 | L50: 计算 | M50: 计算 | N50: 计算 | O50: 计算 | P50: 计算 | Q50: 计算 | R50: 本表计算 | S50: 计算 | T50: 计算 | U50: 计算 | V50: 计算 | W50: 计算 | X50: 计算 | Y50: 计算 | Z50: 计算 | AA50: 计算 | AB50: 计算 | AC50: 计算 | AD50: 计算 | AE50: 本表计算 | AF50: 计算 | AG50: 计算 | AH50: 计算 | AI50: 计算 | AJ50: 计算 | AK50: 计算 | AL50: 计算 | AM50: 计算 | AN50: 计算 | AO50: 计算 | AP50: 计算 | AQ50: 计算 | AR50: 本表计算
A51: ='[3]A1 预算指标总览'!$A$3 -> 华东一区 | B51: ='[3]A1 预算指标总览'!$B$3 -> 福建公司 | C51: 损益总表 | D51: 47 | E51: 资金占用费-应付 | F51: 计算 | G51: 计算 | H51: 计算 | I51: 计算 | J51: 计算 | K51: 计算 | L51: 计算 | M51: 计算 | N51: 计算 | O51: 计算 | P51: 计算 | Q51: 计算 | R51: 本表计算 | S51: 计算 | T51: 计算 | U51: 计算 | V51: 计算 | W51: 计算 | X51: 计算 | Y51: 计算 | Z51: 计算 | AA51: 计算 | AB51: 计算 | AC51: 计算 | AD51: 计算 | AE51: 本表计算 | AF51: 计算 | AG51: 计算 | AH51: 计算 | AI51: 计算 | AJ51: 计算 | AK51: 计算 | AL51: 计算 | AM51: 计算 | AN51: 计算 | AO51: 计算 | AP51: 计算 | AQ51: 计算 | AR51: 本表计算
A52: ='[3]A1 预算指标总览'!$A$3 -> 华东一区 | B52: ='[3]A1 预算指标总览'!$B$3 -> 福建公司 | C52: 损益总表 | D52: 48 | E52: 大区费用分摊 | F52: 计算 | G52: 计算 | H52: 计算 | I52: 计算 | J52: 计算 | K52: 计算 | L52: 计算 | M52: 计算 | N52: 计算 | O52: 计算 | P52: 计算 | Q52: 计算 | R52: 本表计算 | S52: 计算 | T52: 计算 | U52: 计算 | V52: 计算 | W52: 计算 | X52: 计算 | Y52: 计算 | Z52: 计算 | AA52: 计算 | AB52: 计算 | AC52: 计算 | AD52: 计算 | AE52: 本表计算 | AF52: 计算 | AG52: 计算 | AH52: 计算 | AI52: 计算 | AJ52: 计算 | AK52: 计算 | AL52: 计算 | AM52: 计算 | AN52: 计算 | AO52: 计算 | AP52: 计算 | AQ52: 计算 | AR52: 本表计算
A53: ='[3]A1 预算指标总览'!$A$3 -> 华东一区 | B53: ='[3]A1 预算指标总览'!$B$3 -> 福建公司 | C53: 损益总表 | D53: 49 | E53: 大区费用NC入账额对冲 | F53: 计算 | G53: 计算 | H53: 计算 | I53: 计算 | J53: 计算 | K53: 计算 | L53: 计算 | M53: 计算 | N53: 计算 | O53: 计算 | P53: 计算 | Q53: 计算 | R53: 本表计算 | S53: 计算 | T53: 计算 | U53: 计算 | V53: 计算 | W53: 计算 | X53: 计算 | Y53: 计算 | Z53: 计算 | AA53: 计算 | AB53: 计算 | AC53: 计算 | AD53: 计算 | AE53: 本表计算 | AF53: 计算 | AG53: 计算 | AH53: 计算 | AI53: 计算 | AJ53: 计算 | AK53: 计算 | AL53: 计算 | AM53: 计算 | AN53: 计算 | AO53: 计算 | AP53: 计算 | AQ53: 计算 | AR53: 本表计算
A54: ='[3]A1 预算指标总览'!$A$3 -> 华东一区 | B54: ='[3]A1 预算指标总览'!$B$3 -> 福建公司 | C54: 损益总表 | D54: 50 | E54: 代偿逾期费用 | F54: 计算 | G54: 计算 | H54: 计算 | I54: 计算 | J54: 计算 | K54: 计算 | L54: 计算 | M54: 计算 | N54: 计算 | O54: 计算 | P54: 计算 | Q54: 计算 | R54: 本表计算 | S54: 计算 | T54: 计算 | U54: 计算 | V54: 计算 | W54: 计算 | X54: 计算 | Y54: 计算 | Z54: 计算 | AA54: 计算 | AB54: 计算 | AC54: 计算 | AD54: 计算 | AE54: 本表计算 | AF54: 计算 | AG54: 计算 | AH54: 计算 | AI54: 计算 | AJ54: 计算 | AK54: 计算 | AL54: 计算 | AM54: 计算 | AN54: 计算 | AO54: 计算 | AP54: 计算 | AQ54: 计算 | AR54: 本表计算
A55: ='[3]A1 预算指标总览'!$A$3 -> 华东一区 | B55: ='[3]A1 预算指标总览'!$B$3 -> 福建公司 | C55: 损益总表 | D55: 51 | E55: 兄弟公司间的原料买卖收益 | F55: 计算 | G55: 计算 | H55: 计算 | I55: 计算 | J55: 计算 | K55: 计算 | L55: 计算 | M55: 计算 | N55: 计算 | O55: 计算 | P55: 计算 | Q55: 计算 | R55: 本表计算 | S55: 计算 | T55: 计算 | U55: 计算 | V55: 计算 | W55: 计算 | X55: 计算 | Y55: 计算 | Z55: 计算 | AA55: 计算 | AB55: 计算 | AC55: 计算 | AD55: 计算 | AE55: 本表计算 | AF55: 计算 | AG55: 计算 | AH55: 计算 | AI55: 计算 | AJ55: 计算 | AK55: 计算 | AL55: 计算 | AM55: 计算 | AN55: 计算 | AO55: 计算 | AP55: 计算 | AQ55: 计算 | AR55: 本表计算
A56: ='[3]A1 预算指标总览'!$A$3 -> 华东一区 | B56: ='[3]A1 预算指标总览'!$B$3 -> 福建公司 | C56: 损益总表 | D56: 52 | E56: 合计 | F56: 本表计算 | G56: 本表计算 | H56: 本表计算 | I56: 本表计算 | J56: 本表计算 | K56: 本表计算 | L56: 本表计算 | M56: 本表计算 | N56: 本表计算 | O56: 本表计算 | P56: 本表计算 | Q56: 本表计算 | R56: 本表计算 | S56: 本表计算 | T56: 本表计算 | U56: 本表计算 | V56: 本表计算 | W56: 本表计算 | X56: 本表计算 | Y56: 本表计算 | Z56: 本表计算 | AA56: 本表计算 | AB56: 本表计算 | AC56: 本表计算 | AD56: 本表计算 | AE56: 本表计算 | AF56: 本表计算 | AG56: 本表计算 | AH56: 本表计算 | AI56: 本表计算 | AJ56: 本表计算 | AK56: 本表计算 | AL56: 本表计算 | AM56: 本表计算 | AN56: 本表计算 | AO56: 本表计算 | AP56: 本表计算 | AQ56: 本表计算 | AR56: 本表计算
A57: ='[3]A1 预算指标总览'!$A$3 -> 华东一区 | B57: ='[3]A1 预算指标总览'!$B$3 -> 福建公司 | C57: 损益总表 | D57: 53 | R57: 本表计算 | AE57: 本表计算 | AR57: 本表计算
A58: ='[3]A1 预算指标总览'!$A$3 -> 华东一区 | B58: ='[3]A1 预算指标总览'!$B$3 -> 福建公司 | C58: 损益总表 | D58: 54 | E58: NC利润 | F58: 本表计算 | G58: 本表计算 | H58: 本表计算 | I58: 本表计算 | J58: 本表计算 | K58: 本表计算 | L58: 本表计算 | M58: 本表计算 | N58: 本表计算 | O58: 本表计算 | P58: 本表计算 | Q58: 本表计算 | R58: 本表计算 | S58: 本表计算 | T58: 本表计算 | U58: 本表计算 | V58: 本表计算 | W58: 本表计算 | X58: 本表计算 | Y58: 本表计算 | Z58: 本表计算 | AA58: 本表计算 | AB58: 本表计算 | AC58: 本表计算 | AD58: 本表计算 | AE58: 本表计算 | AF58: 本表计算 | AG58: 本表计算 | AH58: 本表计算 | AI58: 本表计算 | AJ58: 本表计算 | AK58: 本表计算 | AL58: 本表计算 | AM58: 本表计算 | AN58: 本表计算 | AO58: 本表计算 | AP58: 本表计算 | AQ58: 本表计算 | AR58: 本表计算

Sheet 产线贡献表
A1: ← 返回目录
E2: 定规则
A3: 公司 | B3: 产品线 | C3: 26年预算值 | M3: 同比 | W3: 25年实际值
C4: 销量 | D4: 毛利 | E4: 销售人数 | F4: 人员费用 | G4: 非人员费用 | H4: 总销售费用 | I4: 销售贡献 | J4: 人均贡献 | K4: 人均销量 | L4: 人均毛利 | M4: 销量 | N4: 毛利 | O4: 销售人数 | P4: 人员费用 | Q4: 非人员费用 | R4: 总销售费用 | S4: 销售贡献 | T4: 人均贡献 | U4: 人均销量 | V4: 人均毛利 | W4: 销量 | X4: 毛利 | Y4: 销售人数 | Z4: 人员费用 | AA4: 非人员费用 | AB4: 总销售费用 | AC4: 销售贡献 | AD4: 人均贡献 | AE4: 人均销量 | AF4: 人均毛利
B5: 虾蟹线 | C5: 计算 | D5: 计算 | E5: 计算 | F5: 计算 | G5: 计算 | H5: 计算 | I5: 本表计算 | J5: 本表计算 | K5: 本表计算 | L5: 本表计算 | M5: 本表计算 | N5: 本表计算 | O5: 本表计算 | P5: 本表计算 | Q5: 本表计算 | R5: 本表计算 | S5: 本表计算 | T5: 本表计算 | U5: 本表计算 | V5: 本表计算 | W5: 计算 | X5: 计算 | Y5: 计算 | Z5: 计算 | AA5: 计算 | AB5: 计算 | AC5: 本表计算 | AD5: 本表计算 | AE5: 本表计算 | AF5: 本表计算
B6: 海特线 | C6: 计算 | D6: 计算 | E6: 计算 | F6: 计算 | G6: 计算 | H6: 计算 | I6: 本表计算 | J6: 本表计算 | K6: 本表计算 | L6: 本表计算 | M6: 本表计算 | N6: 本表计算 | O6: 本表计算 | P6: 本表计算 | Q6: 本表计算 | R6: 本表计算 | S6: 本表计算 | T6: 本表计算 | U6: 本表计算 | V6: 本表计算 | W6: 计算 | X6: 计算 | Y6: 计算 | Z6: 计算 | AA6: 计算 | AB6: 计算 | AC6: 本表计算 | AD6: 本表计算 | AE6: 本表计算 | AF6: 本表计算
B7: 鱼料线 | C7: 计算 | D7: 计算 | E7: 计算 | F7: 计算 | G7: 计算 | H7: 计算 | I7: 本表计算 | J7: 本表计算 | K7: 本表计算 | L7: 本表计算 | M7: 本表计算 | N7: 本表计算 | O7: 本表计算 | P7: 本表计算 | Q7: 本表计算 | R7: 本表计算 | S7: 本表计算 | T7: 本表计算 | U7: 本表计算 | V7: 本表计算 | W7: 计算 | X7: 计算 | Y7: 计算 | Z7: 计算 | AA7: 计算 | AB7: 计算 | AC7: 本表计算 | AD7: 本表计算 | AE7: 本表计算 | AF7: 本表计算
B8: 畜禽线 | C8: 计算 | D8: 计算 | E8: 计算 | F8: 计算 | G8: 计算 | H8: 计算 | I8: 本表计算 | J8: 本表计算 | K8: 本表计算 | L8: 本表计算 | M8: 本表计算 | N8: 本表计算 | O8: 本表计算 | P8: 本表计算 | Q8: 本表计算 | R8: 本表计算 | S8: 本表计算 | T8: 本表计算 | U8: 本表计算 | V8: 本表计算 | W8: 计算 | X8: 计算 | Y8: 计算 | Z8: 计算 | AA8: 计算 | AB8: 计算 | AC8: 本表计算 | AD8: 本表计算 | AE8: 本表计算 | AF8: 本表计算
B9: 合计 | C9: 本表计算 | D9: 本表计算 | E9: 本表计算 | F9: 本表计算 | G9: 本表计算 | H9: 本表计算 | I9: 本表计算 | J9: 本表计算 | K9: 本表计算 | L9: 本表计算 | M9: 本表计算 | N9: 本表计算 | O9: 本表计算 | P9: 本表计算 | Q9: 本表计算 | R9: 本表计算 | S9: 本表计算 | T9: 本表计算 | U9: 本表计算 | V9: 本表计算 | W9: 本表计算 | X9: 本表计算 | Y9: 本表计算 | Z9: 本表计算 | AA9: 本表计算 | AB9: 本表计算 | AC9: 本表计算 | AD9: 本表计算 | AE9: 本表计算 | AF9: 本表计算

Sheet 人效表
A1: ← 返回目录 | B1: 公司 | C1: 产线 | D1: 人均销量 | S1: 人数 | AG1: 销量
D2: 25年 | E2: 26年 | F2: 同比 | G2: 1月 | H2: 2月 | I2: 3月 | J2: 4月 | K2: 5月 | L2: 6月 | M2: 7月 | N2: 8月 | O2: 9月 | P2: 10月 | Q2: 11月 | R2: 12月 | S2: 25年 | T2: 26年 | U2: 1月 | V2: 2月 | W2: 3月 | X2: 4月 | Y2: 5月 | Z2: 6月 | AA2: 7月 | AB2: 8月 | AC2: 9月 | AD2: 10月 | AE2: 11月 | AF2: 12月 | AG2: 25年 | AH2: 26年 | AI2: 1月 | AJ2: 2月 | AK2: 3月 | AL2: 4月 | AM2: 5月 | AN2: 6月 | AO2: 7月 | AP2: 8月 | AQ2: 9月 | AR2: 10月 | AS2: 11月 | AT2: 12月
C3: 整体
C4: 虾蟹线
C5: 海特线
C6: 普鱼线
C7: 畜禽线
C8: 反刍线

Sheet 基础档案
A1: ← 返回目录 | C1: 返回目录 | E1: 销售费用 | H1: 研发费用 | I1: 还原 | K1: 大区 | L1: 序号 | M1: 子公司 | N1: 财务对接人 | O1: 性质 | P1: 客户性质 | Q1: 产品大类 | S1: 华东区 | T1: 华南区 | U1: 华中区 | V1: 其他区 | X1: 月份 | AA1: 客户性质 | AB1: 客户类别 | AC1: 主营料种 | AD1: 产线
A2: 科目名称 | E2: 科目 | F2: 科目说明 | H2: 科目名称 | I2: 费用类别 | J2: 明细类别 | K2: 华南区 | L2: 1 | M2: 福建 | N2: 毕昌 | O2: 基地公司 | P2: 老客户 | Q2: 虾料 | R2: 目录!A1 | S2: 福建 | T2: 江门生物 | U2: 武汉 | V2: 原本 | X2: 1 | Y2: 1 | AA2: 新客户 | AB2: 经销商 | AC2: 虾料 | AD2: 虾蟹线
B3: 分类 | C3: 分解科目 | H3: 530104\研发支出\租赁费 | I3: 管理费用 | J3: 折旧费 | K3: 华东区 | L3: 2 | M3: 浙江 | N3: 高海菊 | O3: 基地公司 | P3: 新客户 | Q3: 蟹料 | S3: 浙江 | T3: 四会 | U3: 汉南 | V3: 越南 | X3: 2 | Y3: 2 | AA3: 老客户 | AB3: 直销户 | AC3: 龙虾料 | AD3: 海特线
A4: 销售吨数 | E4: 变动成本 | H4: 53010201\研发支出\人员人工\工资 | I4: 管理费用 | J4: 人工薪酬（工资、五险一金） | K4: 华中区 | L4: 3 | M4: 唐山 | N4: 梁文雅 | O4: 基地公司 | Q4: 普通膨化鱼料 | S4: 唐山 | T4: 玉林 | U4: 荆州 | V4: 澳保 | X4: 3 | Y4: 3 | AB4: 代工客户 | AC4: 蟹料 | AD4: 普鱼线
A5: 销售标准吨数 | E5: 提成奖励 | H5: 53010202\研发支出\人员人工\绩效工资 | I5: 管理费用 | J5: 人工薪酬（工资、五险一金） | K5: 其他区 | L5: 4 | M5: 惠州 | N5: 王虎伟 | O5: 基地公司 | Q5: 沉水鱼料 | S5: 惠州 | T5: 广西 | U5: 江西 | V5: 伟凝 | X5: 4 | Y5: 4 | AC5: 海特料 | AD5: 畜禽线
A6: 销售人数 | E6: 年终提成 | H6: 530124\研发支出\水电物业费 | I6: 制造费用 | J6: 能耗 | L6: 5 | M6: 淮安 | N6: 曹杰 | O6: 基地公司 | Q6: 高档膨化鱼料 | S6: 澳源 | T6: 贵州 | U6: 池州 | V6: 总部 | X6: 5 | Y6: 5 | AC6: 普通膨化鱼料
A7: 工资和薪金 | B7: 固定 | C7: 人力费用（固定工资、五险一金、职工福利） | E7: 成长分享 | H7: 53010204\研发支出\人员人工\公积金 | I7: 管理费用 | J7: 人工薪酬（工资、五险一金） | L7: 6 | M7: 泰州 | N7: 豆业晶 | O7: 基地公司 | Q7: 浓缩/预混料 | S7: 淮安 | T7: 海南 | U7: 洛阳水产 | X7: 6 | Y7: 6 | AC7: 沉水鱼料
A8: 提成奖励 | B8: 变动 | C8: 提成奖励 | E8: 运输费 | H8: 5301020501\研发支出\人员人工\社保\养老保险 | I8: 管理费用 | J8: 人工薪酬（工资、五险一金） | L8: 7 | M8: 南京 | N8: 郭良 | O8: 基地公司 | Q8: 猪饲料 | S8: 泰州 | T8: 大粤西 | U8: 洛阳陕西 | X8: 7 | Y8: 7 | AC8: 猪饲料
A9: 年终提成 | B9: 变动 | C9: 年终提成 | E9: 技术服务费 | H9: 5301020502\研发支出\人员人工\社保\医疗保险 | I9: 管理费用 | J9: 人工薪酬（工资、五险一金） | L9: 8 | M9: 江门生物 | N9: 邓洪才 | O9: 基地公司 | Q9: 禽料 | S9: 南京 | T9: 湛江 | U9: 洛阳畜禽 | X9: 8 | Y9: 8 | AC9: 禽料
A10: 成长分享 | B10: 变动 | C10: 成长分享 | E10: 固定成本 | H10: 5301020503\研发支出\人员人工\社保\工伤保险 | I10: 管理费用 | J10: 人工薪酬（工资、五险一金） | L10: 9 | M10: 四会 | N10: 张裕华 | O10: 基地公司 | Q10: 反刍料 | S10: 江苏 | T10: 四川 | U10: 湖南 | X10: 9 | Y10: 9 | AC10: 反刍料
A11: 劳务费 | B11: 固定 | C11: 人力费用（固定工资、五险一金、职工福利） | E11: 人力费用（固定工资、五险一金、职工福利） | H11: 5301020504\研发支出\人员人工\社保\失业保险 | I11: 管理费用 | J11: 人工薪酬（工资、五险一金） | L11: 10 | M11: 广西 | N11: 龙玉杰 | O11: 基地公司 | T11: 云南 | U11: 湖南澳源 | X11: 10 | Y11: 10 | AC11: 浓缩预混料
A12: 社保费 | B12: 固定 | C12: 人力费用（固定工资、五险一金、职工福利） | E12: 差旅费 | H12: 5301020505\研发支出\人员人工\社保\生育医疗 | I12: 管理费用 | J12: 人工薪酬（工资、五险一金） | L12: 11 | M12: 云南 | N12: 李小婷 | O12: 销售公司 | U12: 岳阳 | X12: 11 | Y12: 11 | AC12: 动保
A13: 住房公积金 | B13: 固定 | C13: 人力费用（固定工资、五险一金、职工福利） | E13: 车辆使用费 | H13: 530125\研发支出\成长分享 | I13: 管理费用 | J13: 成长分享 | L13: 12 | M13: 贵州 | N13: 蒙鸿娟 | O13: 销售公司 | U13: 益阳 | X13: 12 | Y13: 12
A14: 职工福利金 | B14: 固定 | C14: 人力费用（固定工资、五险一金、职工福利） | E14: 应酬费 | H14: 530103\研发支出\折旧费 | I14: 制造费用 | J14: 折旧费 | L14: 13 | M14: 四川 | N14: 石玉琴 | O14: 销售公司 | U14: 衡阳 | X14: 全年 | Y14: 13
A15: 差旅补助 | B15: 固定 | C15: 差旅费 | E15: 推广、会务 | H15: 530101\研发支出\直接材料及燃动力 | I15: 管理费用 | J15: 办公费用 | L15: 14 | M15: 湛江 | N15: 曾君 | O15: 基地公司
A16: 差旅费 | B16: 固定 | C16: 差旅费 | E16: 固定资产折旧费 | H16: 530111\研发支出\车辆使用费 | I16: 管理费用 | J16: 办公费用 | L16: 15 | M16: 海南 | N16: 何栩童 | O16: 事业部
A17: 车辆使用费 | B17: 固定 | C17: 人力费用（固定工资、五险一金、职工福利） | E17: 诉讼费 | H17: 53010203\研发支出\人员人工\奖金 | I17: 管理费用 | J17: 人工薪酬（工资、五险一金） | L17: 16 | M17: 武汉 | N17: 蒋晓玲 | O17: 基地公司
A18: 应酬费 | B18: 固定 | C18: 应酬费 | H18: 530122\研发支出\办公费 | I18: 管理费用 | J18: 办公费用 | L18: 17 | M18: 汉南 | N18: 余俊 | O18: 基地公司
A19: 销售推广费 | B19: 固定 | C19: 推广、会务 | H19: 530109\研发支出\技术服务费 | I19: 管理费用 | J19: 办公费用 | L19: 18 | M19: 荆州 | N19: 孙子明 | O19: 销售公司
A20: 会务费 | B20: 固定 | C20: 推广、会务 | E20: 管理费用 | H20: 530108\研发支出\差旅费 | I20: 管理费用 | J20: 人工薪酬（工资、五险一金） | L20: 19 | M20: 江西 | N20: 卞淑芬 | O20: 基地公司
A21: 运输费 | B21: 变动 | C21: 运输费 | E21: 科目 | H21: 530121\研发支出\业务招待费 | I21: 管理费用 | J21: 应酬费 | L21: 20 | M21: 洛阳水产 | N21: 韩玉可 | O21: 事业部
A22: 中转仓储费 | B22: 固定 | C22: 固定资产折旧费 | H22: 530119\研发支出\职工福利费 | I22: 管理费用 | J22: 人工薪酬（工资、五险一金） | L22: 22 | M22: 洛阳畜禽 | N22: 韩玉可 | O22: 基地公司
A23: 诉讼费 | B23: 固定 | C23: 诉讼费 | E23: 变动费用 | H23: 530123\研发支出\维护费 | I23: 制造费用 | J23: 维修费 | L23: 23 | M23: 湖南 | N23: 郭佳 | O23: 基地公司
A24: 其他 | B24: 固定 | C24: 固定资产折旧费 | E24: 成长分享 | H24: 530116\研发支出\外聘劳务费 | I24: 管理费用 | J24: 人工薪酬（工资、五险一金） | L24: 24 | M24: 益阳 | N24: 罗燕红 | O24: 销售公司
A25: 运输费（对内） | B25: 变动 | C25: 运输费 | E25: 股份支付 | H25: 530117\研发支出\购置费及检验费 | I25: 制造费用 | J25: 维修费 | L25: 26 | M25: 越南 | N25: 肖阿林 | O25: 基地公司
A26: 办公费 | B26: 固定 | C26: 推广、会务 | E26: 固定费用 | H26: 530112\研发支出\会务费 | I26: 管理费用 | J26: 会务费 | L26: 27 | M26: 澳保 | N26: 路鑫 | O26: 基地公司
A27: 技术服务费 | B27: 变动 | C27: 技术服务费 | E27: 人工薪酬（工资、五险一金） | H27: 530126\研发支出\运输费 | I27: 管理费用 | J27: 办公费用 | L27: 28 | M27: 伟凝 | N27: 陈小冰 | O27: 销售公司
A28: 使用权资产折旧费 | B28: 固定 | C28: 固定资产折旧费 | E28: 应酬费 | H28: 530120\研发支出\使用权资产折旧费 | I28: 管理费用 | J28: 折旧费 | L28: 29 | M28: 总部 | N28: 陈晓佳 | O28: 总部
A29: 固定资产折旧费 | B29: 固定 | C29: 固定资产折旧费 | E29: 办公费用 | H29: 530113\研发支出\知识产权费 | I29: 管理费用 | J29: 折旧费
A30: 无形资产摊销费 | B30: 固定 | C30: 固定资产折旧费 | E30: 培训招聘费 | H30: 530115\研发支出\长期待摊费用摊销 | I30: 管理费用 | J30: 折旧费
A31: 长期待摊费用摊销 | B31: 固定 | C31: 固定资产折旧费 | E31: 水电费 | H31: 530118\研发支出\设计制定费及试验费 | I31: 制造费用 | J31: 维修费

Sheet 物料档案
A1: ← 返回目录
A2: 所属公司 | B2: 启用状态 | C2: 物料编码 | D2: 物料名称 | E2: 物料编码 | F2: 大类 | G2: 小类 | H2: 5+2分类 | I2: 助记码 | J2: 产品系列
A3: 湖南澳华农牧科技有限公司 | B3: 已启用 | C3: 2201020561 | D3: 花鲢1号Φ1.0 | E3: 2201020561 | F3: 普通膨化鱼料 | G3: 鳙鱼料 | I3: WUH1-HL1-1.0 | J3: 花鲢1号 | K3: Φ | N3: 大类 | O3: 产线
A4: 湖南澳华农牧科技有限公司 | B4: 已启用 | C4: 2201020564 | D4: 贵妃宝Φ5.0 | E4: 2201020564 | F4: 普通膨化鱼料 | G4: 草鱼料 | H4: 鱼安康系列-草鱼安康 | I4: WUH1-GFB-5.0 | J4: 贵妃宝 | N4: 龙虾料 | O4: 虾蟹线
A5: 湖南澳华农牧科技有限公司 | B5: 已启用 | C5: 2201020566 | D5: 草鱼安康Φ2.0 | E5: 2201020566 | F5: 普通膨化鱼料 | G5: 草鱼料 | H5: 鱼安康系列-草鱼安康 | I5: WUH1-CYAK-2.0 | J5: 草鱼安康 | N5: 虾料 | O5: 虾蟹线
A6: 湖南澳华农牧科技有限公司 | B6: 已启用 | C6: 2201020567 | D6: 草鱼安康Φ3.0 | E6: 2201020567 | F6: 普通膨化鱼料 | G6: 草鱼料 | H6: 鱼安康系列-草鱼安康 | I6: WUH1-CYAK-3.0 | J6: 草鱼安康 | N6: 蟹料 | O6: 虾蟹线
A7: 湖南澳华农牧科技有限公司 | B7: 已启用 | C7: 2201020569 | D7: 淡水鱼1号料Φ2.0 | E7: 2201020569 | F7: 普通膨化鱼料 | G7: 草鱼料 | I7: WUH1-DSY1-2.0 | J7: 淡水鱼1号料 | N7: 海特料 | O7: 海特线
A8: 湖南澳华农牧科技有限公司 | B8: 已启用 | C8: 2201020570 | D8: 淡水鱼1号料Φ3.0 | E8: 2201020570 | F8: 普通膨化鱼料 | G8: 草鱼料 | I8: WUH1-DSY1-3.0 | J8: 淡水鱼1号料 | N8: 沉水鱼料 | O8: 鱼料线
A9: 湖南澳华农牧科技有限公司 | B9: 已停用 | C9: 2201020571 | D9: 淡水鱼1号料Φ5.0 | E9: 2201020571 | F9: 普通膨化鱼料 | G9: 草鱼料 | I9: WUH1-DSY1-5.0 | J9: 淡水鱼1号料 | N9: 普通膨化鱼料 | O9: 鱼料线
A10: 湖南澳华农牧科技有限公司 | B10: 已停用 | C10: 2201020576 | D10: 冬藏宝Φ3.0 | E10: 2201020576 | F10: 普通膨化鱼料 | G10: 四季料 | I10: WUH1-DSDCB-3.0 | J10: 冬藏宝 | N10: 反刍料 | O10: 畜禽线
A11: 湖南澳华农牧科技有限公司 | B11: 已启用 | C11: 2201020582 | D11: 混养2号Φ3.0 | E11: 2201020582 | F11: 普通膨化鱼料 | G11: 草鱼料 | I11: WUH1-HY2-3.0 | J11: 混养2号 | N11: 浓缩/预混料 | O11: 畜禽线
A12: 湖南澳华农牧科技有限公司 | B12: 已启用 | C12: 2201020316 | D12: 驯化宝Φ2.0 | E12: 2201020316 | F12: 普通膨化鱼料 | G12: 四季料 | H12: 无 | I12: HUN1-XHB-2.0 | J12: 驯化宝 | N12: 禽料 | O12: 畜禽线
A13: 湖南澳华农牧科技有限公司 | B13: 已启用 | C13: 2201020317 | D13: 驯化宝Φ3.0 | E13: 2201020317 | F13: 普通膨化鱼料 | G13: 四季料 | H13: 无 | I13: HUN1-XHB-3.0 | J13: 驯化宝 | N13: 猪饲料 | O13: 畜禽线
A14: 湖南澳华农牧科技有限公司 | B14: 已启用 | C14: 2201020322 | D14: 冬藏宝Φ3.0 | E14: 2201020322 | F14: 普通膨化鱼料 | G14: 四季料 | H14: 无 | I14: HUN1-DCB-3.0 | J14: 冬藏宝
A15: 湖南澳华农牧科技有限公司 | B15: 已启用 | C15: 2201020327 | D15: 膨化混养1号Φ3.0 | E15: 2201020327 | F15: 普通膨化鱼料 | G15: 草鱼料 | H15: 无 | I15: HUN1-PHHY1-3.0 | J15: 膨化混养1号
A16: 湖南澳华农牧科技有限公司 | B16: 已启用 | C16: 2201050001 | D16: 叉尾鮰2号Φ2.0 | E16: 2201050001 | F16: 普通膨化鱼料 | G16: 叉尾鮰料 | I16: ZJ1-CWH2-2.0 | J16: 叉尾鮰2号
A17: 湖南澳华农牧科技有限公司 | B17: 已启用 | C17: 2201050002 | D17: 叉尾鮰2号Φ3.0 | E17: 2201050002 | F17: 普通膨化鱼料 | G17: 叉尾鮰料 | I17: ZJ1-CWH2-3.0 | J17: 叉尾鮰2号
A18: 湖南澳华农牧科技有限公司 | B18: 已启用 | C18: 2201050008 | D18: 特种鱼苗料Φ1.0 | E18: 2201050008 | F18: 高档膨化鱼料 | G18: 鱼苗料 | I18: WUH1-TZYML-1.0 | J18: 特种鱼苗料
A19: 湖南澳华农牧科技有限公司 | B19: 已启用 | C19: 2201050009 | D19: 翘嘴安康Φ2.0 | E19: 2201050009 | F19: 高档膨化鱼料 | G19: 翘嘴料 | H19: 海特料-翘嘴安康 | I19: WUH1-QZAK-2.0 | J19: 翘嘴安康
A20: 湖南澳华农牧科技有限公司 | B20: 已启用 | C20: 2201050010 | D20: 翘嘴安康Φ3.0 | E20: 2201050010 | F20: 高档膨化鱼料 | G20: 翘嘴料 | H20: 海特料-翘嘴安康 | I20: WUH1-QZAK-3.0 | J20: 翘嘴安康
A21: 湖南澳华农牧科技有限公司 | B21: 已启用 | C21: 2201050011 | D21: 翘嘴安康Φ5.0 | E21: 2201050011 | F21: 高档膨化鱼料 | G21: 翘嘴料 | H21: 海特料-翘嘴安康 | I21: WUH1-QZAK-5.0 | J21: 翘嘴安康
A22: 湖南澳华农牧科技有限公司 | B22: 已启用 | C22: 2201050012 | D22: 鲌鱼2号Φ2.0 | E22: 2201050012 | F22: 高档膨化鱼料 | G22: 翘嘴料 | I22: WUH1-BY2H-2.0 | J22: 鲌鱼2号
A23: 湖南澳华农牧科技有限公司 | B23: 已启用 | C23: 2201050013 | D23: 鲌鱼2号Φ3.0 | E23: 2201050013 | F23: 高档膨化鱼料 | G23: 翘嘴料 | I23: WUH1-BY2H-3.0 | J23: 鲌鱼2号
A24: 湖南澳华农牧科技有限公司 | B24: 已启用 | C24: 2201050014 | D24: 鲌鱼2号Φ5.0 | E24: 2201050014 | F24: 高档膨化鱼料 | G24: 翘嘴料 | I24: WUH1-BY2H-5.0 | J24: 鲌鱼2号
A25: 湖南澳华农牧科技有限公司 | B25: 已停用 | C25: 2201020584 | D25: 渔家旺Φ2.0 | E25: 2201020584 | F25: 普通膨化鱼料 | G25: 草鱼料 | I25: WUH1-YJW-2.0 | J25: 渔家旺
A26: 湖南澳华农牧科技有限公司 | B26: 已启用 | C26: 2201020585 | D26: 渔家旺Φ3.0 | E26: 2201020585 | F26: 普通膨化鱼料 | G26: 草鱼料 | I26: WUH1-YJW-3.0 | J26: 渔家旺
A27: 湖南澳华农牧科技有限公司 | B27: 已停用 | C27: 2201020587 | D27: 驯化宝Φ2.0 | E27: 2201020587 | F27: 普通膨化鱼料 | G27: 四季料 | I27: WUH1-XHB-2.0 | J27: 驯化宝
A28: 湖南澳华农牧科技有限公司 | B28: 已停用 | C28: 2201020588 | D28: 驯化宝Φ3.0 | E28: 2201020588 | F28: 普通膨化鱼料 | G28: 四季料 | I28: WUH1-XHB-3.0 | J28: 驯化宝
A29: 湖南澳华农牧科技有限公司 | B29: 已停用 | C29: 2201020596 | D29: 淡水肝肠安康Ⅱ型Φ2.0 | E29: 2201020596 | F29: 普通膨化鱼料 | G29: 功能料 | H29: 功能料系列-肝肠安康 | I29: WUH1-DSGCAKⅡ-2.0 | J29: 淡水肝肠安康Ⅱ型
A30: 湖南澳华农牧科技有限公司 | B30: 已启用 | C30: 2201020698 | D30: 贵妃宝Φ3.0 | E30: 2201020698 | F30: 普通膨化鱼料 | G30: 草鱼料 | H30: 鱼安康系列-草鱼安康 | I30: WUH1-GFB-3.0 | J30: 贵妃宝
A31: 湖南澳华农牧科技有限公司 | B31: 已启用 | C31: 2201020722 | D31: 贵妃宝Φ2.0 | E31: 2201020722 | F31: 普通膨化鱼料 | G31: 草鱼料 | H31: 无 | I31: WUH1-GFB-2.0 | J31: 贵妃宝
A32: 湖南澳华农牧科技有限公司 | B32: 已启用 | C32: 2201100091 | D32: 叉尾鮰3号Φ2.0 | E32: 2201100091 | F32: 普通膨化鱼料 | G32: 叉尾鮰料 | I32: WUH1-CWH3-2.0 | J32: 叉尾鮰3号
A33: 湖南澳华农牧科技有限公司 | B33: 已启用 | C33: 2201100092 | D33: 叉尾鮰3号Φ3.0 | E33: 2201100092 | F33: 普通膨化鱼料 | G33: 叉尾鮰料 | I33: WUH1-CWH3-3.0 | J33: 叉尾鮰3号
A34: 湖南澳华农牧科技有限公司 | B34: 已启用 | C34: 2201100093 | D34: 叉尾鮰3号Φ5.0 | E34: 2201100093 | F34: 普通膨化鱼料 | G34: 叉尾鮰料 | I34: WUH1-CWH3-5.0 | J34: 叉尾鮰3号
A35: 湖南澳华农牧科技有限公司 | B35: 已启用 | C35: 2201100097 | D35: 叉尾安康Φ2.0 | E35: 2201100097 | F35: 普通膨化鱼料 | G35: 叉尾鮰料 | H35: 鱼安康系列-叉尾安康 | I35: WUH1-CWAK-2.0 | J35: 叉尾安康
A36: 湖南澳华农牧科技有限公司 | B36: 已启用 | C36: 2201100098 | D36: 叉尾安康Φ3.0 | E36: 2201100098 | F36: 普通膨化鱼料 | G36: 叉尾鮰料 | H36: 鱼安康系列-叉尾安康 | I36: WUH1-CWAK-3.0 | J36: 叉尾安康
A37: 湖南澳华农牧科技有限公司 | B37: 已启用 | C37: 2201100099 | D37: 叉尾安康Φ5.0 | E37: 2201100099 | F37: 普通膨化鱼料 | G37: 叉尾鮰料 | H37: 鱼安康系列-叉尾安康 | I37: WUH1-CWAK-5.0 | J37: 叉尾安康
A38: 湖南澳华农牧科技有限公司 | B38: 已启用 | C38: 2202010176 | D38: 青蛙1号AΦ1.5 | E38: 2202010176 | F38: 高档膨化鱼料 | G38: 蛙料 | H38: 无 | I38: WUH1-QW1A-1.5 | J38: 青蛙1号A
A39: 湖南澳华农牧科技有限公司 | B39: 已启用 | C39: 2202010179 | D39: 蛙粉A料Φ粉 | E39: 2202010179 | F39: 高档膨化鱼料 | G39: 蛙料 | H39: 无 | I39: WUH18-WFA-F | J39: 蛙粉A料
A40: 湖南澳华农牧科技有限公司 | B40: 已启用 | C40: 2202010183 | D40: 青蛙1号Φ1.5 | E40: 2202010183 | F40: 高档膨化鱼料 | G40: 蛙料 | H40: 无 | I40: WUH18-QW1-1.5 | J40: 青蛙1号
A41: 湖南澳华农牧科技有限公司 | B41: 已启用 | C41: 2202010184 | D41: 青蛙2号Φ2.0 | E41: 2202010184 | F41: 高档膨化鱼料 | G41: 蛙料 | H41: 无 | I41: WUH18-QW2-2.0 | J41: 青蛙2号
A42: 湖南澳华农牧科技有限公司 | B42: 已启用 | C42: 2202010185 | D42: 青蛙3号Φ3.0 | E42: 2202010185 | F42: 高档膨化鱼料 | G42: 蛙料 | H42: 无 | I42: WUH18-QW3-3.0 | J42: 青蛙3号
A43: 湖南澳华农牧科技有限公司 | B43: 已启用 | C43: 2202010187 | D43: 青蛙1号AΦ1.5 | E43: 2202010187 | F43: 高档膨化鱼料 | G43: 蛙料 | H43: 无 | I43: WUH18-QW1A-1.5 | J43: 青蛙1号A
A44: 湖南澳华农牧科技有限公司 | B44: 已启用 | C44: 2202010188 | D44: 青蛙2号AΦ2.0 | E44: 2202010188 | F44: 高档膨化鱼料 | G44: 蛙料 | H44: 无 | I44: WUH18-QW2A-2.0 | J44: 青蛙2号A
A45: 湖南澳华农牧科技有限公司 | B45: 已启用 | C45: 2202010189 | D45: 青蛙3号AΦ3.0 | E45: 2202010189 | F45: 高档膨化鱼料 | G45: 蛙料 | H45: 无 | I45: WUH18-QW3A-3.0 | J45: 青蛙3号A
A46: 湖南澳华农牧科技有限公司 | B46: 已停用 | C46: 2202010195 | D46: 8822Φ2.0 | E46: 2202010195 | F46: 高档膨化鱼料 | G46: 蛙料 | H46: 无 | I46: WUH2-8822-2.0 | J46: 8822
... A75: 湖南澳华农牧科技有限公司 | B75: 已启用 | C75: 2202040113 | D75: 黄颡鱼料Φ粉 | E75: 2202040113 | F75: 高档膨化鱼料 | G75: 黄颡鱼料 | H75: 无 | I75: ZJ1-HSYL-F | J75: 黄颡鱼料
B76: 已启用 | C76: 2202030008 | D76: 加州安康2号Φ2.0 | E76: 2202030008 | F76: 高档膨化鱼料 | G76: 加州鲈鱼料 | H76: 海特料-加州安康 | I76: JM1-JZAK2-2.0 | J76: 加州安康2号
B77: 已启用 | C77: 2202040128 | D77: 铂金黄颡安康Φ1.5 | E77: 2202040128 | F77: 高档膨化鱼料 | G77: 黄颡鱼料 | H77: 海特料-黄颡安康 | I77: WUH1-BJHSAK-1.5 | J77: 铂金黄颡安康
B78: 已启用 | C78: 2202040129 | D78: 铂金黄颡安康Φ2.0 | E78: 2202040129 | F78: 高档膨化鱼料 | G78: 黄颡鱼料 | H78: 海特料-黄颡安康 | I78: WUH1-BJHSAK-2.0 | J78: 铂金黄颡安康
B79: 已启用 | C79: 2202040140 | D79: 铂金黄颡安康Φ1.0 | E79: 2202040140 | F79: 高档膨化鱼料 | G79: 黄颡鱼料 | H79: 海特料-黄颡安康 | I79: WUH1-BJHSAK-1.0 | J79: 铂金黄颡安康
B80: 已启用 | C80: 2202030081 | D80: 鱼宝宝Φ0.5 | E80: 2202030081 | F80: 高档膨化鱼料 | G80: 加州鲈鱼料 | H80: 海特料-加州鲈料 | I80: JM1-YBB-0.5 | J80: 鱼宝宝
B81: 已启用 | C81: 2202030124 | D81: 加州鲈安康3号Φ3.0 | E81: 2202030124 | F81: 高档膨化鱼料 | G81: 加州鲈鱼料 | H81: 海特料-加州鲈安康 | I81: WUH1-JZLAK3-3.0 | J81: 加州鲈安康3号
B82: 已启用 | C82: 2202030125 | D82: 加州鲈安康4号Φ4.0 | E82: 2202030125 | F82: 高档膨化鱼料 | G82: 加州鲈鱼料 | H82: 海特料-加州鲈安康 | I82: WUH1-JZLAK4-4.0 | J82: 加州鲈安康4号
B83: 已启用 | C83: 2202030126 | D83: 加州鲈安康5号Φ5.0 | E83: 2202030126 | F83: 高档膨化鱼料 | G83: 加州鲈鱼料 | H83: 海特料-加州鲈安康 | I83: WUH1-JZLAK5-5.0 | J83: 加州鲈安康5号
B84: 已启用 | C84: 2202030127 | D84: 加州鲈安康6号Φ6.0 | E84: 2202030127 | F84: 高档膨化鱼料 | G84: 加州鲈鱼料 | H84: 海特料-加州鲈安康 | I84: WUH1-JZLAK6-6.0 | J84: 加州鲈安康6号
B85: 已启用 | C85: 2202030128 | D85: 加州鲈安康7号Φ7.0 | E85: 2202030128 | F85: 高档膨化鱼料 | G85: 加州鲈鱼料 | H85: 海特料-加州鲈安康 | I85: WUH1-JZLAK7-7.0 | J85: 加州鲈安康7号
A86: 湖南澳华农牧科技有限公司 | B86: 已停用 | C86: 2202030130 | D86: 铂金加州鲈安康1号Φ1.0 | E86: 2202030130 | F86: 高档膨化鱼料 | G86: 加州鲈鱼料 | H86: 海特料-铂金版加州安康 | I86: WUH1-BJJZLAK1-1.0 | J86: 铂金加州鲈安康1号
A87: 湖南澳华农牧科技有限公司 | B87: 已启用 | C87: 2202030131 | D87: 铂金加州鲈安康2号Φ2.0 | E87: 2202030131 | F87: 高档膨化鱼料 | G87: 加州鲈鱼料 | H87: 海特料-铂金版加州安康 | I87: WUH1-BJJZLAK2-2.0 | J87: 铂金加州鲈安康2号
A88: 湖南澳华农牧科技有限公司 | B88: 已启用 | C88: 2202030132 | D88: 铂金加州鲈安康3号Φ3.0 | E88: 2202030132 | F88: 高档膨化鱼料 | G88: 加州鲈鱼料 | H88: 海特料-铂金版加州安康 | I88: WUH1-BJJZLAK3-3.0 | J88: 铂金加州鲈安康3号
A89: 湖南澳华农牧科技有限公司 | B89: 已启用 | C89: 2202030133 | D89: 铂金加州鲈安康4号Φ4.0 | E89: 2202030133 | F89: 高档膨化鱼料 | G89: 加州鲈鱼料 | H89: 海特料-铂金版加州安康 | I89: WUH1-BJJZLAK4-4.0 | J89: 铂金加州鲈安康4号
A90: 湖南澳华农牧科技有限公司 | B90: 已启用 | C90: 2202030134 | D90: 铂金加州鲈安康5号Φ5.0 | E90: 2202030134 | F90: 高档膨化鱼料 | G90: 加州鲈鱼料 | H90: 海特料-铂金版加州安康 | I90: WUH1-BJJZLAK5-5.0 | J90: 铂金加州鲈安康5号
A91: 湖南澳华农牧科技有限公司 | B91: 已启用 | C91: 2202030135 | D91: 铂金加州鲈安康6号Φ6.0 | E91: 2202030135 | F91: 高档膨化鱼料 | G91: 加州鲈鱼料 | H91: 海特料-铂金版加州安康 | I91: WUH1-BJJZLAK6-6.0 | J91: 铂金加州鲈安康6号
A92: 湖南澳华农牧科技有限公司 | B92: 已启用 | C92: 2202030136 | D92: 铂金加州鲈安康7号Φ7.0 | E92: 2202030136 | F92: 高档膨化鱼料 | G92: 加州鲈鱼料 | H92: 海特料-铂金版加州安康 | I92: WUH1-BJJZLAK7-7.0 | J92: 铂金加州鲈安康7号
A93: 湖南澳华农牧科技有限公司 | B93: 已启用 | C93: 2202080006 | D93: 黄鳝鱼1号Φ1.5 | E93: 2202080006 | F93: 高档膨化鱼料 | G93: 黄鳝鱼料 | H93: 无 | I93: WUH1-HSHY1-1.5 | J93: 黄鳝鱼1号
A94: 湖南澳华农牧科技有限公司 | B94: 已启用 | C94: 2202330032 | D94: 牛蛙0号Φ1.0 | E94: 2202330032 | F94: 高档膨化鱼料 | G94: 牛蛙料 | H94: 无 | I94: HUN1-NW0-1.0 | J94: 牛蛙0号
A95: 湖南澳华农牧科技有限公司 | B95: 已启用 | C95: 2202330033 | D95: 牛蛙1号Φ1.5 | E95: 2202330033 | F95: 高档膨化鱼料 | G95: 牛蛙料 | H95: 无 | I95: HUN1-NW1-1.5 | J95: 牛蛙1号
A96: 湖南澳华农牧科技有限公司 | B96: 已启用 | C96: 2202330034 | D96: 牛蛙2号Φ2.0 | E96: 2202330034 | F96: 高档膨化鱼料 | G96: 牛蛙料 | H96: 无 | I96: HUN1-NW2-2.0 | J96: 牛蛙2号
B97: 已启用 | C97: 2202130015 | D97: 优力肽Φ2.0 | E97: 2202130015 | F97: 高档膨化鱼料 | G97: 生物料 | H97: 无 | I97: WUH1-YLT-2.0 | J97: 优力肽
B98: 已启用 | C98: 2203030052 | D98: 鳊鱼专用料621Φ2.0 | E98: 2203030052 | F98: 沉水鱼料 | G98: 鳊鱼料 | I98: WUH1-621-2.0 | J98: 鳊鱼专用料621
A99: 湖南澳华农牧科技有限公司 | B99: 已启用 | C99: 2203030053 | D99: 鳊鱼专用料621Φ2.5 | E99: 2203030053 | F99: 沉水鱼料 | G99: 鳊鱼料 | I99: WUH1-621-2.5 | J99: 鳊鱼专用料621
A100: 湖南澳华农牧科技有限公司 | B100: 已停用 | C100: 2203030054 | D100: 鳊鱼专用料621Φ3.0 | E100: 2203030054 | F100: 沉水鱼料 | G100: 鳊鱼料 | I100: WUH1-621-3.0 | J100: 鳊鱼专用料621
A101: 湖南澳华农牧科技有限公司 | B101: 已启用 | C101: 2203040028 | D101: 膨化混养1号Φ2.0 | E101: 2203040028 | F101: 普通膨化鱼料 | G101: 草鱼料 | H101: 无 | I101: HUN1-PHHY1-2.0 | J101: 膨化混养1号
A102: 湖南澳华农牧科技有限公司 | B102: 已停用 | C102: 2203010205 | D102: 混养鱼料610Φ小碎 | E102: 2203010205 | F102: 沉水鱼料 | G102: 草鱼料 | I102: WUH1-610-XS | J102: 混养鱼料610
A103: 湖南澳华农牧科技有限公司 | B103: 已启用 | C103: 2203010206 | D103: 混养鱼料610Φ大碎 | E103: 2203010206 | F103: 沉水鱼料 | G103: 草鱼料 | I103: WUH1-610-DS | J103: 混养鱼料610
A104: 湖南澳华农牧科技有限公司 | B104: 已启用 | C104: 2203010207 | D104: 混养鱼料610Φ1.5 | E104: 2203010207 | F104: 沉水鱼料 | G104: 草鱼料 | I104: WUH1-610-1.5 | J104: 混养鱼料610
A105: 湖南澳华农牧科技有限公司 | B105: 已启用 | C105: 2203010208 | D105: 混养鱼料610Φ2.0 | E105: 2203010208 | F105: 沉水鱼料 | G105: 草鱼料 | I105: WUH1-610-2.0 | J105: 混养鱼料610
A106: 湖南澳华农牧科技有限公司 | B106: 已启用 | C106: 2203010209 | D106: 混养鱼料610Φ2.5 | E106: 2203010209 | F106: 沉水鱼料 | G106: 草鱼料 | I106: WUH1-610-2.5 | J106: 混养鱼料610
A107: 湖南澳华农牧科技有限公司 | B107: 已启用 | C107: 2203010210 | D107: 混养鱼料610Φ3.0 | E107: 2203010210 | F107: 沉水鱼料 | G107: 草鱼料 | I107: WUH1-610-3.0 | J107: 混养鱼料610
A108: 湖南澳华农牧科技有限公司 | B108: 已启用 | C108: 2203010211 | D108: 混养鱼料610Φ4.0 | E108: 2203010211 | F108: 沉水鱼料 | G108: 草鱼料 | I108: WUH1-610-4.0 | J108: 混养鱼料610
A109: 湖南澳华农牧科技有限公司 | B109: 已启用 | C109: 2203010218 | D109: 混养鱼料618Φ2.0 | E109: 2203010218 | F109: 沉水鱼料 | G109: 草鱼料 | H109: 618高端颗粒鱼料 | I109: WUH1-618-2.0 | J109: 混养鱼料618
A110: 湖南澳华农牧科技有限公司 | B110: 已启用 | C110: 2203010219 | D110: 混养鱼料618Φ2.5 | E110: 2203010219 | F110: 沉水鱼料 | G110: 草鱼料 | H110: 618高端颗粒鱼料 | I110: WUH1-618-2.5 | J110: 混养鱼料618
A111: 湖南澳华农牧科技有限公司 | B111: 已启用 | C111: 2203010220 | D111: 混养鱼料618Φ3.0 | E111: 2203010220 | F111: 沉水鱼料 | G111: 草鱼料 | H111: 618高端颗粒鱼料 | I111: WUH1-618-3.0 | J111: 混养鱼料618
A112: 湖南澳华农牧科技有限公司 | B112: 已启用 | C112: 2203010235 | D112: 叉尾鮰料661Φ3.0 | E112: 2203010235 | F112: 沉水鱼料 | G112: 叉尾鮰料 | I112: WUH1-661-3.0 | J112: 叉尾鮰料661
A113: 湖南澳华农牧科技有限公司 | B113: 已停用 | C113: 2203010241 | D113: 肝肠宝Ⅱ型Φ2.0 | E113: 2203010241 | F113: 沉水鱼料 | G113: 功能料 | H113: 功能料系列-肝肠宝 | I113: WUH1-GCBⅡ-2.0 | J113: 肝肠宝Ⅱ型
A114: 湖南澳华农牧科技有限公司 | B114: 已停用 | C114: 2203010243 | D114: 肝肠宝Ⅱ型Φ3.0 | E114: 2203010243 | F114: 沉水鱼料 | G114: 功能料 | H114: 功能料系列-肝肠宝 | I114: WUH1-GCBⅡ-3.0 | J114: 肝肠宝Ⅱ型
A115: 湖南澳华农牧科技有限公司 | B115: 已启用 | C115: 2203010245 | D115: 花鲢宝Φ粉 | E115: 2203010245 | F115: 沉水鱼料 | G115: 鳊鱼料 | I115: WUH1-HLB-F | J115: 花鲢宝
A116: 湖南澳华农牧科技有限公司 | B116: 已启用 | C116: 2203010327 | D116: 鲲丰宝Φ3.0 | E116: 2203010327 | F116: 沉水鱼料 | G116: 草鱼料 | H116: 618高端颗粒鱼料 | I116: WUH1-KFB-3.0 | J116: 鲲丰宝
B117: 已启用 | C117: 2203010328 | D117: 鲲丰宝Φ4.0 | E117: 2203010328 | F117: 沉水鱼料 | G117: 草鱼料 | H117: 618高端颗粒鱼料 | I117: WUH1-KFB-4.0 | J117: 鲲丰宝
B118: 已启用 | C118: 2203010337 | D118: 澳冬宝Φ2.0 | E118: 2203010337 | F118: 沉水鱼料 | G118: 草鱼料 | H118: 无 | I118: WUH1-ADB-2.0 | J118: 澳冬宝
B119: 已启用 | C119: 2203010338 | D119: 澳冬宝Φ3.0 | E119: 2203010338 | F119: 沉水鱼料 | G119: 草鱼料 | H119: 无 | I119: WUH1-ADB-3.0 | J119: 澳冬宝
A120: 湖南澳华农牧科技有限公司 | B120: 已启用 | C120: 2203010339 | D120: 混养成鱼料610Φ粉 | E120: 2203010339 | F120: 沉水鱼料 | G120: 草鱼料 | H120: 无 | I120: WH1-610-F | J120: 混养成鱼料610
A121: 湖南澳华农牧科技有限公司 | B121: 已启用 | C121: 2203040350 | D121: 混养成鱼料610Φ粉 | E121: 2203040350 | F121: 沉水鱼料 | G121: 草鱼料 | I121: JX1-610-F | J121: 混养成鱼料610
A122: 湖南澳华农牧科技有限公司 | B122: 已启用 | C122: 2203040391 | D122: 混养鱼料610Φ粉 | E122: 2203040391 | F122: 沉水鱼料 | G122: 混养料 | H122: 无 | I122: WUH1-610-F | J122: 混养鱼料610
A123: 湖南澳华农牧科技有限公司 | B123: 已启用 | C123: 2203100015 | D123: 叉尾鮰料662Φ2.0 | E123: 2203100015 | F123: 沉水鱼料 | G123: 叉尾鮰料 | H123: 无 | I123: WUH1-662-2.0 | J123: 叉尾鮰料662
A124: 湖南澳华农牧科技有限公司 | B124: 已停用 | C124: 2203100016 | D124: 叉尾鮰料662Φ2.5 | E124: 2203100016 | F124: 沉水鱼料 | G124: 叉尾鮰料 | H124: 无 | I124: WUH1-662-2.5 | J124: 叉尾鮰料662
A125: 湖南澳华农牧科技有限公司 | B125: 已启用 | C125: 2203100017 | D125: 叉尾鮰料662Φ3.0 | E125: 2203100017 | F125: 沉水鱼料 | G125: 叉尾鮰料 | H125: 无 | I125: WUH1-662-3.0 | J125: 叉尾鮰料662
A126: 湖南澳华农牧科技有限公司 | B126: 已启用 | C126: 2203100018 | D126: 叉尾鮰料662Φ4.0 | E126: 2203100018 | F126: 沉水鱼料 | G126: 叉尾鮰料 | H126: 无 | I126: WUH1-662-4.0 | J126: 叉尾鮰料662
A127: 湖南澳华农牧科技有限公司 | B127: 已启用 | C127: 2203110008 | D127: 鱼苗宝3号Φ1.0 | E127: 2203110008 | F127: 普通膨化鱼料 | G127: 鱼苗料 | H127: 鱼安康系列-鱼安康 | I127: JX1-YMB3-1.0 | J127: 鱼苗宝3号
A128: 湖南澳华农牧科技有限公司 | B128: 已启用 | C128: 2203120004 | D128: 鳊鱼专用料621Φ1.5 | E128: 2203120004 | F128: 沉水鱼料 | G128: 鳊鱼料 | H128: 无 | I128: WUH1-621-1.5 | J128: 鳊鱼专用料621
...

Sheet A5 表样-聚焦镇量利（查阅）
A1: ← 返回目录
A2: 大区 | B2: 公司 | C2: 聚焦镇名称 | D2: 聚焦镇类型 | E2: 销量 | U2: 毛利额
E3: 2025年销量 | F3: 2026年销量 | G3: 同比增加额 | H3: 同比增长率 | I3: 2026年月度销量 | U3: 2025年毛利额 | V3: 2026年毛利额 | W3: 同比增加额 | X3: 同比增长率 | Y3: 2026年月度毛利额
I4: 1月 | J4: 2月 | K4: 3月 | L4: 4月 | M4: 5月 | N4: 6月 | O4: 7月 | P4: 8月 | Q4: 9月 | R4: 10月 | S4: 11月 | T4: 12月 | Y4: 1月 | Z4: 2月 | AA4: 3月 | AB4: 4月 | AC4: 5月 | AD4: 6月 | AE4: 7月 | AF4: 8月 | AG4: 9月 | AH4: 10月 | AI4: 11月 | AJ4: 12月
A5: ='[3]A1 预算指标总览'!$A$3 -> 华东一区 | B5: ='[3]A1 预算指标总览'!$B$3 -> 福建公司 | E5: 本表计算 | F5: 计算 | G5: 本表计算 | H5: 本表计算 | I5: 计算 | J5: 计算 | K5: 计算 | L5: 计算 | M5: 计算 | N5: 计算 | O5: 计算 | P5: 计算 | Q5: 计算 | R5: 计算 | S5: 计算 | T5: 计算 | U5: 本表计算 | V5: 计算 | W5: 本表计算 | X5: 本表计算 | Y5: 计算 | Z5: 计算 | AA5: 计算 | AB5: 计算 | AC5: 计算 | AD5: 计算 | AE5: 计算 | AF5: 计算 | AG5: 计算 | AH5: 计算 | AI5: 计算 | AJ5: 计算
A6: ='[3]A1 预算指标总览'!$A$3 -> 华东一区 | B6: ='[3]A1 预算指标总览'!$B$3 -> 福建公司 | E6: 本表计算 | F6: 计算 | G6: 本表计算 | H6: 本表计算 | I6: 计算 | J6: 计算 | K6: 计算 | L6: 计算 | M6: 计算 | N6: 计算 | O6: 计算 | P6: 计算 | Q6: 计算 | R6: 计算 | S6: 计算 | T6: 计算 | U6: 本表计算 | V6: 计算 | W6: 本表计算 | X6: 本表计算 | Y6: 计算 | Z6: 计算 | AA6: 计算 | AB6: 计算 | AC6: 计算 | AD6: 计算 | AE6: 计算 | AF6: 计算 | AG6: 计算 | AH6: 计算 | AI6: 计算 | AJ6: 计算
A7: ='[3]A1 预算指标总览'!$A$3 -> 华东一区 | B7: ='[3]A1 预算指标总览'!$B$3 -> 福建公司 | E7: 本表计算 | F7: 计算 | G7: 本表计算 | H7: 本表计算 | I7: 计算 | J7: 计算 | K7: 计算 | L7: 计算 | M7: 计算 | N7: 计算 | O7: 计算 | P7: 计算 | Q7: 计算 | R7: 计算 | S7: 计算 | T7: 计算 | U7: 本表计算 | V7: 计算 | W7: 本表计算 | X7: 本表计算 | Y7: 计算 | Z7: 计算 | AA7: 计算 | AB7: 计算 | AC7: 计算 | AD7: 计算 | AE7: 计算 | AF7: 计算 | AG7: 计算 | AH7: 计算 | AI7: 计算 | AJ7: 计算
A8: ='[3]A1 预算指标总览'!$A$3 -> 华东一区 | B8: ='[3]A1 预算指标总览'!$B$3 -> 福建公司 | E8: 本表计算 | F8: 计算 | G8: 本表计算 | H8: 本表计算 | I8: 计算 | J8: 计算 | K8: 计算 | L8: 计算 | M8: 计算 | N8: 计算 | O8: 计算 | P8: 计算 | Q8: 计算 | R8: 计算 | S8: 计算 | T8: 计算 | U8: 本表计算 | V8: 计算 | W8: 本表计算 | X8: 本表计算 | Y8: 计算 | Z8: 计算 | AA8: 计算 | AB8: 计算 | AC8: 计算 | AD8: 计算 | AE8: 计算 | AF8: 计算 | AG8: 计算 | AH8: 计算 | AI8: 计算 | AJ8: 计算
A9: ='[3]A1 预算指标总览'!$A$3 -> 华东一区 | B9: ='[3]A1 预算指标总览'!$B$3 -> 福建公司 | E9: 本表计算 | F9: 计算 | G9: 本表计算 | H9: 本表计算 | I9: 计算 | J9: 计算 | K9: 计算 | L9: 计算 | M9: 计算 | N9: 计算 | O9: 计算 | P9: 计算 | Q9: 计算 | R9: 计算 | S9: 计算 | T9: 计算 | U9: 本表计算 | V9: 计算 | W9: 本表计算 | X9: 本表计算 | Y9: 计算 | Z9: 计算 | AA9: 计算 | AB9: 计算 | AC9: 计算 | AD9: 计算 | AE9: 计算 | AF9: 计算 | AG9: 计算 | AH9: 计算 | AI9: 计算 | AJ9: 计算
A10: ='[3]A1 预算指标总览'!$A$3 -> 华东一区 | B10: ='[3]A1 预算指标总览'!$B$3 -> 福建公司 | E10: 本表计算 | F10: 计算 | G10: 本表计算 | H10: 本表计算 | I10: 计算 | J10: 计算 | K10: 计算 | L10: 计算 | M10: 计算 | N10: 计算 | O10: 计算 | P10: 计算 | Q10: 计算 | R10: 计算 | S10: 计算 | T10: 计算 | U10: 本表计算 | V10: 计算 | W10: 本表计算 | X10: 本表计算 | Y10: 计算 | Z10: 计算 | AA10: 计算 | AB10: 计算 | AC10: 计算 | AD10: 计算 | AE10: 计算 | AF10: 计算 | AG10: 计算 | AH10: 计算 | AI10: 计算 | AJ10: 计算
A11: ='[3]A1 预算指标总览'!$A$3 -> 华东一区 | B11: ='[3]A1 预算指标总览'!$B$3 -> 福建公司 | E11: 本表计算 | F11: 计算 | G11: 本表计算 | H11: 本表计算 | I11: 计算 | J11: 计算 | K11: 计算 | L11: 计算 | M11: 计算 | N11: 计算 | O11: 计算 | P11: 计算 | Q11: 计算 | R11: 计算 | S11: 计算 | T11: 计算 | U11: 本表计算 | V11: 计算 | W11: 本表计算 | X11: 本表计算 | Y11: 计算 | Z11: 计算 | AA11: 计算 | AB11: 计算 | AC11: 计算 | AD11: 计算 | AE11: 计算 | AF11: 计算 | AG11: 计算 | AH11: 计算 | AI11: 计算 | AJ11: 计算
A12: ='[3]A1 预算指标总览'!$A$3 -> 华东一区 | B12: ='[3]A1 预算指标总览'!$B$3 -> 福建公司 | E12: 本表计算 | F12: 计算 | G12: 本表计算 | H12: 本表计算 | I12: 计算 | J12: 计算 | K12: 计算 | L12: 计算 | M12: 计算 | N12: 计算 | O12: 计算 | P12: 计算 | Q12: 计算 | R12: 计算 | S12: 计算 | T12: 计算 | U12: 本表计算 | V12: 计算 | W12: 本表计算 | X12: 本表计算 | Y12: 计算 | Z12: 计算 | AA12: 计算 | AB12: 计算 | AC12: 计算 | AD12: 计算 | AE12: 计算 | AF12: 计算 | AG12: 计算 | AH12: 计算 | AI12: 计算 | AJ12: 计算
A13: ='[3]A1 预算指标总览'!$A$3 -> 华东一区 | B13: ='[3]A1 预算指标总览'!$B$3 -> 福建公司 | E13: 本表计算 | F13: 计算 | G13: 本表计算 | H13: 本表计算 | I13: 计算 | J13: 计算 | K13: 计算 | L13: 计算 | M13: 计算 | N13: 计算 | O13: 计算 | P13: 计算 | Q13: 计算 | R13: 计算 | S13: 计算 | T13: 计算 | U13: 本表计算 | V13: 计算 | W13: 本表计算 | X13: 本表计算 | Y13: 计算 | Z13: 计算 | AA13: 计算 | AB13: 计算 | AC13: 计算 | AD13: 计算 | AE13: 计算 | AF13: 计算 | AG13: 计算 | AH13: 计算 | AI13: 计算 | AJ13: 计算
A14: ='[3]A1 预算指标总览'!$A$3 -> 华东一区 | B14: ='[3]A1 预算指标总览'!$B$3 -> 福建公司 | E14: 本表计算 | F14: 计算 | G14: 本表计算 | H14: 本表计算 | I14: 计算 | J14: 计算 | K14: 计算 | L14: 计算 | M14: 计算 | N14: 计算 | O14: 计算 | P14: 计算 | Q14: 计算 | R14: 计算 | S14: 计算 | T14: 计算 | U14: 本表计算 | V14: 计算 | W14: 本表计算 | X14: 本表计算 | Y14: 计算 | Z14: 计算 | AA14: 计算 | AB14: 计算 | AC14: 计算 | AD14: 计算 | AE14: 计算 | AF14: 计算 | AG14: 计算 | AH14: 计算 | AI14: 计算 | AJ14: 计算
A15: ='[3]A1 预算指标总览'!$A$3 -> 华东一区 | B15: ='[3]A1 预算指标总览'!$B$3 -> 福建公司 | E15: 本表计算 | F15: 计算 | G15: 本表计算 | H15: 本表计算 | I15: 计算 | J15: 计算 | K15: 计算 | L15: 计算 | M15: 计算 | N15: 计算 | O15: 计算 | P15: 计算 | Q15: 计算 | R15: 计算 | S15: 计算 | T15: 计算 | U15: 本表计算 | V15: 计算 | W15: 本表计算 | X15: 本表计算 | Y15: 计算 | Z15: 计算 | AA15: 计算 | AB15: 计算 | AC15: 计算 | AD15: 计算 | AE15: 计算 | AF15: 计算 | AG15: 计算 | AH15: 计算 | AI15: 计算 | AJ15: 计算
A16: ='[3]A1 预算指标总览'!$A$3 -> 华东一区 | B16: ='[3]A1 预算指标总览'!$B$3 -> 福建公司 | E16: 本表计算 | F16: 计算 | G16: 本表计算 | H16: 本表计算 | I16: 计算 | J16: 计算 | K16: 计算 | L16: 计算 | M16: 计算 | N16: 计算 | O16: 计算 | P16: 计算 | Q16: 计算 | R16: 计算 | S16: 计算 | T16: 计算 | U16: 本表计算 | V16: 计算 | W16: 本表计算 | X16: 本表计算 | Y16: 计算 | Z16: 计算 | AA16: 计算 | AB16: 计算 | AC16: 计算 | AD16: 计算 | AE16: 计算 | AF16: 计算 | AG16: 计算 | AH16: 计算 | AI16: 计算 | AJ16: 计算
... A34: ='[3]A1 预算指标总览'!$A$3 -> 华东一区 | B34: ='[3]A1 预算指标总览'!$B$3 -> 福建公司 | E34: 本表计算 | F34: 计算 | G34: 本表计算 | H34: 本表计算 | I34: 计算 | J34: 计算 | K34: 计算 | L34: 计算 | M34: 计算 | N34: 计算 | O34: 计算 | P34: 计算 | Q34: 计算 | R34: 计算 | S34: 计算 | T34: 计算 | U34: 本表计算 | V34: 计算 | W34: 本表计算 | X34: 本表计算 | Y34: 计算 | Z34: 计算 | AA34: 计算 | AB34: 计算 | AC34: 计算 | AD34: 计算 | AE34: 计算 | AF34: 计算 | AG34: 计算 | AH34: 计算 | AI34: 计算 | AJ34: 计算
A35: ='[3]A1 预算指标总览'!$A$3 -> 华东一区 | B35: ='[3]A1 预算指标总览'!$B$3 -> 福建公司 | C35: 合计 | E35: 本表计算 | F35: 本表计算 | G35: 本表计算 | H35: 本表计算 | I35: 本表计算 | J35: 本表计算 | K35: 本表计算 | L35: 本表计算 | M35: 本表计算 | N35: 本表计算 | O35: 本表计算 | P35: 本表计算 | Q35: 本表计算 | R35: 本表计算 | S35: 本表计算 | T35: 本表计算 | U35: 本表计算 | V35: 本表计算 | W35: 本表计算 | X35: 本表计算 | Y35: 本表计算 | Z35: 本表计算 | AA35: 本表计算 | AB35: 本表计算 | AC35: 本表计算 | AD35: 本表计算 | AE35: 本表计算 | AF35: 本表计算 | AG35: 本表计算 | AH35: 本表计算 | AI35: 本表计算 | AJ35: 本表计算

Sheet A6 表样-大类量利（查阅）
A1: ← 返回目录
A2: 大区 | B2: 公司 | C2: 大类 | D2: 2026年全年预算值 | K2: 2025年实际值 | R2: 同比增长（预算-同比）
D3: 销量 | E3: 主营业务收入 | F3: 毛利额 | G3: 吨毛利 | H3: 毛利率 | I3: 配销差额 | J3: 吨配销差 | K3: 销量 | L3: 主营业务收入 | M3: 毛利额 | N3: 吨毛利 | O3: 毛利率 | P3: 配销差额 | Q3: 吨配销差 | R3: 销量 | S3: 主营业务收入 | T3: 毛利额 | U3: 吨毛利 | V3: 毛利率 | W3: 配销差额 | X3: 吨配销差
C4: 虾料 | D4: 计算 | E4: 计算 | F4: 计算 | G4: 本表计算 | H4: 本表计算 | K4: 计算 | L4: 计算 | M4: 计算 | N4: 本表计算 | O4: 本表计算 | R4: 本表计算 | S4: 本表计算 | T4: 本表计算 | U4: 本表计算 | V4: 本表计算
C5: 龙虾料 | D5: 计算 | E5: 计算 | F5: 计算 | G5: 本表计算 | H5: 本表计算 | K5: 计算 | L5: 计算 | M5: 计算 | N5: 本表计算 | O5: 本表计算 | R5: 本表计算 | S5: 本表计算 | T5: 本表计算 | U5: 本表计算 | V5: 本表计算
C6: 蟹料 | D6: 计算 | E6: 计算 | F6: 计算 | G6: 本表计算 | H6: 本表计算 | K6: 计算 | L6: 计算 | M6: 计算 | N6: 本表计算 | O6: 本表计算 | R6: 本表计算 | S6: 本表计算 | T6: 本表计算 | U6: 本表计算 | V6: 本表计算
C7: 其中：高价值虾蟹 | D7: 计算 | E7: 计算 | F7: 计算 | G7: 本表计算 | H7: 本表计算 | K7: 计算 | L7: 计算 | M7: 计算 | N7: 本表计算 | O7: 本表计算 | R7: 本表计算 | S7: 本表计算 | T7: 本表计算 | U7: 本表计算 | V7: 本表计算
C8: 普通膨化鱼料 | D8: 计算 | E8: 计算 | F8: 计算 | G8: 本表计算 | H8: 本表计算 | K8: 计算 | L8: 计算 | M8: 计算 | N8: 本表计算 | O8: 本表计算 | R8: 本表计算 | S8: 本表计算 | T8: 本表计算 | U8: 本表计算 | V8: 本表计算
C9: 沉水鱼料 | D9: 计算 | E9: 计算 | F9: 计算 | G9: 本表计算 | H9: 本表计算 | K9: 计算 | L9: 计算 | M9: 计算 | N9: 本表计算 | O9: 本表计算 | R9: 本表计算 | S9: 本表计算 | T9: 本表计算 | U9: 本表计算 | V9: 本表计算
C10: 其中：高价值鱼料 | D10: 计算 | E10: 计算 | F10: 计算 | G10: 本表计算 | H10: 本表计算 | K10: 计算 | L10: 计算 | M10: 计算 | N10: 本表计算 | O10: 本表计算 | R10: 本表计算 | S10: 本表计算 | T10: 本表计算 | U10: 本表计算 | V10: 本表计算
C11: 海特料 | D11: 计算 | E11: 计算 | F11: 计算 | G11: 本表计算 | H11: 本表计算 | K11: 计算 | L11: 计算 | M11: 计算 | N11: 本表计算 | O11: 本表计算 | R11: 本表计算 | S11: 本表计算 | T11: 本表计算 | U11: 本表计算 | V11: 本表计算
C12: 其中：高价值产品 | D12: 计算 | E12: 计算 | F12: 计算 | G12: 本表计算 | H12: 本表计算 | K12: 计算 | L12: 计算 | M12: 计算 | N12: 本表计算 | O12: 本表计算 | R12: 本表计算 | S12: 本表计算 | T12: 本表计算 | U12: 本表计算 | V12: 本表计算
C13: 水产小计 | D13: 本表计算 | E13: 本表计算 | F13: 本表计算 | G13: 本表计算 | H13: 本表计算 | K13: 本表计算 | L13: 本表计算 | M13: 本表计算 | N13: 本表计算 | O13: 本表计算 | R13: 本表计算 | S13: 本表计算 | T13: 本表计算 | U13: 本表计算 | V13: 本表计算
C14: 猪饲料 | D14: 计算 | E14: 计算 | F14: 计算 | G14: 本表计算 | H14: 本表计算 | K14: 计算 | L14: 计算 | M14: 计算 | N14: 本表计算 | O14: 本表计算 | R14: 本表计算 | S14: 本表计算 | T14: 本表计算 | U14: 本表计算 | V14: 本表计算
C15: 浓缩/预混料 | D15: 计算 | E15: 计算 | F15: 计算 | G15: 本表计算 | H15: 本表计算 | K15: 计算 | L15: 计算 | M15: 计算 | N15: 本表计算 | O15: 本表计算 | R15: 本表计算 | S15: 本表计算 | T15: 本表计算 | U15: 本表计算 | V15: 本表计算
... C23: 其中：高价值占比 | D23: 本表计算 | E23: 本表计算 | F23: 本表计算 | G23: 本表计算 | H23: 本表计算 | K23: 本表计算 | L23: 本表计算 | M23: 本表计算 | N23: 本表计算 | O23: 本表计算 | R23: 本表计算 | S23: 本表计算 | T23: 本表计算 | U23: 本表计算 | V23: 本表计算

Sheet A7 大类小类量利（查阅）
A1: ← 返回目录
B2: 大区 | C2: 公司 | D2: 大类 | E2: 小类 | F2: 2026年预算 | K2: 2025年实际值 | P2: 同比增长（预测-同比）
F3: 销量 | G3: 毛利额 | H3: 吨毛利 | I3: 配销差额 | J3: 吨配销差 | K3: 销量 | L3: 毛利额 | M3: 吨毛利 | N3: 配销差额 | O3: 吨配销差 | P3: 销量 | Q3: 毛利额 | R3: 吨毛利 | S3: 配销差额 | T3: 吨配销差
D4: 海特料 | E4: 大黄鱼料 | F4: 计算 | G4: 计算 | H4: 本表计算 | K4: 计算 | L4: 计算 | M4: 本表计算 | P4: 本表计算 | Q4: 本表计算 | R4: 本表计算
E5: 石斑鱼料 | F5: 计算 | G5: 计算 | H5: 本表计算 | K5: 计算 | L5: 计算 | M5: 本表计算 | P5: 本表计算 | Q5: 本表计算 | R5: 本表计算
F6: 计算 | G6: 计算 | H6: 本表计算 | K6: 计算 | L6: 计算 | M6: 本表计算 | P6: 本表计算 | Q6: 本表计算 | R6: 本表计算 | U6: =D6&E6
F7: 计算 | G7: 计算 | H7: 本表计算 | K7: 计算 | L7: 计算 | M7: 本表计算 | P7: 本表计算 | Q7: 本表计算 | R7: 本表计算 | U7: =D7&E7
F8: 计算 | G8: 计算 | H8: 本表计算 | K8: 计算 | L8: 计算 | M8: 本表计算 | P8: 本表计算 | Q8: 本表计算 | R8: 本表计算 | U8: =D8&E8
F9: 计算 | G9: 计算 | H9: 本表计算 | K9: 计算 | L9: 计算 | M9: 本表计算 | P9: 本表计算 | Q9: 本表计算 | R9: 本表计算 | U9: =D9&E9
F10: 计算 | G10: 计算 | H10: 本表计算 | K10: 计算 | L10: 计算 | M10: 本表计算 | P10: 本表计算 | Q10: 本表计算 | R10: 本表计算 | U10: =D10&E10
F11: 计算 | G11: 计算 | H11: 本表计算 | K11: 计算 | L11: 计算 | M11: 本表计算 | P11: 本表计算 | Q11: 本表计算 | R11: 本表计算 | U11: =D11&E11
F12: 计算 | G12: 计算 | H12: 本表计算 | K12: 计算 | L12: 计算 | M12: 本表计算 | P12: 本表计算 | Q12: 本表计算 | R12: 本表计算 | U12: =D12&E12
F13: 计算 | G13: 计算 | H13: 本表计算 | K13: 计算 | L13: 计算 | M13: 本表计算 | P13: 本表计算 | Q13: 本表计算 | R13: 本表计算 | U13: =D13&E13
F14: 计算 | G14: 计算 | H14: 本表计算 | K14: 计算 | L14: 计算 | M14: 本表计算 | P14: 本表计算 | Q14: 本表计算 | R14: 本表计算 | U14: =D14&E14
F15: 计算 | G15: 计算 | H15: 本表计算 | K15: 计算 | L15: 计算 | M15: 本表计算 | P15: 本表计算 | Q15: 本表计算 | R15: 本表计算 | U15: =D15&E15
F16: 计算 | G16: 计算 | H16: 本表计算 | K16: 计算 | L16: 计算 | M16: 本表计算 | P16: 本表计算 | Q16: 本表计算 | R16: 本表计算 | U16: =D16&E16
F17: 计算 | G17: 计算 | H17: 本表计算 | K17: 计算 | L17: 计算 | M17: 本表计算 | P17: 本表计算 | Q17: 本表计算 | R17: 本表计算 | U17: =D17&E17
... F19: 计算 | G19: 计算 | H19: 本表计算 | K19: 计算 | L19: 计算 | M19: 本表计算 | P19: 本表计算 | Q19: 本表计算 | R19: 本表计算 | U19: =D19&E19
F20: 计算 | G20: 计算 | H20: 本表计算 | K20: 计算 | L20: 计算 | M20: 本表计算 | P20: 本表计算 | Q20: 本表计算 | R20: 本表计算
F21: 计算 | G21: 计算 | H21: 本表计算 | K21: 计算 | L21: 计算 | M21: 本表计算 | P21: 本表计算 | Q21: 本表计算 | R21: 本表计算
F22: 计算 | G22: 计算 | H22: 本表计算 | K22: 计算 | L22: 计算 | M22: 本表计算 | P22: 本表计算 | Q22: 本表计算 | R22: 本表计算
F23: 计算 | G23: 计算 | H23: 本表计算 | K23: 计算 | L23: 计算 | M23: 本表计算 | P23: 本表计算 | Q23: 本表计算 | R23: 本表计算 | U23: =D23&E23
F24: 计算 | G24: 计算 | H24: 本表计算 | K24: 计算 | L24: 计算 | M24: 本表计算 | P24: 本表计算 | Q24: 本表计算 | R24: 本表计算 | U24: =D24&E24

Sheet 新增-产品系列配销差及吨毛利（查阅）
A1: ← 返回目录 | B1: 大类 | C1: 小类 | D1: 产品系列 | E1: 单吨配销差 | AE1: 单吨毛利
E2: 2026年预算值 | R2: 同比 | AE2: 2026年预算值 | AR2: 同比
E3: 1月 | F3: 2月 | G3: 3月 | H3: 4月 | I3: 5月 | J3: 6月 | K3: 7月 | L3: 8月 | M3: 9月 | N3: 10月 | O3: 11月 | P3: 12月 | Q3: 合计 | R3: 1月 | S3: 2月 | T3: 3月 | U3: 4月 | V3: 5月 | W3: 6月 | X3: 7月 | Y3: 8月 | Z3: 9月 | AA3: 10月 | AB3: 11月 | AC3: 12月 | AD3: 合计 | AE3: 1月 | AF3: 2月 | AG3: 3月 | AH3: 4月 | AI3: 5月 | AJ3: 6月 | AK3: 7月 | AL3: 8月 | AM3: 9月 | AN3: 10月 | AO3: 11月 | AP3: 12月 | AQ3: 合计 | AR3: 1月 | AS3: 2月 | AT3: 3月 | AU3: 4月 | AV3: 5月 | AW3: 6月 | AX3: 7月 | AY3: 8月 | AZ3: 9月 | BA3: 10月 | BB3: 11月 | BC3: 12月 | BD3: 合计
B4: 虾料 | C4: 虾安康 | D4: 铂金版虾安康
D5: 金刚安康
D6: 虾奶粉
D7: 虾安康

Sheet A9-表样-客户产品毛利表（外销）
A1: ← 返回目录 | B1: 任务名称： | C1: 1.1销量预算表_编制
B2: 年份： | C2: 2026 | D2: 月份： | E2: 01,02,03
B3: 版本类型： | C3: 年度
B4: 版本： | C4: v1
B5: 业务单元： | C5: 江门澳华
A7: 版本 | B7: 大区 | C7: 公司 | D7: 区域/聚焦镇 | E7: 客户编码 | F7: 客户 | G7: 是否大客户 | H7: 产品系列编码 | I7: 产品系列名称 | J7: 大类 | K7: 小类 | L7: 战略产品 | M7: 销售吨位 | N7: 赠送吨位 | O7: 单吨售价 | P7: 售价总额 | Q7: 单吨折扣 | R7: 折扣总额 | S7: 单吨净收 | T7: 销售净收入额 | U7: 销售成本 | V7: 单吨销售成本 | W7: 赠送成本 | X7: 单吨配方成本 | Y7: 单吨包装物 | Z7: 单吨燃动 | AA7: 单吨人工 | AB7: 单吨变动制造费用 | AC7: 单吨固定制造费用 | AD7: 单吨制造费用 | AE7: 单吨配销差 | AF7: 配销差总额 | AG7: 单吨边际贡献 | AH7: 总边际贡献 | AI7: 单吨毛利 | AJ7: 销售总毛利 | AK7: 销售费用额 | AL7: 销售净贡献
A8: V1 | B8: 华南大区 | C8: 江门澳华 | H8: JK001 | I8: 虾安康 | J8: 虾蟹线 | K8: 虾料 | L8: 高价值

Sheet A9-表样-客户产品毛利表（内销）
A1: ← 返回目录 | B1: 任务名称： | C1: 1.1销量预算表_编制
B2: 年份： | C2: 2026 | D2: 月份： | E2: 01,02,03
B3: 版本类型： | C3: 年度
B4: 版本： | C4: v1
B5: 业务单元： | C5: 江门澳华
A7: 版本 | B7: 大区 | C7: 公司 | D7: 区域/聚焦镇 | E7: 客户编码 | F7: 客户 | G7: 是否大客户 | H7: 产品系列编码 | I7: 产品系列名称 | J7: 大类 | K7: 小类 | L7: 战略产品 | M7: 销售吨位 | N7: 赠送吨位 | O7: 单吨售价 | P7: 售价总额 | Q7: 单吨净收 | R7: 销售净收入额 | S7: 销售成本 | T7: 单吨销售成本 | U7: 单吨配方成本 | V7: 单吨包装物 | W7: 单吨燃动 | X7: 单吨人工 | Y7: 单吨变动制造费用 | Z7: 单吨固定制造费用 | AA7: 单吨制造费用 | AB7: 单吨配销差 | AC7: 配销差总额 | AD7: 单吨毛利 | AE7: 销售总毛利
A8: V1 | B8: 华南大区 | C8: 江门澳华 | H8: JK001 | I8: 虾安康 | J8: 虾蟹线 | K8: 虾料 | L8: 高价值

Sheet 查阅-产品生产成本
A1: ← 返回目录 | B1: 公司 | C1: 大类 | D1: 小类 | E1: 2026年预算 | L1: 2025年实际值 | S1: 同比增长（预测-同比）
E2: 单吨配方成本 | F2: 单吨包装物 | G2: 单吨制造费用 | H2: 其中：单吨燃动 | I2: 其中：单吨人工 | J2: 其中：单吨其他变动费用 | K2: 其中：单吨固定制造费用 | L2: 单吨配方成本 | M2: 单吨包装物 | N2: 单吨制造费用 | O2: 其中：单吨燃动 | P2: 其中：单吨人工 | Q2: 其中：单吨其他变动费用 | R2: 其中：单吨固定制造费用 | S2: 单吨配方成本 | T2: 单吨包装物 | U2: 单吨制造费用 | V2: 其中：单吨燃动 | W2: 其中：单吨人工 | X2: 其中：单吨其他变动费用 | Y2: 其中：单吨固定制造费用
C3: 海特料 | D3: 大黄鱼料 | L3: 计算 | M3: 计算 | N3: 本表计算 | S3: 本表计算 | T3: 本表计算 | U3: 本表计算
D4: 石斑鱼料 | L4: 计算 | M4: 计算 | N4: 本表计算 | S4: 本表计算 | T4: 本表计算 | U4: 本表计算
L5: 计算 | M5: 计算 | N5: 本表计算 | S5: 本表计算 | T5: 本表计算 | U5: 本表计算
L6: 计算 | M6: 计算 | N6: 本表计算 | S6: 本表计算 | T6: 本表计算 | U6: 本表计算
L7: 计算 | M7: 计算 | N7: 本表计算 | S7: 本表计算 | T7: 本表计算 | U7: 本表计算
L8: 计算 | M8: 计算 | N8: 本表计算 | S8: 本表计算 | T8: 本表计算 | U8: 本表计算
L9: 计算 | M9: 计算 | N9: 本表计算 | S9: 本表计算 | T9: 本表计算 | U9: 本表计算
L10: 计算 | M10: 计算 | N10: 本表计算 | S10: 本表计算 | T10: 本表计算 | U10: 本表计算
L11: 计算 | M11: 计算 | N11: 本表计算 | S11: 本表计算 | T11: 本表计算 | U11: 本表计算
L12: 计算 | M12: 计算 | N12: 本表计算 | S12: 本表计算 | T12: 本表计算 | U12: 本表计算
L13: 计算 | M13: 计算 | N13: 本表计算 | S13: 本表计算 | T13: 本表计算 | U13: 本表计算
L14: 计算 | M14: 计算 | N14: 本表计算 | S14: 本表计算 | T14: 本表计算 | U14: 本表计算
L15: 计算 | M15: 计算 | N15: 本表计算 | S15: 本表计算 | T15: 本表计算 | U15: 本表计算
L16: 计算 | M16: 计算 | N16: 本表计算 | S16: 本表计算 | T16: 本表计算 | U16: 本表计算
... L23: 计算 | M23: 计算 | N23: 本表计算 | S23: 本表计算 | T23: 本表计算 | U23: 本表计算

Sheet  单吨制造费用-生产、财务-查阅
A1: ← 返回目录 | E1: 填录说明： | F1: 第一步，选择年、公司、版本、场景；
F2: 第二步，下拉选择产品系列；
F3: 第四步，系统将根据生产预算表自动计算产品系列的单吨制造费用数据。
F4: 第四步，填制数据完成后，单击【提交】按钮，将数据提交至系统。
A5: 责任部门：生产部、财务部 | E5: 单位：元/吨
A7: 年 | B7: 2026年 | C7: 公司 | D7: xx澳华 | E7: 版本 | F7: V1 | G7: 场景
A9: 大类 | B9: 小类 | C9: 产品系列编码 | D9: 产品系列 | E9: 25年平均单吨制造费用 | F9: 26年平均单吨制造费用 | G9: 平均单吨制造费用同比增减额 | H9: 2026年单吨制造费用 | T9: 2025年单吨制造费用 | AF9: 单吨制造费用同比
H10: 1月 | I10: 2月 | J10: 3月 | K10: 4月 | L10: 5月 | M10: 6月 | N10: 7月 | O10: 8月 | P10: 9月 | Q10: 10月 | R10: 11月 | S10: 12月 | T10: 1月 | U10: 2月 | V10: 3月 | W10: 4月 | X10: 5月 | Y10: 6月 | Z10: 7月 | AA10: 8月 | AB10: 9月 | AC10: 10月 | AD10: 11月 | AE10: 12月 | AF10: 1月 | AG10: 2月 | AH10: 3月 | AI10: 4月 | AJ10: 5月 | AK10: 6月 | AL10: 7月 | AM10: 8月 | AN10: 9月 | AO10: 10月 | AP10: 11月 | AQ10: 12月
A11: 自动生成 | B11: 自动生成 | C11: 自动生成 | D11: 自动生成 | E11: 自动生成 | F11: 计算 | G11: 计算 | H11: 自动生成 | I11: 自动生成 | J11: 自动生成 | K11: 自动生成 | L11: 自动生成 | M11: 自动生成 | N11: 自动生成 | O11: 自动生成 | P11: 自动生成 | Q11: 自动生成 | R11: 自动生成 | S11: 自动生成 | T11: 自动生成 | U11: 自动生成 | V11: 自动生成 | W11: 自动生成 | X11: 自动生成 | Y11: 自动生成 | Z11: 自动生成 | AA11: 自动生成 | AB11: 自动生成 | AC11: 自动生成 | AD11: 自动生成 | AE11: 自动生成 | AF11: 自动生成 | AG11: 自动生成 | AH11: 自动生成 | AI11: 自动生成 | AJ11: 自动生成 | AK11: 自动生成 | AL11: 自动生成 | AM11: 自动生成 | AN11: 自动生成 | AO11: 自动生成 | AP11: 自动生成 | AQ11: 自动生成

Sheet 查阅-动保产品大类毛利
A1: ← 返回目录
A3: 大类 | B3: 产品系列 | C3: 2026年预算 | G3: 2025年实际值 | K3: 同比增长（预算-同比）
C5: 销售额 | D5: 生产成本 | E5: 毛利额 | F5: 毛利率 | G5: 销售额 | H5: 生产成本 | I5: 毛利额 | J5: 毛利率 | K5: 销售额 | L5: 生产生产 | M5: 毛利额 | N5: 毛利率
A6: 软颗粒 | B6: 肽康宝
B7: 虾酸奶

Sheet 查阅-动保产品大类毛利 (分月)
A1: ← 返回目录
A3: 大类 | B3: 产品系列 | C3: 销售额 | AC3: 2026年毛利额
C4: 2026年预算数 | P4: 同比 | AC4: 2026年预算数 | AP4: 同比
C5: 合计 | D5: 1月 | E5: 2月 | F5: 3月 | G5: 4月 | H5: 5月 | I5: 6月 | J5: 7月 | K5: 8月 | L5: 9月 | M5: 10月 | N5: 11月 | O5: 12月 | P5: 合计 | Q5: 1月 | R5: 2月 | S5: 3月 | T5: 4月 | U5: 5月 | V5: 6月 | W5: 7月 | X5: 8月 | Y5: 9月 | Z5: 10月 | AA5: 11月 | AB5: 12月 | AC5: 合计 | AD5: 1月 | AE5: 2月 | AF5: 3月 | AG5: 4月 | AH5: 5月 | AI5: 6月 | AJ5: 7月 | AK5: 8月 | AL5: 9月 | AM5: 10月 | AN5: 11月 | AO5: 12月 | AP5: 合计 | AQ5: 1月 | AR5: 2月 | AS5: 3月 | AT5: 4月 | AU5: 5月 | AV5: 6月 | AW5: 7月 | AX5: 8月 | AY5: 9月 | AZ5: 10月 | BA5: 11月 | BB5: 12月
A6: 软颗粒 | B6: 肽康宝
B7: 虾酸奶

Sheet 查阅-动保产品公司毛利（分月）
A1: ← 返回目录
C2: 注：销售额取饲料公司填报数据；动保仅填毛利率/吨毛利数据
A3: 公司 | B3: 大类 | C3: 销售额 | AC3: 2026年毛利额
C4: 2026年预算数 | P4: 同比 | AC4: 2026年预算数 | AP4: 同比
C5: 合计 | D5: 1月 | E5: 2月 | F5: 3月 | G5: 4月 | H5: 5月 | I5: 6月 | J5: 7月 | K5: 8月 | L5: 9月 | M5: 10月 | N5: 11月 | O5: 12月 | P5: 合计 | Q5: 1月 | R5: 2月 | S5: 3月 | T5: 4月 | U5: 5月 | V5: 6月 | W5: 7月 | X5: 8月 | Y5: 9月 | Z5: 10月 | AA5: 11月 | AB5: 12月 | AC5: 合计 | AD5: 1月 | AE5: 2月 | AF5: 3月 | AG5: 4月 | AH5: 5月 | AI5: 6月 | AJ5: 7月 | AK5: 8月 | AL5: 9月 | AM5: 10月 | AN5: 11月 | AO5: 12月 | AP5: 合计 | AQ5: 1月 | AR5: 2月 | AS5: 3月 | AT5: 4月 | AU5: 5月 | AV5: 6月 | AW5: 7月 | AX5: 8月 | AY5: 9月 | AZ5: 10月 | BA5: 11月 | BB5: 12月
A6: 江门 | B6: 软颗粒
B7: 常规
A8: 武汉 | B8: 软颗粒
B9: 常规

Sheet 查阅-动保产品毛利表（明细）
A1: ← 返回目录 | B1: 任务名称： | C1: 动保产品毛利明细
B2: 年份： | C2: 2026 | D2: 月份： | E2: 01,02,03
B3: 版本类型： | C3: 年度
B4: 版本： | C4: v1
B5: 业务单元： | C5: 江门澳保
A7: 版本 | B7: 大区 | C7: 公司 | D7: 区域/聚焦镇 | E7: 客户编码 | F7: 客户 | G7: 大类 | H7: 产品系列编码 | I7: 产品系列名称 | J7: 销售额 | K7: 成本额 | L7: 总毛利额 | M7: 毛利率
A8: V1 | B8: 华南大区 | C8: 江门澳华 | G8: 软颗粒 | H8: JK001 | I8: 肽康宝

Sheet 填写-饲料销量-营销部
A1: ← 返回目录 | B1: CUBE: | C1: TONGWEI:02外销量（按客户）-导入
B2: 币种 | C2: Local
B3: 新老客户 | C3: 老客户
B4: 备用维1 | C4: 备用1不区分
B5: 备用维2 | C5: 备用2不区分
B6: 科目 | C6: 外销量
B7: 输入项 | C7: 值
B11: F0100xxx饲料外销销量录入表 | F11: 填录说明： | G11: 第一步，选择年、公司、部门、版本、场景；
G12: 第二步，下拉选择客户名称、是否大客户、产品系列；
G13: 第三步，系统将显示上年销量数，按照产品系列分月填录销量数据；
G14: 第四步，填制数据完成后，单击【提交】按钮，将数据提交至系统。
B15: 责任部门：营销部
F16: 单位：吨
G17: 0
AO18: .
B19: 年 | C19: 2026年 | D19: 公司 | E19: xx澳华 | F19: 部门 | G19: 虾蟹料一部 | H19: 版本 | I19: V1 | J19: 场景 | K19: 年度
B21: 行 | C21: 聚焦镇 | D21: 客户编码 | E21: 客户 | F21: 是否大客户 | G21: 大类 | H21: 小类 | I21: 产品系列编码 | J21: 产品系列 | K21: 战略产品系列 | L21: 2025年合计 | M21: 2026年合计 | N21: 同比增减额 | O21: 同比增减率 | P21: 2026年预算 | AC21: 2025年实际数 | AO21: 同比
P22: 1月 | Q22: 2月 | R22: 3月 | S22: 4月 | T22: 5月 | U22: 6月 | V22: 7月 | W22: 8月 | X22: 9月 | Y22: 10月 | Z22: 11月 | AA22: 12月 | AB22: 备注 | AC22: 1月 | AD22: 2月 | AE22: 3月 | AF22: 4月 | AG22: 5月 | AH22: 6月 | AI22: 7月 | AJ22: 8月 | AK22: 9月 | AL22: 10月 | AM22: 11月 | AN22: 12月 | AO22: 1月 | AP22: 2月 | AQ22: 3月 | AR22: 4月 | AS22: 5月 | AT22: 6月 | AU22: 7月 | AV22: 8月 | AW22: 9月 | AX22: 10月 | AY22: 11月 | AZ22: 12月
C23: 自动生成 | D23: 自动生成 | E23: 选择 | F23: 选择 | G23: 自动生成 | H23: 自动生成 | I23: 自动生成 | J23: 选择 | K23: 自动生成 | L23: 自动生成 | M23: 求和 | N23: 计算 | O23: 计算 | P23: 填入 | Q23: 填入 | R23: 填入 | S23: 填入 | T23: 填入 | U23: 填入 | V23: 填入 | W23: 填入 | X23: 填入 | Y23: 填入 | Z23: 填入 | AA23: 填入 | AB23: 填入 | AC23: 自动生成 | AD23: 自动生成 | AE23: 自动生成 | AF23: 自动生成 | AG23: 自动生成 | AH23: 自动生成 | AI23: 自动生成 | AJ23: 自动生成 | AK23: 自动生成 | AL23: 自动生成 | AM23: 自动生成 | AN23: 自动生成 | AO23: 计算 | AP23: 计算 | AQ23: 计算 | AR23: 计算 | AS23: 计算 | AT23: 计算 | AU23: 计算 | AV23: 计算 | AW23: 计算 | AX23: 计算 | AY23: 计算 | AZ23: 计算
B24: 合计 | C24: / | D24: / | E24: / | F24: / | G24: / | H24: / | I24: / | J24: / | K24: / | M24: 求和 | N24: 计算 | O24: 计算 | P24: 求和 | Q24: 求和 | R24: 求和 | S24: 求和 | T24: 求和 | U24: 求和 | V24: 求和 | W24: 求和 | X24: 求和 | Y24: 求和 | Z24: 求和 | AA24: 求和 | AC24: 求和 | AD24: 求和 | AE24: 求和 | AF24: 求和 | AG24: 求和 | AH24: 求和 | AI24: 求和 | AJ24: 求和 | AK24: 求和 | AL24: 求和 | AM24: 求和 | AN24: 求和 | AO24: 求和 | AP24: 求和 | AQ24: 求和 | AR24: 求和 | AS24: 求和 | AT24: 求和 | AU24: 求和 | AV24: 求和 | AW24: 求和 | AX24: 求和 | AY24: 求和 | AZ24: 求和
B25: 行1 | F25: 是 | G25: 虾料 | H25: 虾安康 | J25: 铂金版虾安康 | M25: 求和 | N25: 计算 | O25: 计算
B26: 行2 | F26: 否 | J26: 金刚安康 | M26: 求和 | N26: 计算 | O26: 计算
B27: 行3 | J27: 虾奶粉 | M27: 求和 | N27: 计算 | O27: 计算
B28: 行4 | J28: 虾安康 | M28: 求和 | N28: 计算 | O28: 计算
B29: 行5 | M29: 求和 | N29: 计算 | O29: 计算
B30: 行6 | M30: 求和 | N30: 计算 | O30: 计算
B31: 行8 | M31: 求和 | N31: 计算 | O31: 计算
B32: 行9 | M32: 求和 | N32: 计算 | O32: 计算
B33: 行10 | M33: 求和 | N33: 计算 | O33: 计算
B34: 行11 | M34: 求和 | N34: 计算 | O34: 计算
B35: 行12 | M35: 求和 | N35: 计算 | O35: 计算
B36: 行13 | M36: 求和 | N36: 计算 | O36: 计算
B37: 行16 | M37: 求和 | N37: 计算 | O37: 计算
B38: 行17 | M38: 求和 | N38: 计算 | O38: 计算
B39: 行18 | M39: 求和 | N39: 计算 | O39: 计算
B40: 行19 | M40: 求和 | N40: 计算 | O40: 计算
... B87: 行68 | M87: 求和 | N87: 计算 | O87: 计算
B88: 行69 | M88: 求和 | N88: 计算 | O88: 计算 | P88: 0 | Q88: 0 | R88: 0 | S88: 0 | T88: 0 | U88: 0 | V88: 0 | W88: 0 | X88: 0 | Y88: 0 | Z88: 0 | AA88: 0 | AC88: 0 | AD88: 0 | AE88: 0 | AF88: 0 | AG88: 0 | AH88: 0 | AI88: 0 | AJ88: 0 | AK88: 0 | AL88: 0 | AM88: 0 | AN88: 0 | AO88: 0 | AP88: 0 | AQ88: 0 | AR88: 0 | AS88: 0 | AT88: 0 | AU88: 0 | AV88: 0 | AW88: 0 | AX88: 0 | AY88: 0 | AZ88: 0
B89: 行70 | M89: 求和 | N89: 计算 | O89: 计算 | P89: 0 | Q89: 0 | R89: 0 | S89: 0 | T89: 0 | U89: 0 | V89: 0 | W89: 0 | X89: 0 | Y89: 0 | Z89: 0 | AA89: 0 | AC89: 0 | AD89: 0 | AE89: 0 | AF89: 0 | AG89: 0 | AH89: 0 | AI89: 0 | AJ89: 0 | AK89: 0 | AL89: 0 | AM89: 0 | AN89: 0 | AO89: 0 | AP89: 0 | AQ89: 0 | AR89: 0 | AS89: 0 | AT89: 0 | AU89: 0 | AV89: 0 | AW89: 0 | AX89: 0 | AY89: 0 | AZ89: 0
B90: 行71 | M90: 求和 | N90: 计算 | O90: 计算 | P90: 0 | Q90: 0 | R90: 0 | S90: 0 | T90: 0 | U90: 0 | V90: 0 | W90: 0 | X90: 0 | Y90: 0 | Z90: 0 | AA90: 0 | AC90: 0 | AD90: 0 | AE90: 0 | AF90: 0 | AG90: 0 | AH90: 0 | AI90: 0 | AJ90: 0 | AK90: 0 | AL90: 0 | AM90: 0 | AN90: 0 | AO90: 0 | AP90: 0 | AQ90: 0 | AR90: 0 | AS90: 0 | AT90: 0 | AU90: 0 | AV90: 0 | AW90: 0 | AX90: 0 | AY90: 0 | AZ90: 0
B91: 行72 | M91: 求和 | N91: 计算 | O91: 计算 | P91: 0 | Q91: 0 | R91: 0 | S91: 0 | T91: 0 | U91: 0 | V91: 0 | W91: 0 | X91: 0 | Y91: 0 | Z91: 0 | AA91: 0 | AC91: 0 | AD91: 0 | AE91: 0 | AF91: 0 | AG91: 0 | AH91: 0 | AI91: 0 | AJ91: 0 | AK91: 0 | AL91: 0 | AM91: 0 | AN91: 0 | AO91: 0 | AP91: 0 | AQ91: 0 | AR91: 0 | AS91: 0 | AT91: 0 | AU91: 0 | AV91: 0 | AW91: 0 | AX91: 0 | AY91: 0 | AZ91: 0
B92: 行73 | M92: 求和 | N92: 计算 | O92: 计算 | P92: 0 | Q92: 0 | R92: 0 | S92: 0 | T92: 0 | U92: 0 | V92: 0 | W92: 0 | X92: 0 | Y92: 0 | Z92: 0 | AA92: 0 | AC92: 0 | AD92: 0 | AE92: 0 | AF92: 0 | AG92: 0 | AH92: 0 | AI92: 0 | AJ92: 0 | AK92: 0 | AL92: 0 | AM92: 0 | AN92: 0 | AO92: 0 | AP92: 0 | AQ92: 0 | AR92: 0 | AS92: 0 | AT92: 0 | AU92: 0 | AV92: 0 | AW92: 0 | AX92: 0 | AY92: 0 | AZ92: 0
B93: 行74 | M93: 求和 | N93: 计算 | O93: 计算 | P93: 0 | Q93: 0 | R93: 0 | S93: 0 | T93: 0 | U93: 0 | V93: 0 | W93: 0 | X93: 0 | Y93: 0 | Z93: 0 | AA93: 0 | AC93: 0 | AD93: 0 | AE93: 0 | AF93: 0 | AG93: 0 | AH93: 0 | AI93: 0 | AJ93: 0 | AK93: 0 | AL93: 0 | AM93: 0 | AN93: 0 | AO93: 0 | AP93: 0 | AQ93: 0 | AR93: 0 | AS93: 0 | AT93: 0 | AU93: 0 | AV93: 0 | AW93: 0 | AX93: 0 | AY93: 0 | AZ93: 0
B94: 行75 | M94: 求和 | N94: 计算 | O94: 计算 | P94: 0 | Q94: 0 | R94: 0 | S94: 0 | T94: 0 | U94: 0 | V94: 0 | W94: 0 | X94: 0 | Y94: 0 | Z94: 0 | AA94: 0 | AC94: 0 | AD94: 0 | AE94: 0 | AF94: 0 | AG94: 0 | AH94: 0 | AI94: 0 | AJ94: 0 | AK94: 0 | AL94: 0 | AM94: 0 | AN94: 0 | AO94: 0 | AP94: 0 | AQ94: 0 | AR94: 0 | AS94: 0 | AT94: 0 | AU94: 0 | AV94: 0 | AW94: 0 | AX94: 0 | AY94: 0 | AZ94: 0
B95: 行76 | M95: 求和 | N95: 计算 | O95: 计算 | P95: 0 | Q95: 0 | R95: 0 | S95: 0 | T95: 0 | U95: 0 | V95: 0 | W95: 0 | X95: 0 | Y95: 0 | Z95: 0 | AA95: 0 | AC95: 0 | AD95: 0 | AE95: 0 | AF95: 0 | AG95: 0 | AH95: 0 | AI95: 0 | AJ95: 0 | AK95: 0 | AL95: 0 | AM95: 0 | AN95: 0 | AO95: 0 | AP95: 0 | AQ95: 0 | AR95: 0 | AS95: 0 | AT95: 0 | AU95: 0 | AV95: 0 | AW95: 0 | AX95: 0 | AY95: 0 | AZ95: 0
B96: 行77 | M96: 求和 | N96: 计算 | O96: 计算 | P96: 0 | Q96: 0 | R96: 0 | S96: 0 | T96: 0 | U96: 0 | V96: 0 | W96: 0 | X96: 0 | Y96: 0 | Z96: 0 | AA96: 0 | AC96: 0 | AD96: 0 | AE96: 0 | AF96: 0 | AG96: 0 | AH96: 0 | AI96: 0 | AJ96: 0 | AK96: 0 | AL96: 0 | AM96: 0 | AN96: 0 | AO96: 0 | AP96: 0 | AQ96: 0 | AR96: 0 | AS96: 0 | AT96: 0 | AU96: 0 | AV96: 0 | AW96: 0 | AX96: 0 | AY96: 0 | AZ96: 0
B97: 行78 | M97: 求和 | N97: 计算 | O97: 计算 | P97: 0 | Q97: 0 | R97: 0 | S97: 0 | T97: 0 | U97: 0 | V97: 0 | W97: 0 | X97: 0 | Y97: 0 | Z97: 0 | AA97: 0 | AC97: 0 | AD97: 0 | AE97: 0 | AF97: 0 | AG97: 0 | AH97: 0 | AI97: 0 | AJ97: 0 | AK97: 0 | AL97: 0 | AM97: 0 | AN97: 0 | AO97: 0 | AP97: 0 | AQ97: 0 | AR97: 0 | AS97: 0 | AT97: 0 | AU97: 0 | AV97: 0 | AW97: 0 | AX97: 0 | AY97: 0 | AZ97: 0
B98: 行79 | M98: 求和 | N98: 计算 | O98: 计算 | P98: 0 | Q98: 0 | R98: 0 | S98: 0 | T98: 0 | U98: 0 | V98: 0 | W98: 0 | X98: 0 | Y98: 0 | Z98: 0 | AA98: 0 | AC98: 0 | AD98: 0 | AE98: 0 | AF98: 0 | AG98: 0 | AH98: 0 | AI98: 0 | AJ98: 0 | AK98: 0 | AL98: 0 | AM98: 0 | AN98: 0 | AO98: 0 | AP98: 0 | AQ98: 0 | AR98: 0 | AS98: 0 | AT98: 0 | AU98: 0 | AV98: 0 | AW98: 0 | AX98: 0 | AY98: 0 | AZ98: 0
B99: 行80 | M99: 求和 | N99: 计算 | O99: 计算 | P99: 0 | Q99: 0 | R99: 0 | S99: 0 | T99: 0 | U99: 0 | V99: 0 | W99: 0 | X99: 0 | Y99: 0 | Z99: 0 | AA99: 0 | AC99: 0 | AD99: 0 | AE99: 0 | AF99: 0 | AG99: 0 | AH99: 0 | AI99: 0 | AJ99: 0 | AK99: 0 | AL99: 0 | AM99: 0 | AN99: 0 | AO99: 0 | AP99: 0 | AQ99: 0 | AR99: 0 | AS99: 0 | AT99: 0 | AU99: 0 | AV99: 0 | AW99: 0 | AX99: 0 | AY99: 0 | AZ99: 0
... B119: 行100 | M119: 求和 | N119: 计算 | O119: 计算 | P119: 0 | Q119: 0 | R119: 0 | S119: 0 | T119: 0 | U119: 0 | V119: 0 | W119: 0 | X119: 0 | Y119: 0 | Z119: 0 | AA119: 0 | AC119: 0 | AD119: 0 | AE119: 0 | AF119: 0 | AG119: 0 | AH119: 0 | AI119: 0 | AJ119: 0 | AK119: 0 | AL119: 0 | AM119: 0 | AN119: 0 | AO119: 0 | AP119: 0 | AQ119: 0 | AR119: 0 | AS119: 0 | AT119: 0 | AU119: 0 | AV119: 0 | AW119: 0 | AX119: 0 | AY119: 0 | AZ119: 0

Sheet 填写-动保销售额-营销部
A1: ← 返回目录 | B1: CUBE: | C1: TONGWEI:02外销量（按客户）-导入
B2: 币种 | C2: Local
B3: 新老客户 | C3: 老客户
B4: 备用维1 | C4: 备用1不区分
B5: 备用维2 | C5: 备用2不区分
B6: 科目 | C6: 外销量
B7: 输入项 | C7: 值
B11: F0100xxx动保销售额录入表（除发酵料外） | F11: 填录说明： | G11: 第一步，选择年、公司、部门、版本、场景；
G12: 第二步，下拉选择客户名称、是否大客户、产品系列；
G13: 第三步，系统将显示上年销售额，按照产品系列分月填录销售额数据；
G14: 第四步，填制数据完成后，单击【提交】按钮，将数据提交至系统。
B15: 责任部门：营销部
F16: 单位：元
G17: 0
AN18: .
B19: 年 | C19: 2026年 | D19: 公司 | E19: xx澳华 | F19: 部门 | G19: 虾蟹料一部 | H19: 版本 | I19: V1 | J19: 场景 | K19: 年度
B21: 行 | C21: 聚焦镇 | D21: 客户编码 | E21: 客户 | F21: 是否大客户 | G21: 大类 | H21: 产品系列编码 | I21: 产品系列 | J21: 2025年合计 | K21: 2026年合计 | L21: 同比增减额 | M21: 同比增减率 | N21: 2026年预算数 | AA21: 2025年实际数 | AM21: 同比
N22: 1月 | O22: 2月 | P22: 3月 | Q22: 4月 | R22: 5月 | S22: 6月 | T22: 7月 | U22: 8月 | V22: 9月 | W22: 10月 | X22: 11月 | Y22: 12月 | Z22: 备注 | AA22: 1月 | AB22: 2月 | AC22: 3月 | AD22: 4月 | AE22: 5月 | AF22: 6月 | AG22: 7月 | AH22: 8月 | AI22: 9月 | AJ22: 10月 | AK22: 11月 | AL22: 12月 | AM22: 1月 | AN22: 2月 | AO22: 3月 | AP22: 4月 | AQ22: 5月 | AR22: 6月 | AS22: 7月 | AT22: 8月 | AU22: 9月 | AV22: 10月 | AW22: 11月 | AX22: 12月
C23: 自动生成 | D23: 自动生成 | E23: 选择 | F23: 选择 | G23: 自动生成 | H23: 自动生成 | I23: 选择 | J23: 自动生成 | K23: 求和 | L23: 计算 | M23: 计算 | N23: 填入 | O23: 填入 | P23: 填入 | Q23: 填入 | R23: 填入 | S23: 填入 | T23: 填入 | U23: 填入 | V23: 填入 | W23: 填入 | X23: 填入 | Y23: 填入 | Z23: 填入 | AA23: 自动生成 | AB23: 自动生成 | AC23: 自动生成 | AD23: 自动生成 | AE23: 自动生成 | AF23: 自动生成 | AG23: 自动生成 | AH23: 自动生成 | AI23: 自动生成 | AJ23: 自动生成 | AK23: 自动生成 | AL23: 自动生成 | AM23: 计算 | AN23: 计算 | AO23: 计算 | AP23: 计算 | AQ23: 计算 | AR23: 计算 | AS23: 计算 | AT23: 计算 | AU23: 计算 | AV23: 计算 | AW23: 计算 | AX23: 计算
B24: 合计 | C24: / | D24: / | E24: / | F24: / | G24: / | H24: / | I24: / | K24: 求和 | L24: 计算 | M24: 计算 | N24: 求和 | O24: 求和 | P24: 求和 | Q24: 求和 | R24: 求和 | S24: 求和 | T24: 求和 | U24: 求和 | V24: 求和 | W24: 求和 | X24: 求和 | Y24: 求和 | AA24: 求和 | AB24: 求和 | AC24: 求和 | AD24: 求和 | AE24: 求和 | AF24: 求和 | AG24: 求和 | AH24: 求和 | AI24: 求和 | AJ24: 求和 | AK24: 求和 | AL24: 求和 | AM24: 求和 | AN24: 求和 | AO24: 求和 | AP24: 求和 | AQ24: 求和 | AR24: 求和 | AS24: 求和 | AT24: 求和 | AU24: 求和 | AV24: 求和 | AW24: 求和 | AX24: 求和
B25: 行1 | F25: 是 | G25: 软颗粒 | I25: 肽康宝 | K25: 求和 | L25: 计算 | M25: 计算
B26: 行2 | F26: 否 | I26: 虾酸奶 | K26: 求和 | L26: 计算 | M26: 计算
B27: 行3 | G27: 常规动保 | K27: 求和 | L27: 计算 | M27: 计算
B28: 行4 | K28: 求和 | L28: 计算 | M28: 计算
B29: 行5 | K29: 求和 | L29: 计算 | M29: 计算
B30: 行6 | K30: 求和 | L30: 计算 | M30: 计算
B31: 行8 | K31: 求和 | L31: 计算 | M31: 计算
B32: 行9 | K32: 求和 | L32: 计算 | M32: 计算
B33: 行10 | K33: 求和 | L33: 计算 | M33: 计算
B34: 行11 | K34: 求和 | L34: 计算 | M34: 计算
B35: 行12 | K35: 求和 | L35: 计算 | M35: 计算
B36: 行13 | K36: 求和 | L36: 计算 | M36: 计算
B37: 行16 | K37: 求和 | L37: 计算 | M37: 计算
B38: 行17 | K38: 求和 | L38: 计算 | M38: 计算
B39: 行18 | K39: 求和 | L39: 计算 | M39: 计算
... B87: 行68 | K87: 求和 | L87: 计算 | M87: 计算
B88: 行69 | K88: 求和 | L88: 计算 | M88: 计算 | N88: 0 | O88: 0 | P88: 0 | Q88: 0 | R88: 0 | S88: 0 | T88: 0 | U88: 0 | V88: 0 | W88: 0 | X88: 0 | Y88: 0 | AA88: 0 | AB88: 0 | AC88: 0 | AD88: 0 | AE88: 0 | AF88: 0 | AG88: 0 | AH88: 0 | AI88: 0 | AJ88: 0 | AK88: 0 | AL88: 0 | AM88: 0 | AN88: 0 | AO88: 0 | AP88: 0 | AQ88: 0 | AR88: 0 | AS88: 0 | AT88: 0 | AU88: 0 | AV88: 0 | AW88: 0 | AX88: 0
B89: 行70 | K89: 求和 | L89: 计算 | M89: 计算 | N89: 0 | O89: 0 | P89: 0 | Q89: 0 | R89: 0 | S89: 0 | T89: 0 | U89: 0 | V89: 0 | W89: 0 | X89: 0 | Y89: 0 | AA89: 0 | AB89: 0 | AC89: 0 | AD89: 0 | AE89: 0 | AF89: 0 | AG89: 0 | AH89: 0 | AI89: 0 | AJ89: 0 | AK89: 0 | AL89: 0 | AM89: 0 | AN89: 0 | AO89: 0 | AP89: 0 | AQ89: 0 | AR89: 0 | AS89: 0 | AT89: 0 | AU89: 0 | AV89: 0 | AW89: 0 | AX89: 0
B90: 行71 | K90: 求和 | L90: 计算 | M90: 计算 | N90: 0 | O90: 0 | P90: 0 | Q90: 0 | R90: 0 | S90: 0 | T90: 0 | U90: 0 | V90: 0 | W90: 0 | X90: 0 | Y90: 0 | AA90: 0 | AB90: 0 | AC90: 0 | AD90: 0 | AE90: 0 | AF90: 0 | AG90: 0 | AH90: 0 | AI90: 0 | AJ90: 0 | AK90: 0 | AL90: 0 | AM90: 0 | AN90: 0 | AO90: 0 | AP90: 0 | AQ90: 0 | AR90: 0 | AS90: 0 | AT90: 0 | AU90: 0 | AV90: 0 | AW90: 0 | AX90: 0
B91: 行72 | K91: 求和 | L91: 计算 | M91: 计算 | N91: 0 | O91: 0 | P91: 0 | Q91: 0 | R91: 0 | S91: 0 | T91: 0 | U91: 0 | V91: 0 | W91: 0 | X91: 0 | Y91: 0 | AA91: 0 | AB91: 0 | AC91: 0 | AD91: 0 | AE91: 0 | AF91: 0 | AG91: 0 | AH91: 0 | AI91: 0 | AJ91: 0 | AK91: 0 | AL91: 0 | AM91: 0 | AN91: 0 | AO91: 0 | AP91: 0 | AQ91: 0 | AR91: 0 | AS91: 0 | AT91: 0 | AU91: 0 | AV91: 0 | AW91: 0 | AX91: 0
B92: 行73 | K92: 求和 | L92: 计算 | M92: 计算 | N92: 0 | O92: 0 | P92: 0 | Q92: 0 | R92: 0 | S92: 0 | T92: 0 | U92: 0 | V92: 0 | W92: 0 | X92: 0 | Y92: 0 | AA92: 0 | AB92: 0 | AC92: 0 | AD92: 0 | AE92: 0 | AF92: 0 | AG92: 0 | AH92: 0 | AI92: 0 | AJ92: 0 | AK92: 0 | AL92: 0 | AM92: 0 | AN92: 0 | AO92: 0 | AP92: 0 | AQ92: 0 | AR92: 0 | AS92: 0 | AT92: 0 | AU92: 0 | AV92: 0 | AW92: 0 | AX92: 0
B93: 行74 | K93: 求和 | L93: 计算 | M93: 计算 | N93: 0 | O93: 0 | P93: 0 | Q93: 0 | R93: 0 | S93: 0 | T93: 0 | U93: 0 | V93: 0 | W93: 0 | X93: 0 | Y93: 0 | AA93: 0 | AB93: 0 | AC93: 0 | AD93: 0 | AE93: 0 | AF93: 0 | AG93: 0 | AH93: 0 | AI93: 0 | AJ93: 0 | AK93: 0 | AL93: 0 | AM93: 0 | AN93: 0 | AO93: 0 | AP93: 0 | AQ93: 0 | AR93: 0 | AS93: 0 | AT93: 0 | AU93: 0 | AV93: 0 | AW93: 0 | AX93: 0
B94: 行75 | K94: 求和 | L94: 计算 | M94: 计算 | N94: 0 | O94: 0 | P94: 0 | Q94: 0 | R94: 0 | S94: 0 | T94: 0 | U94: 0 | V94: 0 | W94: 0 | X94: 0 | Y94: 0 | AA94: 0 | AB94: 0 | AC94: 0 | AD94: 0 | AE94: 0 | AF94: 0 | AG94: 0 | AH94: 0 | AI94: 0 | AJ94: 0 | AK94: 0 | AL94: 0 | AM94: 0 | AN94: 0 | AO94: 0 | AP94: 0 | AQ94: 0 | AR94: 0 | AS94: 0 | AT94: 0 | AU94: 0 | AV94: 0 | AW94: 0 | AX94: 0
B95: 行76 | K95: 求和 | L95: 计算 | M95: 计算 | N95: 0 | O95: 0 | P95: 0 | Q95: 0 | R95: 0 | S95: 0 | T95: 0 | U95: 0 | V95: 0 | W95: 0 | X95: 0 | Y95: 0 | AA95: 0 | AB95: 0 | AC95: 0 | AD95: 0 | AE95: 0 | AF95: 0 | AG95: 0 | AH95: 0 | AI95: 0 | AJ95: 0 | AK95: 0 | AL95: 0 | AM95: 0 | AN95: 0 | AO95: 0 | AP95: 0 | AQ95: 0 | AR95: 0 | AS95: 0 | AT95: 0 | AU95: 0 | AV95: 0 | AW95: 0 | AX95: 0
B96: 行77 | K96: 求和 | L96: 计算 | M96: 计算 | N96: 0 | O96: 0 | P96: 0 | Q96: 0 | R96: 0 | S96: 0 | T96: 0 | U96: 0 | V96: 0 | W96: 0 | X96: 0 | Y96: 0 | AA96: 0 | AB96: 0 | AC96: 0 | AD96: 0 | AE96: 0 | AF96: 0 | AG96: 0 | AH96: 0 | AI96: 0 | AJ96: 0 | AK96: 0 | AL96: 0 | AM96: 0 | AN96: 0 | AO96: 0 | AP96: 0 | AQ96: 0 | AR96: 0 | AS96: 0 | AT96: 0 | AU96: 0 | AV96: 0 | AW96: 0 | AX96: 0
B97: 行78 | K97: 求和 | L97: 计算 | M97: 计算 | N97: 0 | O97: 0 | P97: 0 | Q97: 0 | R97: 0 | S97: 0 | T97: 0 | U97: 0 | V97: 0 | W97: 0 | X97: 0 | Y97: 0 | AA97: 0 | AB97: 0 | AC97: 0 | AD97: 0 | AE97: 0 | AF97: 0 | AG97: 0 | AH97: 0 | AI97: 0 | AJ97: 0 | AK97: 0 | AL97: 0 | AM97: 0 | AN97: 0 | AO97: 0 | AP97: 0 | AQ97: 0 | AR97: 0 | AS97: 0 | AT97: 0 | AU97: 0 | AV97: 0 | AW97: 0 | AX97: 0
B98: 行79 | K98: 求和 | L98: 计算 | M98: 计算 | N98: 0 | O98: 0 | P98: 0 | Q98: 0 | R98: 0 | S98: 0 | T98: 0 | U98: 0 | V98: 0 | W98: 0 | X98: 0 | Y98: 0 | AA98: 0 | AB98: 0 | AC98: 0 | AD98: 0 | AE98: 0 | AF98: 0 | AG98: 0 | AH98: 0 | AI98: 0 | AJ98: 0 | AK98: 0 | AL98: 0 | AM98: 0 | AN98: 0 | AO98: 0 | AP98: 0 | AQ98: 0 | AR98: 0 | AS98: 0 | AT98: 0 | AU98: 0 | AV98: 0 | AW98: 0 | AX98: 0
B99: 行80 | K99: 求和 | L99: 计算 | M99: 计算 | N99: 0 | O99: 0 | P99: 0 | Q99: 0 | R99: 0 | S99: 0 | T99: 0 | U99: 0 | V99: 0 | W99: 0 | X99: 0 | Y99: 0 | AA99: 0 | AB99: 0 | AC99: 0 | AD99: 0 | AE99: 0 | AF99: 0 | AG99: 0 | AH99: 0 | AI99: 0 | AJ99: 0 | AK99: 0 | AL99: 0 | AM99: 0 | AN99: 0 | AO99: 0 | AP99: 0 | AQ99: 0 | AR99: 0 | AS99: 0 | AT99: 0 | AU99: 0 | AV99: 0 | AW99: 0 | AX99: 0
... B119: 行100 | K119: 求和 | L119: 计算 | M119: 计算 | N119: 0 | O119: 0 | P119: 0 | Q119: 0 | R119: 0 | S119: 0 | T119: 0 | U119: 0 | V119: 0 | W119: 0 | X119: 0 | Y119: 0 | AA119: 0 | AB119: 0 | AC119: 0 | AD119: 0 | AE119: 0 | AF119: 0 | AG119: 0 | AH119: 0 | AI119: 0 | AJ119: 0 | AK119: 0 | AL119: 0 | AM119: 0 | AN119: 0 | AO119: 0 | AP119: 0 | AQ119: 0 | AR119: 0 | AS119: 0 | AT119: 0 | AU119: 0 | AV119: 0 | AW119: 0 | AX119: 0

Sheet 填写-动保发酵料-营销部
A1: ← 返回目录 | B1: CUBE: | C1: TONGWEI:02外销量（按客户）-导入
B2: 币种 | C2: Local
B3: 新老客户 | C3: 老客户
B4: 备用维1 | C4: 备用1不区分
B5: 备用维2 | C5: 备用2不区分
B6: 科目 | C6: 外销量
B7: 输入项 | C7: 值
B11: F0100xxx动保发酵料录入表 | F11: 填录说明： | G11: 第一步，选择年、公司、部门、版本、场景；
G12: 第二步，下拉选择客户名称、是否大客户、产品系列；
G13: 第三步，系统将显示上年销售吨位，按照产品系列分月填录销量数据；
G14: 第四步，填制数据完成后，单击【提交】按钮，将数据提交至系统。
B15: 责任部门：营销部
F16: 单位：吨
G17: 0
AN18: .
B19: 年 | C19: 2026年 | D19: 公司 | E19: xx澳华 | F19: 部门 | G19: 虾蟹料一部 | H19: 版本 | I19: V1 | J19: 场景 | K19: 年度
B21: 行 | C21: 聚焦镇 | D21: 客户编码 | E21: 客户 | F21: 是否大客户 | G21: 大类 | H21: 产品系列编码 | I21: 产品系列 | J21: 2025年合计 | K21: 2026年合计 | L21: 同比增减额 | M21: 同比增减率 | N21: 2026年预算数 | AA21: 2025年实际数 | AM21: 同比
N22: 1月 | O22: 2月 | P22: 3月 | Q22: 4月 | R22: 5月 | S22: 6月 | T22: 7月 | U22: 8月 | V22: 9月 | W22: 10月 | X22: 11月 | Y22: 12月 | Z22: 备注 | AA22: 1月 | AB22: 2月 | AC22: 3月 | AD22: 4月 | AE22: 5月 | AF22: 6月 | AG22: 7月 | AH22: 8月 | AI22: 9月 | AJ22: 10月 | AK22: 11月 | AL22: 12月 | AM22: 1月 | AN22: 2月 | AO22: 3月 | AP22: 4月 | AQ22: 5月 | AR22: 6月 | AS22: 7月 | AT22: 8月 | AU22: 9月 | AV22: 10月 | AW22: 11月 | AX22: 12月
C23: 自动生成 | D23: 自动生成 | E23: 选择 | F23: 选择 | G23: 自动生成 | H23: 自动生成 | I23: 选择 | J23: 自动生成 | K23: 求和 | L23: 计算 | M23: 计算 | N23: 填入 | O23: 填入 | P23: 填入 | Q23: 填入 | R23: 填入 | S23: 填入 | T23: 填入 | U23: 填入 | V23: 填入 | W23: 填入 | X23: 填入 | Y23: 填入 | Z23: 填入 | AA23: 自动生成 | AB23: 自动生成 | AC23: 自动生成 | AD23: 自动生成 | AE23: 自动生成 | AF23: 自动生成 | AG23: 自动生成 | AH23: 自动生成 | AI23: 自动生成 | AJ23: 自动生成 | AK23: 自动生成 | AL23: 自动生成 | AM23: 计算 | AN23: 计算 | AO23: 计算 | AP23: 计算 | AQ23: 计算 | AR23: 计算 | AS23: 计算 | AT23: 计算 | AU23: 计算 | AV23: 计算 | AW23: 计算 | AX23: 计算
B24: 合计 | C24: / | D24: / | E24: / | F24: / | G24: / | H24: / | I24: / | K24: 求和 | L24: 计算 | M24: 计算 | N24: 求和 | O24: 求和 | P24: 求和 | Q24: 求和 | R24: 求和 | S24: 求和 | T24: 求和 | U24: 求和 | V24: 求和 | W24: 求和 | X24: 求和 | Y24: 求和 | AA24: 求和 | AB24: 求和 | AC24: 求和 | AD24: 求和 | AE24: 求和 | AF24: 求和 | AG24: 求和 | AH24: 求和 | AI24: 求和 | AJ24: 求和 | AK24: 求和 | AL24: 求和 | AM24: 求和 | AN24: 求和 | AO24: 求和 | AP24: 求和 | AQ24: 求和 | AR24: 求和 | AS24: 求和 | AT24: 求和 | AU24: 求和 | AV24: 求和 | AW24: 求和 | AX24: 求和
B25: 行1 | F25: 是 | G25: 软颗粒 | I25: 肽康宝 | K25: 求和 | L25: 计算 | M25: 计算
B26: 行2 | F26: 否 | I26: 虾酸奶 | K26: 求和 | L26: 计算 | M26: 计算
B27: 行3 | G27: 常规动保 | K27: 求和 | L27: 计算 | M27: 计算
B28: 行4 | K28: 求和 | L28: 计算 | M28: 计算
B29: 行5 | K29: 求和 | L29: 计算 | M29: 计算
B30: 行6 | K30: 求和 | L30: 计算 | M30: 计算
B31: 行8 | K31: 求和 | L31: 计算 | M31: 计算
B32: 行9 | K32: 求和 | L32: 计算 | M32: 计算
B33: 行10 | K33: 求和 | L33: 计算 | M33: 计算
B34: 行11 | K34: 求和 | L34: 计算 | M34: 计算
B35: 行12 | K35: 求和 | L35: 计算 | M35: 计算
B36: 行13 | K36: 求和 | L36: 计算 | M36: 计算
B37: 行16 | K37: 求和 | L37: 计算 | M37: 计算
B38: 行17 | K38: 求和 | L38: 计算 | M38: 计算
B39: 行18 | K39: 求和 | L39: 计算 | M39: 计算
... B87: 行68 | K87: 求和 | L87: 计算 | M87: 计算
B88: 行69 | K88: 求和 | L88: 计算 | M88: 计算 | N88: 0 | O88: 0 | P88: 0 | Q88: 0 | R88: 0 | S88: 0 | T88: 0 | U88: 0 | V88: 0 | W88: 0 | X88: 0 | Y88: 0 | AA88: 0 | AB88: 0 | AC88: 0 | AD88: 0 | AE88: 0 | AF88: 0 | AG88: 0 | AH88: 0 | AI88: 0 | AJ88: 0 | AK88: 0 | AL88: 0 | AM88: 0 | AN88: 0 | AO88: 0 | AP88: 0 | AQ88: 0 | AR88: 0 | AS88: 0 | AT88: 0 | AU88: 0 | AV88: 0 | AW88: 0 | AX88: 0
B89: 行70 | K89: 求和 | L89: 计算 | M89: 计算 | N89: 0 | O89: 0 | P89: 0 | Q89: 0 | R89: 0 | S89: 0 | T89: 0 | U89: 0 | V89: 0 | W89: 0 | X89: 0 | Y89: 0 | AA89: 0 | AB89: 0 | AC89: 0 | AD89: 0 | AE89: 0 | AF89: 0 | AG89: 0 | AH89: 0 | AI89: 0 | AJ89: 0 | AK89: 0 | AL89: 0 | AM89: 0 | AN89: 0 | AO89: 0 | AP89: 0 | AQ89: 0 | AR89: 0 | AS89: 0 | AT89: 0 | AU89: 0 | AV89: 0 | AW89: 0 | AX89: 0
B90: 行71 | K90: 求和 | L90: 计算 | M90: 计算 | N90: 0 | O90: 0 | P90: 0 | Q90: 0 | R90: 0 | S90: 0 | T90: 0 | U90: 0 | V90: 0 | W90: 0 | X90: 0 | Y90: 0 | AA90: 0 | AB90: 0 | AC90: 0 | AD90: 0 | AE90: 0 | AF90: 0 | AG90: 0 | AH90: 0 | AI90: 0 | AJ90: 0 | AK90: 0 | AL90: 0 | AM90: 0 | AN90: 0 | AO90: 0 | AP90: 0 | AQ90: 0 | AR90: 0 | AS90: 0 | AT90: 0 | AU90: 0 | AV90: 0 | AW90: 0 | AX90: 0
B91: 行72 | K91: 求和 | L91: 计算 | M91: 计算 | N91: 0 | O91: 0 | P91: 0 | Q91: 0 | R91: 0 | S91: 0 | T91: 0 | U91: 0 | V91: 0 | W91: 0 | X91: 0 | Y91: 0 | AA91: 0 | AB91: 0 | AC91: 0 | AD91: 0 | AE91: 0 | AF91: 0 | AG91: 0 | AH91: 0 | AI91: 0 | AJ91: 0 | AK91: 0 | AL91: 0 | AM91: 0 | AN91: 0 | AO91: 0 | AP91: 0 | AQ91: 0 | AR91: 0 | AS91: 0 | AT91: 0 | AU91: 0 | AV91: 0 | AW91: 0 | AX91: 0
B92: 行73 | K92: 求和 | L92: 计算 | M92: 计算 | N92: 0 | O92: 0 | P92: 0 | Q92: 0 | R92: 0 | S92: 0 | T92: 0 | U92: 0 | V92: 0 | W92: 0 | X92: 0 | Y92: 0 | AA92: 0 | AB92: 0 | AC92: 0 | AD92: 0 | AE92: 0 | AF92: 0 | AG92: 0 | AH92: 0 | AI92: 0 | AJ92: 0 | AK92: 0 | AL92: 0 | AM92: 0 | AN92: 0 | AO92: 0 | AP92: 0 | AQ92: 0 | AR92: 0 | AS92: 0 | AT92: 0 | AU92: 0 | AV92: 0 | AW92: 0 | AX92: 0
B93: 行74 | K93: 求和 | L93: 计算 | M93: 计算 | N93: 0 | O93: 0 | P93: 0 | Q93: 0 | R93: 0 | S93: 0 | T93: 0 | U93: 0 | V93: 0 | W93: 0 | X93: 0 | Y93: 0 | AA93: 0 | AB93: 0 | AC93: 0 | AD93: 0 | AE93: 0 | AF93: 0 | AG93: 0 | AH93: 0 | AI93: 0 | AJ93: 0 | AK93: 0 | AL93: 0 | AM93: 0 | AN93: 0 | AO93: 0 | AP93: 0 | AQ93: 0 | AR93: 0 | AS93: 0 | AT93: 0 | AU93: 0 | AV93: 0 | AW93: 0 | AX93: 0
B94: 行75 | K94: 求和 | L94: 计算 | M94: 计算 | N94: 0 | O94: 0 | P94: 0 | Q94: 0 | R94: 0 | S94: 0 | T94: 0 | U94: 0 | V94: 0 | W94: 0 | X94: 0 | Y94: 0 | AA94: 0 | AB94: 0 | AC94: 0 | AD94: 0 | AE94: 0 | AF94: 0 | AG94: 0 | AH94: 0 | AI94: 0 | AJ94: 0 | AK94: 0 | AL94: 0 | AM94: 0 | AN94: 0 | AO94: 0 | AP94: 0 | AQ94: 0 | AR94: 0 | AS94: 0 | AT94: 0 | AU94: 0 | AV94: 0 | AW94: 0 | AX94: 0
B95: 行76 | K95: 求和 | L95: 计算 | M95: 计算 | N95: 0 | O95: 0 | P95: 0 | Q95: 0 | R95: 0 | S95: 0 | T95: 0 | U95: 0 | V95: 0 | W95: 0 | X95: 0 | Y95: 0 | AA95: 0 | AB95: 0 | AC95: 0 | AD95: 0 | AE95: 0 | AF95: 0 | AG95: 0 | AH95: 0 | AI95: 0 | AJ95: 0 | AK95: 0 | AL95: 0 | AM95: 0 | AN95: 0 | AO95: 0 | AP95: 0 | AQ95: 0 | AR95: 0 | AS95: 0 | AT95: 0 | AU95: 0 | AV95: 0 | AW95: 0 | AX95: 0
B96: 行77 | K96: 求和 | L96: 计算 | M96: 计算 | N96: 0 | O96: 0 | P96: 0 | Q96: 0 | R96: 0 | S96: 0 | T96: 0 | U96: 0 | V96: 0 | W96: 0 | X96: 0 | Y96: 0 | AA96: 0 | AB96: 0 | AC96: 0 | AD96: 0 | AE96: 0 | AF96: 0 | AG96: 0 | AH96: 0 | AI96: 0 | AJ96: 0 | AK96: 0 | AL96: 0 | AM96: 0 | AN96: 0 | AO96: 0 | AP96: 0 | AQ96: 0 | AR96: 0 | AS96: 0 | AT96: 0 | AU96: 0 | AV96: 0 | AW96: 0 | AX96: 0
B97: 行78 | K97: 求和 | L97: 计算 | M97: 计算 | N97: 0 | O97: 0 | P97: 0 | Q97: 0 | R97: 0 | S97: 0 | T97: 0 | U97: 0 | V97: 0 | W97: 0 | X97: 0 | Y97: 0 | AA97: 0 | AB97: 0 | AC97: 0 | AD97: 0 | AE97: 0 | AF97: 0 | AG97: 0 | AH97: 0 | AI97: 0 | AJ97: 0 | AK97: 0 | AL97: 0 | AM97: 0 | AN97: 0 | AO97: 0 | AP97: 0 | AQ97: 0 | AR97: 0 | AS97: 0 | AT97: 0 | AU97: 0 | AV97: 0 | AW97: 0 | AX97: 0
B98: 行79 | K98: 求和 | L98: 计算 | M98: 计算 | N98: 0 | O98: 0 | P98: 0 | Q98: 0 | R98: 0 | S98: 0 | T98: 0 | U98: 0 | V98: 0 | W98: 0 | X98: 0 | Y98: 0 | AA98: 0 | AB98: 0 | AC98: 0 | AD98: 0 | AE98: 0 | AF98: 0 | AG98: 0 | AH98: 0 | AI98: 0 | AJ98: 0 | AK98: 0 | AL98: 0 | AM98: 0 | AN98: 0 | AO98: 0 | AP98: 0 | AQ98: 0 | AR98: 0 | AS98: 0 | AT98: 0 | AU98: 0 | AV98: 0 | AW98: 0 | AX98: 0
B99: 行80 | K99: 求和 | L99: 计算 | M99: 计算 | N99: 0 | O99: 0 | P99: 0 | Q99: 0 | R99: 0 | S99: 0 | T99: 0 | U99: 0 | V99: 0 | W99: 0 | X99: 0 | Y99: 0 | AA99: 0 | AB99: 0 | AC99: 0 | AD99: 0 | AE99: 0 | AF99: 0 | AG99: 0 | AH99: 0 | AI99: 0 | AJ99: 0 | AK99: 0 | AL99: 0 | AM99: 0 | AN99: 0 | AO99: 0 | AP99: 0 | AQ99: 0 | AR99: 0 | AS99: 0 | AT99: 0 | AU99: 0 | AV99: 0 | AW99: 0 | AX99: 0
... B119: 行100 | K119: 求和 | L119: 计算 | M119: 计算 | N119: 0 | O119: 0 | P119: 0 | Q119: 0 | R119: 0 | S119: 0 | T119: 0 | U119: 0 | V119: 0 | W119: 0 | X119: 0 | Y119: 0 | AA119: 0 | AB119: 0 | AC119: 0 | AD119: 0 | AE119: 0 | AF119: 0 | AG119: 0 | AH119: 0 | AI119: 0 | AJ119: 0 | AK119: 0 | AL119: 0 | AM119: 0 | AN119: 0 | AO119: 0 | AP119: 0 | AQ119: 0 | AR119: 0 | AS119: 0 | AT119: 0 | AU119: 0 | AV119: 0 | AW119: 0 | AX119: 0

Sheet 填写-动保销售额（除发酵料）删除-动保公司填写
A1: ← 返回目录 | B1: CUBE: | C1: TONGWEI:02外销量（按客户）-导入
B2: 币种 | C2: Local
B3: 新老客户 | C3: 老客户
B4: 备用维1 | C4: 备用1不区分
B5: 备用维2 | C5: 备用2不区分
B6: 科目 | C6: 外销量
B7: 输入项 | C7: 值
B11: F0100xxx动保销售额录入表（除发酵料外） | F11: 填录说明： | G11: 第一步，选择年、公司、版本、场景；
G12: 第二步，下拉选择客户名称、产品系列；
G13: 第三步，系统将显示上年销售额，按照产品系列分月填录销售额数据；
G14: 第四步，填制数据完成后，单击【提交】按钮，将数据提交至系统。
B15: 责任部门：营销部
F16: 单位：元
G17: 0
AN18: .
B19: 年 | C19: 2026年 | D19: 公司 | E19: xx澳华 | F19: 版本 | G19: V1 | H19: 场景 | I19: 年度
B21: 行 | C21: 客户编码 | D21: 客户 | E21: 大类 | F21: 产品系列编码 | G21: 产品系列 | H21: 2025年销售额合计 | I21: 2026年销售额合计 | J21: 同比增减额 | K21: 同比增减率 | L21: 2026年预算数 | Y21: 2025年销售额 | AK21: 同比
L22: 1月 | M22: 2月 | N22: 3月 | O22: 4月 | P22: 5月 | Q22: 6月 | R22: 7月 | S22: 8月 | T22: 9月 | U22: 10月 | V22: 11月 | W22: 12月 | X22: 备注 | Y22: 1月 | Z22: 2月 | AA22: 3月 | AB22: 4月 | AC22: 5月 | AD22: 6月 | AE22: 7月 | AF22: 8月 | AG22: 9月 | AH22: 10月 | AI22: 11月 | AJ22: 12月 | AK22: 1月 | AL22: 2月 | AM22: 3月 | AN22: 4月 | AO22: 5月 | AP22: 6月 | AQ22: 7月 | AR22: 8月 | AS22: 9月 | AT22: 10月 | AU22: 11月 | AV22: 12月
C23: 自动生成 | D23: 选择 | E23: 自动生成 | F23: 自动生成 | G23: 选择 | H23: 自动生成 | I23: 求和 | J23: 计算 | K23: 计算 | L23: 填入 | M23: 填入 | N23: 填入 | O23: 填入 | P23: 填入 | Q23: 填入 | R23: 填入 | S23: 填入 | T23: 填入 | U23: 填入 | V23: 填入 | W23: 填入 | X23: 填入 | Y23: 自动生成 | Z23: 自动生成 | AA23: 自动生成 | AB23: 自动生成 | AC23: 自动生成 | AD23: 自动生成 | AE23: 自动生成 | AF23: 自动生成 | AG23: 自动生成 | AH23: 自动生成 | AI23: 自动生成 | AJ23: 自动生成 | AK23: 计算 | AL23: 计算 | AM23: 计算 | AN23: 计算 | AO23: 计算 | AP23: 计算 | AQ23: 计算 | AR23: 计算 | AS23: 计算 | AT23: 计算 | AU23: 计算 | AV23: 计算
B24: 合计 | C24: / | D24: / | E24: / | F24: / | G24: / | I24: 求和 | J24: 计算 | K24: 计算 | L24: 求和 | M24: 求和 | N24: 求和 | O24: 求和 | P24: 求和 | Q24: 求和 | R24: 求和 | S24: 求和 | T24: 求和 | U24: 求和 | V24: 求和 | W24: 求和 | Y24: 求和 | Z24: 求和 | AA24: 求和 | AB24: 求和 | AC24: 求和 | AD24: 求和 | AE24: 求和 | AF24: 求和 | AG24: 求和 | AH24: 求和 | AI24: 求和 | AJ24: 求和 | AK24: 求和 | AL24: 求和 | AM24: 求和 | AN24: 求和 | AO24: 求和 | AP24: 求和 | AQ24: 求和 | AR24: 求和 | AS24: 求和 | AT24: 求和 | AU24: 求和 | AV24: 求和
B25: 行1 | E25: 软颗粒 | G25: 肽康宝 | I25: 求和 | J25: 计算 | K25: 计算
B26: 行2 | G26: 虾酸奶 | I26: 求和 | J26: 计算 | K26: 计算
B27: 行3 | E27: 常规动保 | I27: 求和 | J27: 计算 | K27: 计算
B28: 行4 | I28: 求和 | J28: 计算 | K28: 计算
B29: 行5 | I29: 求和 | J29: 计算 | K29: 计算
B30: 行6 | I30: 求和 | J30: 计算 | K30: 计算
B31: 行8 | I31: 求和 | J31: 计算 | K31: 计算
B32: 行9 | I32: 求和 | J32: 计算 | K32: 计算
B33: 行10 | I33: 求和 | J33: 计算 | K33: 计算
B34: 行11 | I34: 求和 | J34: 计算 | K34: 计算
B35: 行12 | I35: 求和 | J35: 计算 | K35: 计算
B36: 行13 | I36: 求和 | J36: 计算 | K36: 计算
B37: 行16 | I37: 求和 | J37: 计算 | K37: 计算
B38: 行17 | I38: 求和 | J38: 计算 | K38: 计算
B39: 行18 | I39: 求和 | J39: 计算 | K39: 计算
... B87: 行68 | I87: 求和 | J87: 计算 | K87: 计算
B88: 行69 | I88: 求和 | J88: 计算 | K88: 计算 | L88: 0 | M88: 0 | N88: 0 | O88: 0 | P88: 0 | Q88: 0 | R88: 0 | S88: 0 | T88: 0 | U88: 0 | V88: 0 | W88: 0 | Y88: 0 | Z88: 0 | AA88: 0 | AB88: 0 | AC88: 0 | AD88: 0 | AE88: 0 | AF88: 0 | AG88: 0 | AH88: 0 | AI88: 0 | AJ88: 0 | AK88: 0 | AL88: 0 | AM88: 0 | AN88: 0 | AO88: 0 | AP88: 0 | AQ88: 0 | AR88: 0 | AS88: 0 | AT88: 0 | AU88: 0 | AV88: 0
B89: 行70 | I89: 求和 | J89: 计算 | K89: 计算 | L89: 0 | M89: 0 | N89: 0 | O89: 0 | P89: 0 | Q89: 0 | R89: 0 | S89: 0 | T89: 0 | U89: 0 | V89: 0 | W89: 0 | Y89: 0 | Z89: 0 | AA89: 0 | AB89: 0 | AC89: 0 | AD89: 0 | AE89: 0 | AF89: 0 | AG89: 0 | AH89: 0 | AI89: 0 | AJ89: 0 | AK89: 0 | AL89: 0 | AM89: 0 | AN89: 0 | AO89: 0 | AP89: 0 | AQ89: 0 | AR89: 0 | AS89: 0 | AT89: 0 | AU89: 0 | AV89: 0
B90: 行71 | I90: 求和 | J90: 计算 | K90: 计算 | L90: 0 | M90: 0 | N90: 0 | O90: 0 | P90: 0 | Q90: 0 | R90: 0 | S90: 0 | T90: 0 | U90: 0 | V90: 0 | W90: 0 | Y90: 0 | Z90: 0 | AA90: 0 | AB90: 0 | AC90: 0 | AD90: 0 | AE90: 0 | AF90: 0 | AG90: 0 | AH90: 0 | AI90: 0 | AJ90: 0 | AK90: 0 | AL90: 0 | AM90: 0 | AN90: 0 | AO90: 0 | AP90: 0 | AQ90: 0 | AR90: 0 | AS90: 0 | AT90: 0 | AU90: 0 | AV90: 0
B91: 行72 | I91: 求和 | J91: 计算 | K91: 计算 | L91: 0 | M91: 0 | N91: 0 | O91: 0 | P91: 0 | Q91: 0 | R91: 0 | S91: 0 | T91: 0 | U91: 0 | V91: 0 | W91: 0 | Y91: 0 | Z91: 0 | AA91: 0 | AB91: 0 | AC91: 0 | AD91: 0 | AE91: 0 | AF91: 0 | AG91: 0 | AH91: 0 | AI91: 0 | AJ91: 0 | AK91: 0 | AL91: 0 | AM91: 0 | AN91: 0 | AO91: 0 | AP91: 0 | AQ91: 0 | AR91: 0 | AS91: 0 | AT91: 0 | AU91: 0 | AV91: 0
B92: 行73 | I92: 求和 | J92: 计算 | K92: 计算 | L92: 0 | M92: 0 | N92: 0 | O92: 0 | P92: 0 | Q92: 0 | R92: 0 | S92: 0 | T92: 0 | U92: 0 | V92: 0 | W92: 0 | Y92: 0 | Z92: 0 | AA92: 0 | AB92: 0 | AC92: 0 | AD92: 0 | AE92: 0 | AF92: 0 | AG92: 0 | AH92: 0 | AI92: 0 | AJ92: 0 | AK92: 0 | AL92: 0 | AM92: 0 | AN92: 0 | AO92: 0 | AP92: 0 | AQ92: 0 | AR92: 0 | AS92: 0 | AT92: 0 | AU92: 0 | AV92: 0
B93: 行74 | I93: 求和 | J93: 计算 | K93: 计算 | L93: 0 | M93: 0 | N93: 0 | O93: 0 | P93: 0 | Q93: 0 | R93: 0 | S93: 0 | T93: 0 | U93: 0 | V93: 0 | W93: 0 | Y93: 0 | Z93: 0 | AA93: 0 | AB93: 0 | AC93: 0 | AD93: 0 | AE93: 0 | AF93: 0 | AG93: 0 | AH93: 0 | AI93: 0 | AJ93: 0 | AK93: 0 | AL93: 0 | AM93: 0 | AN93: 0 | AO93: 0 | AP93: 0 | AQ93: 0 | AR93: 0 | AS93: 0 | AT93: 0 | AU93: 0 | AV93: 0
B94: 行75 | I94: 求和 | J94: 计算 | K94: 计算 | L94: 0 | M94: 0 | N94: 0 | O94: 0 | P94: 0 | Q94: 0 | R94: 0 | S94: 0 | T94: 0 | U94: 0 | V94: 0 | W94: 0 | Y94: 0 | Z94: 0 | AA94: 0 | AB94: 0 | AC94: 0 | AD94: 0 | AE94: 0 | AF94: 0 | AG94: 0 | AH94: 0 | AI94: 0 | AJ94: 0 | AK94: 0 | AL94: 0 | AM94: 0 | AN94: 0 | AO94: 0 | AP94: 0 | AQ94: 0 | AR94: 0 | AS94: 0 | AT94: 0 | AU94: 0 | AV94: 0
B95: 行76 | I95: 求和 | J95: 计算 | K95: 计算 | L95: 0 | M95: 0 | N95: 0 | O95: 0 | P95: 0 | Q95: 0 | R95: 0 | S95: 0 | T95: 0 | U95: 0 | V95: 0 | W95: 0 | Y95: 0 | Z95: 0 | AA95: 0 | AB95: 0 | AC95: 0 | AD95: 0 | AE95: 0 | AF95: 0 | AG95: 0 | AH95: 0 | AI95: 0 | AJ95: 0 | AK95: 0 | AL95: 0 | AM95: 0 | AN95: 0 | AO95: 0 | AP95: 0 | AQ95: 0 | AR95: 0 | AS95: 0 | AT95: 0 | AU95: 0 | AV95: 0
B96: 行77 | I96: 求和 | J96: 计算 | K96: 计算 | L96: 0 | M96: 0 | N96: 0 | O96: 0 | P96: 0 | Q96: 0 | R96: 0 | S96: 0 | T96: 0 | U96: 0 | V96: 0 | W96: 0 | Y96: 0 | Z96: 0 | AA96: 0 | AB96: 0 | AC96: 0 | AD96: 0 | AE96: 0 | AF96: 0 | AG96: 0 | AH96: 0 | AI96: 0 | AJ96: 0 | AK96: 0 | AL96: 0 | AM96: 0 | AN96: 0 | AO96: 0 | AP96: 0 | AQ96: 0 | AR96: 0 | AS96: 0 | AT96: 0 | AU96: 0 | AV96: 0
B97: 行78 | I97: 求和 | J97: 计算 | K97: 计算 | L97: 0 | M97: 0 | N97: 0 | O97: 0 | P97: 0 | Q97: 0 | R97: 0 | S97: 0 | T97: 0 | U97: 0 | V97: 0 | W97: 0 | Y97: 0 | Z97: 0 | AA97: 0 | AB97: 0 | AC97: 0 | AD97: 0 | AE97: 0 | AF97: 0 | AG97: 0 | AH97: 0 | AI97: 0 | AJ97: 0 | AK97: 0 | AL97: 0 | AM97: 0 | AN97: 0 | AO97: 0 | AP97: 0 | AQ97: 0 | AR97: 0 | AS97: 0 | AT97: 0 | AU97: 0 | AV97: 0
B98: 行79 | I98: 求和 | J98: 计算 | K98: 计算 | L98: 0 | M98: 0 | N98: 0 | O98: 0 | P98: 0 | Q98: 0 | R98: 0 | S98: 0 | T98: 0 | U98: 0 | V98: 0 | W98: 0 | Y98: 0 | Z98: 0 | AA98: 0 | AB98: 0 | AC98: 0 | AD98: 0 | AE98: 0 | AF98: 0 | AG98: 0 | AH98: 0 | AI98: 0 | AJ98: 0 | AK98: 0 | AL98: 0 | AM98: 0 | AN98: 0 | AO98: 0 | AP98: 0 | AQ98: 0 | AR98: 0 | AS98: 0 | AT98: 0 | AU98: 0 | AV98: 0
B99: 行80 | I99: 求和 | J99: 计算 | K99: 计算 | L99: 0 | M99: 0 | N99: 0 | O99: 0 | P99: 0 | Q99: 0 | R99: 0 | S99: 0 | T99: 0 | U99: 0 | V99: 0 | W99: 0 | Y99: 0 | Z99: 0 | AA99: 0 | AB99: 0 | AC99: 0 | AD99: 0 | AE99: 0 | AF99: 0 | AG99: 0 | AH99: 0 | AI99: 0 | AJ99: 0 | AK99: 0 | AL99: 0 | AM99: 0 | AN99: 0 | AO99: 0 | AP99: 0 | AQ99: 0 | AR99: 0 | AS99: 0 | AT99: 0 | AU99: 0 | AV99: 0
... B119: 行100 | I119: 求和 | J119: 计算 | K119: 计算 | L119: 0 | M119: 0 | N119: 0 | O119: 0 | P119: 0 | Q119: 0 | R119: 0 | S119: 0 | T119: 0 | U119: 0 | V119: 0 | W119: 0 | Y119: 0 | Z119: 0 | AA119: 0 | AB119: 0 | AC119: 0 | AD119: 0 | AE119: 0 | AF119: 0 | AG119: 0 | AH119: 0 | AI119: 0 | AJ119: 0 | AK119: 0 | AL119: 0 | AM119: 0 | AN119: 0 | AO119: 0 | AP119: 0 | AQ119: 0 | AR119: 0 | AS119: 0 | AT119: 0 | AU119: 0 | AV119: 0

Sheet 填写-动保销量（发酵料）删除--动保公司填写
A1: ← 返回目录 | B1: CUBE: | C1: TONGWEI:02外销量（按客户）-导入
B2: 币种 | C2: Local
B3: 新老客户 | C3: 老客户
B4: 备用维1 | C4: 备用1不区分
B5: 备用维2 | C5: 备用2不区分
B6: 科目 | C6: 外销量
B7: 输入项 | C7: 值
B11: F0100xxx动保发酵料录入表 | F11: 填录说明： | G11: 第一步，选择年、公司、版本、场景；
G12: 第二步，下拉选择客户名称、产品系列；
G13: 第三步，系统将显示上年销售吨位，按照产品系列分月填录销量数据；
G14: 第四步，填制数据完成后，单击【提交】按钮，将数据提交至系统。
B15: 责任部门：营销部
F16: 单位：吨
G17: 0
AN18: .
B19: 年 | C19: 2026年 | D19: 公司 | E19: xx澳华 | F19: 版本 | G19: V1 | H19: 场景 | I19: 年度
B21: 行 | C21: 客户编码 | D21: 客户 | E21: 大类 | F21: 产品系列编码 | G21: 产品系列 | H21: 2025年销量合计 | I21: 2026年销量合计 | J21: 同比增减额 | K21: 同比增减率 | L21: 2026年预算数 | Y21: 2025年实际数 | AK21: 同比
L22: 1月 | M22: 2月 | N22: 3月 | O22: 4月 | P22: 5月 | Q22: 6月 | R22: 7月 | S22: 8月 | T22: 9月 | U22: 10月 | V22: 11月 | W22: 12月 | X22: 备注 | Y22: 1月 | Z22: 2月 | AA22: 3月 | AB22: 4月 | AC22: 5月 | AD22: 6月 | AE22: 7月 | AF22: 8月 | AG22: 9月 | AH22: 10月 | AI22: 11月 | AJ22: 12月 | AK22: 1月 | AL22: 2月 | AM22: 3月 | AN22: 4月 | AO22: 5月 | AP22: 6月 | AQ22: 7月 | AR22: 8月 | AS22: 9月 | AT22: 10月 | AU22: 11月 | AV22: 12月
C23: 自动生成 | D23: 选择 | E23: 自动生成 | F23: 自动生成 | G23: 选择 | H23: 自动生成 | I23: 求和 | J23: 计算 | K23: 计算 | L23: 填入 | M23: 填入 | N23: 填入 | O23: 填入 | P23: 填入 | Q23: 填入 | R23: 填入 | S23: 填入 | T23: 填入 | U23: 填入 | V23: 填入 | W23: 填入 | X23: 填入 | Y23: 自动生成 | Z23: 自动生成 | AA23: 自动生成 | AB23: 自动生成 | AC23: 自动生成 | AD23: 自动生成 | AE23: 自动生成 | AF23: 自动生成 | AG23: 自动生成 | AH23: 自动生成 | AI23: 自动生成 | AJ23: 自动生成 | AK23: 计算 | AL23: 计算 | AM23: 计算 | AN23: 计算 | AO23: 计算 | AP23: 计算 | AQ23: 计算 | AR23: 计算 | AS23: 计算 | AT23: 计算 | AU23: 计算 | AV23: 计算
B24: 合计 | C24: / | D24: / | E24: / | F24: / | G24: / | I24: 求和 | J24: 计算 | K24: 计算 | L24: 求和 | M24: 求和 | N24: 求和 | O24: 求和 | P24: 求和 | Q24: 求和 | R24: 求和 | S24: 求和 | T24: 求和 | U24: 求和 | V24: 求和 | W24: 求和 | Y24: 求和 | Z24: 求和 | AA24: 求和 | AB24: 求和 | AC24: 求和 | AD24: 求和 | AE24: 求和 | AF24: 求和 | AG24: 求和 | AH24: 求和 | AI24: 求和 | AJ24: 求和 | AK24: 求和 | AL24: 求和 | AM24: 求和 | AN24: 求和 | AO24: 求和 | AP24: 求和 | AQ24: 求和 | AR24: 求和 | AS24: 求和 | AT24: 求和 | AU24: 求和 | AV24: 求和
B25: 行1 | E25: 软颗粒 | G25: 肽康宝 | I25: 求和 | J25: 计算 | K25: 计算
B26: 行2 | G26: 虾酸奶 | I26: 求和 | J26: 计算 | K26: 计算
B27: 行3 | E27: 常规动保 | I27: 求和 | J27: 计算 | K27: 计算
B28: 行4 | I28: 求和 | J28: 计算 | K28: 计算
B29: 行5 | I29: 求和 | J29: 计算 | K29: 计算
B30: 行6 | I30: 求和 | J30: 计算 | K30: 计算
B31: 行8 | I31: 求和 | J31: 计算 | K31: 计算
B32: 行9 | I32: 求和 | J32: 计算 | K32: 计算
B33: 行10 | I33: 求和 | J33: 计算 | K33: 计算
B34: 行11 | I34: 求和 | J34: 计算 | K34: 计算
B35: 行12 | I35: 求和 | J35: 计算 | K35: 计算
B36: 行13 | I36: 求和 | J36: 计算 | K36: 计算
B37: 行16 | I37: 求和 | J37: 计算 | K37: 计算
B38: 行17 | I38: 求和 | J38: 计算 | K38: 计算
B39: 行18 | I39: 求和 | J39: 计算 | K39: 计算
... B87: 行68 | I87: 求和 | J87: 计算 | K87: 计算
B88: 行69 | I88: 求和 | J88: 计算 | K88: 计算 | L88: 0 | M88: 0 | N88: 0 | O88: 0 | P88: 0 | Q88: 0 | R88: 0 | S88: 0 | T88: 0 | U88: 0 | V88: 0 | W88: 0 | Y88: 0 | Z88: 0 | AA88: 0 | AB88: 0 | AC88: 0 | AD88: 0 | AE88: 0 | AF88: 0 | AG88: 0 | AH88: 0 | AI88: 0 | AJ88: 0 | AK88: 0 | AL88: 0 | AM88: 0 | AN88: 0 | AO88: 0 | AP88: 0 | AQ88: 0 | AR88: 0 | AS88: 0 | AT88: 0 | AU88: 0 | AV88: 0
B89: 行70 | I89: 求和 | J89: 计算 | K89: 计算 | L89: 0 | M89: 0 | N89: 0 | O89: 0 | P89: 0 | Q89: 0 | R89: 0 | S89: 0 | T89: 0 | U89: 0 | V89: 0 | W89: 0 | Y89: 0 | Z89: 0 | AA89: 0 | AB89: 0 | AC89: 0 | AD89: 0 | AE89: 0 | AF89: 0 | AG89: 0 | AH89: 0 | AI89: 0 | AJ89: 0 | AK89: 0 | AL89: 0 | AM89: 0 | AN89: 0 | AO89: 0 | AP89: 0 | AQ89: 0 | AR89: 0 | AS89: 0 | AT89: 0 | AU89: 0 | AV89: 0
B90: 行71 | I90: 求和 | J90: 计算 | K90: 计算 | L90: 0 | M90: 0 | N90: 0 | O90: 0 | P90: 0 | Q90: 0 | R90: 0 | S90: 0 | T90: 0 | U90: 0 | V90: 0 | W90: 0 | Y90: 0 | Z90: 0 | AA90: 0 | AB90: 0 | AC90: 0 | AD90: 0 | AE90: 0 | AF90: 0 | AG90: 0 | AH90: 0 | AI90: 0 | AJ90: 0 | AK90: 0 | AL90: 0 | AM90: 0 | AN90: 0 | AO90: 0 | AP90: 0 | AQ90: 0 | AR90: 0 | AS90: 0 | AT90: 0 | AU90: 0 | AV90: 0
B91: 行72 | I91: 求和 | J91: 计算 | K91: 计算 | L91: 0 | M91: 0 | N91: 0 | O91: 0 | P91: 0 | Q91: 0 | R91: 0 | S91: 0 | T91: 0 | U91: 0 | V91: 0 | W91: 0 | Y91: 0 | Z91: 0 | AA91: 0 | AB91: 0 | AC91: 0 | AD91: 0 | AE91: 0 | AF91: 0 | AG91: 0 | AH91: 0 | AI91: 0 | AJ91: 0 | AK91: 0 | AL91: 0 | AM91: 0 | AN91: 0 | AO91: 0 | AP91: 0 | AQ91: 0 | AR91: 0 | AS91: 0 | AT91: 0 | AU91: 0 | AV91: 0
B92: 行73 | I92: 求和 | J92: 计算 | K92: 计算 | L92: 0 | M92: 0 | N92: 0 | O92: 0 | P92: 0 | Q92: 0 | R92: 0 | S92: 0 | T92: 0 | U92: 0 | V92: 0 | W92: 0 | Y92: 0 | Z92: 0 | AA92: 0 | AB92: 0 | AC92: 0 | AD92: 0 | AE92: 0 | AF92: 0 | AG92: 0 | AH92: 0 | AI92: 0 | AJ92: 0 | AK92: 0 | AL92: 0 | AM92: 0 | AN92: 0 | AO92: 0 | AP92: 0 | AQ92: 0 | AR92: 0 | AS92: 0 | AT92: 0 | AU92: 0 | AV92: 0
B93: 行74 | I93: 求和 | J93: 计算 | K93: 计算 | L93: 0 | M93: 0 | N93: 0 | O93: 0 | P93: 0 | Q93: 0 | R93: 0 | S93: 0 | T93: 0 | U93: 0 | V93: 0 | W93: 0 | Y93: 0 | Z93: 0 | AA93: 0 | AB93: 0 | AC93: 0 | AD93: 0 | AE93: 0 | AF93: 0 | AG93: 0 | AH93: 0 | AI93: 0 | AJ93: 0 | AK93: 0 | AL93: 0 | AM93: 0 | AN93: 0 | AO93: 0 | AP93: 0 | AQ93: 0 | AR93: 0 | AS93: 0 | AT93: 0 | AU93: 0 | AV93: 0
B94: 行75 | I94: 求和 | J94: 计算 | K94: 计算 | L94: 0 | M94: 0 | N94: 0 | O94: 0 | P94: 0 | Q94: 0 | R94: 0 | S94: 0 | T94: 0 | U94: 0 | V94: 0 | W94: 0 | Y94: 0 | Z94: 0 | AA94: 0 | AB94: 0 | AC94: 0 | AD94: 0 | AE94: 0 | AF94: 0 | AG94: 0 | AH94: 0 | AI94: 0 | AJ94: 0 | AK94: 0 | AL94: 0 | AM94: 0 | AN94: 0 | AO94: 0 | AP94: 0 | AQ94: 0 | AR94: 0 | AS94: 0 | AT94: 0 | AU94: 0 | AV94: 0
B95: 行76 | I95: 求和 | J95: 计算 | K95: 计算 | L95: 0 | M95: 0 | N95: 0 | O95: 0 | P95: 0 | Q95: 0 | R95: 0 | S95: 0 | T95: 0 | U95: 0 | V95: 0 | W95: 0 | Y95: 0 | Z95: 0 | AA95: 0 | AB95: 0 | AC95: 0 | AD95: 0 | AE95: 0 | AF95: 0 | AG95: 0 | AH95: 0 | AI95: 0 | AJ95: 0 | AK95: 0 | AL95: 0 | AM95: 0 | AN95: 0 | AO95: 0 | AP95: 0 | AQ95: 0 | AR95: 0 | AS95: 0 | AT95: 0 | AU95: 0 | AV95: 0
B96: 行77 | I96: 求和 | J96: 计算 | K96: 计算 | L96: 0 | M96: 0 | N96: 0 | O96: 0 | P96: 0 | Q96: 0 | R96: 0 | S96: 0 | T96: 0 | U96: 0 | V96: 0 | W96: 0 | Y96: 0 | Z96: 0 | AA96: 0 | AB96: 0 | AC96: 0 | AD96: 0 | AE96: 0 | AF96: 0 | AG96: 0 | AH96: 0 | AI96: 0 | AJ96: 0 | AK96: 0 | AL96: 0 | AM96: 0 | AN96: 0 | AO96: 0 | AP96: 0 | AQ96: 0 | AR96: 0 | AS96: 0 | AT96: 0 | AU96: 0 | AV96: 0
B97: 行78 | I97: 求和 | J97: 计算 | K97: 计算 | L97: 0 | M97: 0 | N97: 0 | O97: 0 | P97: 0 | Q97: 0 | R97: 0 | S97: 0 | T97: 0 | U97: 0 | V97: 0 | W97: 0 | Y97: 0 | Z97: 0 | AA97: 0 | AB97: 0 | AC97: 0 | AD97: 0 | AE97: 0 | AF97: 0 | AG97: 0 | AH97: 0 | AI97: 0 | AJ97: 0 | AK97: 0 | AL97: 0 | AM97: 0 | AN97: 0 | AO97: 0 | AP97: 0 | AQ97: 0 | AR97: 0 | AS97: 0 | AT97: 0 | AU97: 0 | AV97: 0
B98: 行79 | I98: 求和 | J98: 计算 | K98: 计算 | L98: 0 | M98: 0 | N98: 0 | O98: 0 | P98: 0 | Q98: 0 | R98: 0 | S98: 0 | T98: 0 | U98: 0 | V98: 0 | W98: 0 | Y98: 0 | Z98: 0 | AA98: 0 | AB98: 0 | AC98: 0 | AD98: 0 | AE98: 0 | AF98: 0 | AG98: 0 | AH98: 0 | AI98: 0 | AJ98: 0 | AK98: 0 | AL98: 0 | AM98: 0 | AN98: 0 | AO98: 0 | AP98: 0 | AQ98: 0 | AR98: 0 | AS98: 0 | AT98: 0 | AU98: 0 | AV98: 0
B99: 行80 | I99: 求和 | J99: 计算 | K99: 计算 | L99: 0 | M99: 0 | N99: 0 | O99: 0 | P99: 0 | Q99: 0 | R99: 0 | S99: 0 | T99: 0 | U99: 0 | V99: 0 | W99: 0 | Y99: 0 | Z99: 0 | AA99: 0 | AB99: 0 | AC99: 0 | AD99: 0 | AE99: 0 | AF99: 0 | AG99: 0 | AH99: 0 | AI99: 0 | AJ99: 0 | AK99: 0 | AL99: 0 | AM99: 0 | AN99: 0 | AO99: 0 | AP99: 0 | AQ99: 0 | AR99: 0 | AS99: 0 | AT99: 0 | AU99: 0 | AV99: 0
... B119: 行100 | I119: 求和 | J119: 计算 | K119: 计算 | L119: 0 | M119: 0 | N119: 0 | O119: 0 | P119: 0 | Q119: 0 | R119: 0 | S119: 0 | T119: 0 | U119: 0 | V119: 0 | W119: 0 | Y119: 0 | Z119: 0 | AA119: 0 | AB119: 0 | AC119: 0 | AD119: 0 | AE119: 0 | AF119: 0 | AG119: 0 | AH119: 0 | AI119: 0 | AJ119: 0 | AK119: 0 | AL119: 0 | AM119: 0 | AN119: 0 | AO119: 0 | AP119: 0 | AQ119: 0 | AR119: 0 | AS119: 0 | AT119: 0 | AU119: 0 | AV119: 0

Sheet 填写-动保成本（除发酵料）--动保公司填写
A1: ← 返回目录 | B1: CUBE: | C1: TONGWEI:02外销量（按客户）-导入
B2: 币种 | C2: Local
B3: 新老客户 | C3: 老客户
B4: 备用维1 | C4: 备用1不区分
B5: 备用维2 | C5: 备用2不区分
B6: 科目 | C6: 外销量
B7: 输入项 | C7: 值
B11: F0100xxx动保成本录入表（除发酵料外） | F11: 填录说明： | G11: 第一步，选择年、公司、版本、场景；
G12: 第二步，自动生成饲料公司及动保公司填报的销售额数据；
G13: 第三步，按产品系列分月填录成本、毛利数据；
G14: 第四步，填制数据完成后，单击【提交】按钮，将数据提交至系统。
B15: 责任部门：营销部
F16: 单位：元
G17: 0
AL18: .
B19: 年 | C19: 2026年 | D19: 公司 | E19: xx澳华 | F19: 版本 | G19: V1 | H19: 场景 | I19: 年度
B21: 公司 | C21: 大类 | D21: 产品系列编码 | E21: 产品系列 | F21: 2025年总销售额 | G21: 2026年总销售额 | H21: 总销售额同比 | I21: 销售额 | U21: 2025年总成本 | V21: 2026年总成本 | W21: 总成本同比 | X21: 总成本 | AJ21: 2025年总毛利额 | AK21: 2026年总毛利额 | AL21: 总毛利额同比 | AM21: 毛利额
I22: 1月 | J22: 2月 | K22: 3月 | L22: 4月 | M22: 5月 | N22: 6月 | O22: 7月 | P22: 8月 | Q22: 9月 | R22: 10月 | S22: 11月 | T22: 12月 | X22: 1月 | Y22: 2月 | Z22: 3月 | AA22: 4月 | AB22: 5月 | AC22: 6月 | AD22: 7月 | AE22: 8月 | AF22: 9月 | AG22: 10月 | AH22: 11月 | AI22: 12月 | AM22: 1月 | AN22: 2月 | AO22: 3月 | AP22: 4月 | AQ22: 5月 | AR22: 6月 | AS22: 7月 | AT22: 8月 | AU22: 9月 | AV22: 10月 | AW22: 11月 | AX22: 12月
B23: 自动生成 | C23: 自动生成 | D23: 自动生成 | E23: 自动生成 | F23: 计算 | G23: 计算 | H23: 计算 | I23: 自动生成 | J23: 自动生成 | K23: 自动生成 | L23: 自动生成 | M23: 自动生成 | N23: 自动生成 | O23: 自动生成 | P23: 自动生成 | Q23: 自动生成 | R23: 自动生成 | S23: 自动生成 | T23: 自动生成 | U23: 计算 | V23: 计算 | W23: 计算 | X23: 填入 | Y23: 填入 | Z23: 填入 | AA23: 填入 | AB23: 填入 | AC23: 填入 | AD23: 填入 | AE23: 填入 | AF23: 填入 | AG23: 填入 | AH23: 填入 | AI23: 填入 | AJ23: 计算 | AK23: 计算 | AL23: 计算 | AM23: 计算 | AN23: 计算 | AO23: 计算 | AP23: 计算 | AQ23: 计算 | AR23: 计算 | AS23: 计算 | AT23: 计算 | AU23: 计算 | AV23: 计算 | AW23: 计算 | AX23: 计算
B24: 合计 | C24: / | D24: / | E24: / | F24: 计算 | G24: 计算 | H24: 计算 | I24: 求和 | J24: 求和 | K24: 求和 | L24: 求和 | M24: 求和 | N24: 求和 | O24: 求和 | P24: 求和 | Q24: 求和 | R24: 求和 | S24: 求和 | T24: 求和 | U24: 计算 | V24: 计算 | W24: 计算 | X24: 求和 | Y24: 求和 | Z24: 求和 | AA24: 求和 | AB24: 求和 | AC24: 求和 | AD24: 求和 | AE24: 求和 | AF24: 求和 | AG24: 求和 | AH24: 求和 | AI24: 求和 | AJ24: 计算 | AK24: 计算 | AL24: 计算 | AM24: 计算 | AN24: 计算 | AO24: 计算 | AP24: 计算 | AQ24: 计算 | AR24: 计算 | AS24: 计算 | AT24: 计算 | AU24: 计算 | AV24: 计算 | AW24: 计算 | AX24: 计算
C25: 软颗粒 | E25: 肽康宝 | F25: 计算 | G25: 计算 | H25: 计算 | U25: 计算 | V25: 计算 | W25: 计算 | AJ25: 计算 | AK25: 计算 | AL25: 计算
E26: 虾酸奶 | F26: 计算 | G26: 计算 | H26: 计算 | U26: 计算 | V26: 计算 | W26: 计算 | AJ26: 计算 | AK26: 计算 | AL26: 计算
C27: 常规动保 | F27: 计算 | G27: 计算 | H27: 计算 | U27: 计算 | V27: 计算 | W27: 计算 | AJ27: 计算 | AK27: 计算 | AL27: 计算
F28: 计算 | G28: 计算 | H28: 计算 | U28: 计算 | V28: 计算 | W28: 计算 | AJ28: 计算 | AK28: 计算 | AL28: 计算
F29: 计算 | G29: 计算 | H29: 计算 | U29: 计算 | V29: 计算 | W29: 计算 | AJ29: 计算 | AK29: 计算 | AL29: 计算
F30: 计算 | G30: 计算 | H30: 计算 | U30: 计算 | V30: 计算 | W30: 计算 | AJ30: 计算 | AK30: 计算 | AL30: 计算
F31: 计算 | G31: 计算 | H31: 计算 | U31: 计算 | V31: 计算 | W31: 计算 | AJ31: 计算 | AK31: 计算 | AL31: 计算
F32: 计算 | G32: 计算 | H32: 计算 | U32: 计算 | V32: 计算 | W32: 计算 | AJ32: 计算 | AK32: 计算 | AL32: 计算
F33: 计算 | G33: 计算 | H33: 计算 | U33: 计算 | V33: 计算 | W33: 计算 | AJ33: 计算 | AK33: 计算 | AL33: 计算
F34: 计算 | G34: 计算 | H34: 计算 | U34: 计算 | V34: 计算 | W34: 计算 | AJ34: 计算 | AK34: 计算 | AL34: 计算
F35: 计算 | G35: 计算 | H35: 计算 | U35: 计算 | V35: 计算 | W35: 计算 | AJ35: 计算 | AK35: 计算 | AL35: 计算
F36: 计算 | G36: 计算 | H36: 计算 | U36: 计算 | V36: 计算 | W36: 计算 | AJ36: 计算 | AK36: 计算 | AL36: 计算
F37: 计算 | G37: 计算 | H37: 计算 | U37: 计算 | V37: 计算 | W37: 计算 | AJ37: 计算 | AK37: 计算 | AL37: 计算
F38: 计算 | G38: 计算 | H38: 计算 | U38: 计算 | V38: 计算 | W38: 计算 | AJ38: 计算 | AK38: 计算 | AL38: 计算
F39: 计算 | G39: 计算 | H39: 计算 | U39: 计算 | V39: 计算 | W39: 计算 | AJ39: 计算 | AK39: 计算 | AL39: 计算
... F87: 计算 | G87: 计算 | H87: 计算 | U87: 计算 | V87: 计算 | W87: 计算 | AJ87: 计算 | AK87: 计算 | AL87: 计算
F88: 计算 | G88: 计算 | H88: 计算 | I88: 0 | J88: 0 | K88: 0 | L88: 0 | M88: 0 | N88: 0 | O88: 0 | P88: 0 | Q88: 0 | R88: 0 | S88: 0 | T88: 0 | U88: 计算 | V88: 计算 | W88: 计算 | X88: 0 | Y88: 0 | Z88: 0 | AA88: 0 | AB88: 0 | AC88: 0 | AD88: 0 | AE88: 0 | AF88: 0 | AG88: 0 | AH88: 0 | AI88: 0 | AJ88: 计算 | AK88: 计算 | AL88: 计算 | AM88: 0 | AN88: 0 | AO88: 0 | AP88: 0 | AQ88: 0 | AR88: 0 | AS88: 0 | AT88: 0 | AU88: 0 | AV88: 0 | AW88: 0 | AX88: 0
F89: 计算 | G89: 计算 | H89: 计算 | I89: 0 | J89: 0 | K89: 0 | L89: 0 | M89: 0 | N89: 0 | O89: 0 | P89: 0 | Q89: 0 | R89: 0 | S89: 0 | T89: 0 | U89: 计算 | V89: 计算 | W89: 计算 | X89: 0 | Y89: 0 | Z89: 0 | AA89: 0 | AB89: 0 | AC89: 0 | AD89: 0 | AE89: 0 | AF89: 0 | AG89: 0 | AH89: 0 | AI89: 0 | AJ89: 计算 | AK89: 计算 | AL89: 计算 | AM89: 0 | AN89: 0 | AO89: 0 | AP89: 0 | AQ89: 0 | AR89: 0 | AS89: 0 | AT89: 0 | AU89: 0 | AV89: 0 | AW89: 0 | AX89: 0
F90: 计算 | G90: 计算 | H90: 计算 | I90: 0 | J90: 0 | K90: 0 | L90: 0 | M90: 0 | N90: 0 | O90: 0 | P90: 0 | Q90: 0 | R90: 0 | S90: 0 | T90: 0 | U90: 计算 | V90: 计算 | W90: 计算 | X90: 0 | Y90: 0 | Z90: 0 | AA90: 0 | AB90: 0 | AC90: 0 | AD90: 0 | AE90: 0 | AF90: 0 | AG90: 0 | AH90: 0 | AI90: 0 | AJ90: 计算 | AK90: 计算 | AL90: 计算 | AM90: 0 | AN90: 0 | AO90: 0 | AP90: 0 | AQ90: 0 | AR90: 0 | AS90: 0 | AT90: 0 | AU90: 0 | AV90: 0 | AW90: 0 | AX90: 0
F91: 计算 | G91: 计算 | H91: 计算 | I91: 0 | J91: 0 | K91: 0 | L91: 0 | M91: 0 | N91: 0 | O91: 0 | P91: 0 | Q91: 0 | R91: 0 | S91: 0 | T91: 0 | U91: 计算 | V91: 计算 | W91: 计算 | X91: 0 | Y91: 0 | Z91: 0 | AA91: 0 | AB91: 0 | AC91: 0 | AD91: 0 | AE91: 0 | AF91: 0 | AG91: 0 | AH91: 0 | AI91: 0 | AJ91: 计算 | AK91: 计算 | AL91: 计算 | AM91: 0 | AN91: 0 | AO91: 0 | AP91: 0 | AQ91: 0 | AR91: 0 | AS91: 0 | AT91: 0 | AU91: 0 | AV91: 0 | AW91: 0 | AX91: 0
F92: 计算 | G92: 计算 | H92: 计算 | I92: 0 | J92: 0 | K92: 0 | L92: 0 | M92: 0 | N92: 0 | O92: 0 | P92: 0 | Q92: 0 | R92: 0 | S92: 0 | T92: 0 | U92: 计算 | V92: 计算 | W92: 计算 | X92: 0 | Y92: 0 | Z92: 0 | AA92: 0 | AB92: 0 | AC92: 0 | AD92: 0 | AE92: 0 | AF92: 0 | AG92: 0 | AH92: 0 | AI92: 0 | AJ92: 计算 | AK92: 计算 | AL92: 计算 | AM92: 0 | AN92: 0 | AO92: 0 | AP92: 0 | AQ92: 0 | AR92: 0 | AS92: 0 | AT92: 0 | AU92: 0 | AV92: 0 | AW92: 0 | AX92: 0
F93: 计算 | G93: 计算 | H93: 计算 | I93: 0 | J93: 0 | K93: 0 | L93: 0 | M93: 0 | N93: 0 | O93: 0 | P93: 0 | Q93: 0 | R93: 0 | S93: 0 | T93: 0 | U93: 计算 | V93: 计算 | W93: 计算 | X93: 0 | Y93: 0 | Z93: 0 | AA93: 0 | AB93: 0 | AC93: 0 | AD93: 0 | AE93: 0 | AF93: 0 | AG93: 0 | AH93: 0 | AI93: 0 | AJ93: 计算 | AK93: 计算 | AL93: 计算 | AM93: 0 | AN93: 0 | AO93: 0 | AP93: 0 | AQ93: 0 | AR93: 0 | AS93: 0 | AT93: 0 | AU93: 0 | AV93: 0 | AW93: 0 | AX93: 0
F94: 计算 | G94: 计算 | H94: 计算 | I94: 0 | J94: 0 | K94: 0 | L94: 0 | M94: 0 | N94: 0 | O94: 0 | P94: 0 | Q94: 0 | R94: 0 | S94: 0 | T94: 0 | U94: 计算 | V94: 计算 | W94: 计算 | X94: 0 | Y94: 0 | Z94: 0 | AA94: 0 | AB94: 0 | AC94: 0 | AD94: 0 | AE94: 0 | AF94: 0 | AG94: 0 | AH94: 0 | AI94: 0 | AJ94: 计算 | AK94: 计算 | AL94: 计算 | AM94: 0 | AN94: 0 | AO94: 0 | AP94: 0 | AQ94: 0 | AR94: 0 | AS94: 0 | AT94: 0 | AU94: 0 | AV94: 0 | AW94: 0 | AX94: 0
F95: 计算 | G95: 计算 | H95: 计算 | I95: 0 | J95: 0 | K95: 0 | L95: 0 | M95: 0 | N95: 0 | O95: 0 | P95: 0 | Q95: 0 | R95: 0 | S95: 0 | T95: 0 | U95: 计算 | V95: 计算 | W95: 计算 | X95: 0 | Y95: 0 | Z95: 0 | AA95: 0 | AB95: 0 | AC95: 0 | AD95: 0 | AE95: 0 | AF95: 0 | AG95: 0 | AH95: 0 | AI95: 0 | AJ95: 计算 | AK95: 计算 | AL95: 计算 | AM95: 0 | AN95: 0 | AO95: 0 | AP95: 0 | AQ95: 0 | AR95: 0 | AS95: 0 | AT95: 0 | AU95: 0 | AV95: 0 | AW95: 0 | AX95: 0
F96: 计算 | G96: 计算 | H96: 计算 | I96: 0 | J96: 0 | K96: 0 | L96: 0 | M96: 0 | N96: 0 | O96: 0 | P96: 0 | Q96: 0 | R96: 0 | S96: 0 | T96: 0 | U96: 计算 | V96: 计算 | W96: 计算 | X96: 0 | Y96: 0 | Z96: 0 | AA96: 0 | AB96: 0 | AC96: 0 | AD96: 0 | AE96: 0 | AF96: 0 | AG96: 0 | AH96: 0 | AI96: 0 | AJ96: 计算 | AK96: 计算 | AL96: 计算 | AM96: 0 | AN96: 0 | AO96: 0 | AP96: 0 | AQ96: 0 | AR96: 0 | AS96: 0 | AT96: 0 | AU96: 0 | AV96: 0 | AW96: 0 | AX96: 0
F97: 计算 | G97: 计算 | H97: 计算 | I97: 0 | J97: 0 | K97: 0 | L97: 0 | M97: 0 | N97: 0 | O97: 0 | P97: 0 | Q97: 0 | R97: 0 | S97: 0 | T97: 0 | U97: 计算 | V97: 计算 | W97: 计算 | X97: 0 | Y97: 0 | Z97: 0 | AA97: 0 | AB97: 0 | AC97: 0 | AD97: 0 | AE97: 0 | AF97: 0 | AG97: 0 | AH97: 0 | AI97: 0 | AJ97: 计算 | AK97: 计算 | AL97: 计算 | AM97: 0 | AN97: 0 | AO97: 0 | AP97: 0 | AQ97: 0 | AR97: 0 | AS97: 0 | AT97: 0 | AU97: 0 | AV97: 0 | AW97: 0 | AX97: 0
F98: 计算 | G98: 计算 | H98: 计算 | I98: 0 | J98: 0 | K98: 0 | L98: 0 | M98: 0 | N98: 0 | O98: 0 | P98: 0 | Q98: 0 | R98: 0 | S98: 0 | T98: 0 | U98: 计算 | V98: 计算 | W98: 计算 | X98: 0 | Y98: 0 | Z98: 0 | AA98: 0 | AB98: 0 | AC98: 0 | AD98: 0 | AE98: 0 | AF98: 0 | AG98: 0 | AH98: 0 | AI98: 0 | AJ98: 计算 | AK98: 计算 | AL98: 计算 | AM98: 0 | AN98: 0 | AO98: 0 | AP98: 0 | AQ98: 0 | AR98: 0 | AS98: 0 | AT98: 0 | AU98: 0 | AV98: 0 | AW98: 0 | AX98: 0
F99: 计算 | G99: 计算 | H99: 计算 | I99: 0 | J99: 0 | K99: 0 | L99: 0 | M99: 0 | N99: 0 | O99: 0 | P99: 0 | Q99: 0 | R99: 0 | S99: 0 | T99: 0 | U99: 计算 | V99: 计算 | W99: 计算 | X99: 0 | Y99: 0 | Z99: 0 | AA99: 0 | AB99: 0 | AC99: 0 | AD99: 0 | AE99: 0 | AF99: 0 | AG99: 0 | AH99: 0 | AI99: 0 | AJ99: 计算 | AK99: 计算 | AL99: 计算 | AM99: 0 | AN99: 0 | AO99: 0 | AP99: 0 | AQ99: 0 | AR99: 0 | AS99: 0 | AT99: 0 | AU99: 0 | AV99: 0 | AW99: 0 | AX99: 0
... F119: 计算 | G119: 计算 | H119: 计算 | I119: 0 | J119: 0 | K119: 0 | L119: 0 | M119: 0 | N119: 0 | O119: 0 | P119: 0 | Q119: 0 | R119: 0 | S119: 0 | T119: 0 | U119: 计算 | V119: 计算 | W119: 计算 | X119: 0 | Y119: 0 | Z119: 0 | AA119: 0 | AB119: 0 | AC119: 0 | AD119: 0 | AE119: 0 | AF119: 0 | AG119: 0 | AH119: 0 | AI119: 0 | AJ119: 计算 | AK119: 计算 | AL119: 计算 | AM119: 0 | AN119: 0 | AO119: 0 | AP119: 0 | AQ119: 0 | AR119: 0 | AS119: 0 | AT119: 0 | AU119: 0 | AV119: 0 | AW119: 0 | AX119: 0

Sheet 填写-动保成本（发酵料）--动保公司填写
A1: ← 返回目录 | B1: CUBE: | C1: TONGWEI:02外销量（按客户）-导入
B2: 币种 | C2: Local
B3: 新老客户 | C3: 老客户
B4: 备用维1 | C4: 备用1不区分
B5: 备用维2 | C5: 备用2不区分
B6: 科目 | C6: 外销量
B7: 输入项 | C7: 值
B11: F0100xxx动保发酵料成本录入表 | F11: 填录说明： | G11: 第一步，选择年、公司、版本、场景；
G12: 第二步，自动生成饲料公司及动保公司填报的销售吨数数据；
G13: 第三步，按照产品系列分月填录售价、成本、毛利数据；
G14: 第四步，填制数据完成后，单击【提交】按钮，将数据提交至系统。
B15: 责任部门：营销部
F16: 单位：吨
G17: 0
AM18: . | BB18: .
B19: 年 | C19: 2026年 | D19: 公司 | E19: xx澳华 | F19: 版本 | G19: V1 | H19: 场景 | I19: 年度
B21: 公司 | C21: 大类 | D21: 产品系列编码 | E21: 产品系列 | F21: 2025年销售吨数 | G21: 2026年销售吨数 | H21: 销售吨数同比 | I21: 2026年销售吨数 | U21: 2025年平均单吨售价 | V21: 2026年平均单吨售价 | W21: 平均单吨售价同比 | X21: 2026年吨售价 | AJ21: 2025年平均吨成本 | AK21: 2026年平均吨成本 | AL21: 平均吨成本同比 | AM21: 2026年吨成本 | AY21: 2025年平均吨毛利 | AZ21: 2026年平均吨毛利 | BA21: 吨毛利同比 | BB21: 2026年吨毛利
I22: 1月 | J22: 2月 | K22: 3月 | L22: 4月 | M22: 5月 | N22: 6月 | O22: 7月 | P22: 8月 | Q22: 9月 | R22: 10月 | S22: 11月 | T22: 12月 | X22: 1月 | Y22: 2月 | Z22: 3月 | AA22: 4月 | AB22: 5月 | AC22: 6月 | AD22: 7月 | AE22: 8月 | AF22: 9月 | AG22: 10月 | AH22: 11月 | AI22: 12月 | AM22: 1月 | AN22: 2月 | AO22: 3月 | AP22: 4月 | AQ22: 5月 | AR22: 6月 | AS22: 7月 | AT22: 8月 | AU22: 9月 | AV22: 10月 | AW22: 11月 | AX22: 12月 | BB22: 1月 | BC22: 2月 | BD22: 3月 | BE22: 4月 | BF22: 5月 | BG22: 6月 | BH22: 7月 | BI22: 8月 | BJ22: 9月 | BK22: 10月 | BL22: 11月 | BM22: 12月
B23: 自动生成 | C23: 自动生成 | D23: 自动生成 | E23: 自动生成 | F23: 自动生成 | G23: 求和 | H23: 计算 | I23: 自动生成 | J23: 自动生成 | K23: 自动生成 | L23: 自动生成 | M23: 自动生成 | N23: 自动生成 | O23: 自动生成 | P23: 自动生成 | Q23: 自动生成 | R23: 自动生成 | S23: 自动生成 | T23: 自动生成 | U23: 自动生成 | V23: 求和 | W23: 计算 | X23: 填入 | Y23: 填入 | Z23: 填入 | AA23: 填入 | AB23: 填入 | AC23: 填入 | AD23: 填入 | AE23: 填入 | AF23: 填入 | AG23: 填入 | AH23: 填入 | AI23: 填入 | AJ23: 自动生成 | AK23: 求和 | AL23: 计算 | AM23: 填入 | AN23: 填入 | AO23: 填入 | AP23: 填入 | AQ23: 填入 | AR23: 填入 | AS23: 填入 | AT23: 填入 | AU23: 填入 | AV23: 填入 | AW23: 填入 | AX23: 填入 | AY23: 自动生成 | AZ23: 求和 | BA23: 计算 | BB23: 计算 | BC23: 计算 | BD23: 计算 | BE23: 计算 | BF23: 计算 | BG23: 计算 | BH23: 计算 | BI23: 计算 | BJ23: 计算 | BK23: 计算 | BL23: 计算 | BM23: 计算
B24: 合计 | C24: / | D24: / | E24: / | G24: 求和 | H24: 计算 | I24: 求和 | J24: 求和 | K24: 求和 | L24: 求和 | M24: 求和 | N24: 求和 | O24: 求和 | P24: 求和 | Q24: 求和 | R24: 求和 | S24: 求和 | T24: 求和 | V24: 求和 | W24: 计算 | X24: 求和 | Y24: 求和 | Z24: 求和 | AA24: 求和 | AB24: 求和 | AC24: 求和 | AD24: 求和 | AE24: 求和 | AF24: 求和 | AG24: 求和 | AH24: 求和 | AI24: 求和 | AK24: 求和 | AL24: 计算 | AM24: 求和 | AN24: 求和 | AO24: 求和 | AP24: 求和 | AQ24: 求和 | AR24: 求和 | AS24: 求和 | AT24: 求和 | AU24: 求和 | AV24: 求和 | AW24: 求和 | AX24: 求和 | AZ24: 求和 | BA24: 计算 | BB24: 求和 | BC24: 求和 | BD24: 求和 | BE24: 求和 | BF24: 求和 | BG24: 求和 | BH24: 求和 | BI24: 求和 | BJ24: 求和 | BK24: 求和 | BL24: 求和 | BM24: 求和
C25: 软颗粒 | E25: 肽康宝 | G25: 求和 | H25: 计算 | V25: 求和 | W25: 计算 | AK25: 求和 | AL25: 计算 | AZ25: 求和 | BA25: 计算
E26: 虾酸奶 | G26: 求和 | H26: 计算 | V26: 求和 | W26: 计算 | AK26: 求和 | AL26: 计算 | AZ26: 求和 | BA26: 计算
C27: 常规动保 | G27: 求和 | H27: 计算 | V27: 求和 | W27: 计算 | AK27: 求和 | AL27: 计算 | AZ27: 求和 | BA27: 计算
G28: 求和 | H28: 计算 | V28: 求和 | W28: 计算 | AK28: 求和 | AL28: 计算 | AZ28: 求和 | BA28: 计算
G29: 求和 | H29: 计算 | V29: 求和 | W29: 计算 | AK29: 求和 | AL29: 计算 | AZ29: 求和 | BA29: 计算
G30: 求和 | H30: 计算 | V30: 求和 | W30: 计算 | AK30: 求和 | AL30: 计算 | AZ30: 求和 | BA30: 计算
G31: 求和 | H31: 计算 | V31: 求和 | W31: 计算 | AK31: 求和 | AL31: 计算 | AZ31: 求和 | BA31: 计算
G32: 求和 | H32: 计算 | V32: 求和 | W32: 计算 | AK32: 求和 | AL32: 计算 | AZ32: 求和 | BA32: 计算
G33: 求和 | H33: 计算 | V33: 求和 | W33: 计算 | AK33: 求和 | AL33: 计算 | AZ33: 求和 | BA33: 计算
G34: 求和 | H34: 计算 | V34: 求和 | W34: 计算 | AK34: 求和 | AL34: 计算 | AZ34: 求和 | BA34: 计算
G35: 求和 | H35: 计算 | V35: 求和 | W35: 计算 | AK35: 求和 | AL35: 计算 | AZ35: 求和 | BA35: 计算
G36: 求和 | H36: 计算 | V36: 求和 | W36: 计算 | AK36: 求和 | AL36: 计算 | AZ36: 求和 | BA36: 计算
G37: 求和 | H37: 计算 | V37: 求和 | W37: 计算 | AK37: 求和 | AL37: 计算 | AZ37: 求和 | BA37: 计算
G38: 求和 | H38: 计算 | V38: 求和 | W38: 计算 | AK38: 求和 | AL38: 计算 | AZ38: 求和 | BA38: 计算
G39: 求和 | H39: 计算 | V39: 求和 | W39: 计算 | AK39: 求和 | AL39: 计算 | AZ39: 求和 | BA39: 计算
... G87: 求和 | H87: 计算 | V87: 求和 | W87: 计算 | AK87: 求和 | AL87: 计算 | AZ87: 求和 | BA87: 计算
G88: 求和 | H88: 计算 | I88: 0 | J88: 0 | K88: 0 | L88: 0 | M88: 0 | N88: 0 | O88: 0 | P88: 0 | Q88: 0 | R88: 0 | S88: 0 | T88: 0 | V88: 求和 | W88: 计算 | X88: 0 | Y88: 0 | Z88: 0 | AA88: 0 | AB88: 0 | AC88: 0 | AD88: 0 | AE88: 0 | AF88: 0 | AG88: 0 | AH88: 0 | AI88: 0 | AK88: 求和 | AL88: 计算 | AM88: 0 | AN88: 0 | AO88: 0 | AP88: 0 | AQ88: 0 | AR88: 0 | AS88: 0 | AT88: 0 | AU88: 0 | AV88: 0 | AW88: 0 | AX88: 0 | AZ88: 求和 | BA88: 计算 | BB88: 0 | BC88: 0 | BD88: 0 | BE88: 0 | BF88: 0 | BG88: 0 | BH88: 0 | BI88: 0 | BJ88: 0 | BK88: 0 | BL88: 0 | BM88: 0
G89: 求和 | H89: 计算 | I89: 0 | J89: 0 | K89: 0 | L89: 0 | M89: 0 | N89: 0 | O89: 0 | P89: 0 | Q89: 0 | R89: 0 | S89: 0 | T89: 0 | V89: 求和 | W89: 计算 | X89: 0 | Y89: 0 | Z89: 0 | AA89: 0 | AB89: 0 | AC89: 0 | AD89: 0 | AE89: 0 | AF89: 0 | AG89: 0 | AH89: 0 | AI89: 0 | AK89: 求和 | AL89: 计算 | AM89: 0 | AN89: 0 | AO89: 0 | AP89: 0 | AQ89: 0 | AR89: 0 | AS89: 0 | AT89: 0 | AU89: 0 | AV89: 0 | AW89: 0 | AX89: 0 | AZ89: 求和 | BA89: 计算 | BB89: 0 | BC89: 0 | BD89: 0 | BE89: 0 | BF89: 0 | BG89: 0 | BH89: 0 | BI89: 0 | BJ89: 0 | BK89: 0 | BL89: 0 | BM89: 0
G90: 求和 | H90: 计算 | I90: 0 | J90: 0 | K90: 0 | L90: 0 | M90: 0 | N90: 0 | O90: 0 | P90: 0 | Q90: 0 | R90: 0 | S90: 0 | T90: 0 | V90: 求和 | W90: 计算 | X90: 0 | Y90: 0 | Z90: 0 | AA90: 0 | AB90: 0 | AC90: 0 | AD90: 0 | AE90: 0 | AF90: 0 | AG90: 0 | AH90: 0 | AI90: 0 | AK90: 求和 | AL90: 计算 | AM90: 0 | AN90: 0 | AO90: 0 | AP90: 0 | AQ90: 0 | AR90: 0 | AS90: 0 | AT90: 0 | AU90: 0 | AV90: 0 | AW90: 0 | AX90: 0 | AZ90: 求和 | BA90: 计算 | BB90: 0 | BC90: 0 | BD90: 0 | BE90: 0 | BF90: 0 | BG90: 0 | BH90: 0 | BI90: 0 | BJ90: 0 | BK90: 0 | BL90: 0 | BM90: 0
G91: 求和 | H91: 计算 | I91: 0 | J91: 0 | K91: 0 | L91: 0 | M91: 0 | N91: 0 | O91: 0 | P91: 0 | Q91: 0 | R91: 0 | S91: 0 | T91: 0 | V91: 求和 | W91: 计算 | X91: 0 | Y91: 0 | Z91: 0 | AA91: 0 | AB91: 0 | AC91: 0 | AD91: 0 | AE91: 0 | AF91: 0 | AG91: 0 | AH91: 0 | AI91: 0 | AK91: 求和 | AL91: 计算 | AM91: 0 | AN91: 0 | AO91: 0 | AP91: 0 | AQ91: 0 | AR91: 0 | AS91: 0 | AT91: 0 | AU91: 0 | AV91: 0 | AW91: 0 | AX91: 0 | AZ91: 求和 | BA91: 计算 | BB91: 0 | BC91: 0 | BD91: 0 | BE91: 0 | BF91: 0 | BG91: 0 | BH91: 0 | BI91: 0 | BJ91: 0 | BK91: 0 | BL91: 0 | BM91: 0
G92: 求和 | H92: 计算 | I92: 0 | J92: 0 | K92: 0 | L92: 0 | M92: 0 | N92: 0 | O92: 0 | P92: 0 | Q92: 0 | R92: 0 | S92: 0 | T92: 0 | V92: 求和 | W92: 计算 | X92: 0 | Y92: 0 | Z92: 0 | AA92: 0 | AB92: 0 | AC92: 0 | AD92: 0 | AE92: 0 | AF92: 0 | AG92: 0 | AH92: 0 | AI92: 0 | AK92: 求和 | AL92: 计算 | AM92: 0 | AN92: 0 | AO92: 0 | AP92: 0 | AQ92: 0 | AR92: 0 | AS92: 0 | AT92: 0 | AU92: 0 | AV92: 0 | AW92: 0 | AX92: 0 | AZ92: 求和 | BA92: 计算 | BB92: 0 | BC92: 0 | BD92: 0 | BE92: 0 | BF92: 0 | BG92: 0 | BH92: 0 | BI92: 0 | BJ92: 0 | BK92: 0 | BL92: 0 | BM92: 0
G93: 求和 | H93: 计算 | I93: 0 | J93: 0 | K93: 0 | L93: 0 | M93: 0 | N93: 0 | O93: 0 | P93: 0 | Q93: 0 | R93: 0 | S93: 0 | T93: 0 | V93: 求和 | W93: 计算 | X93: 0 | Y93: 0 | Z93: 0 | AA93: 0 | AB93: 0 | AC93: 0 | AD93: 0 | AE93: 0 | AF93: 0 | AG93: 0 | AH93: 0 | AI93: 0 | AK93: 求和 | AL93: 计算 | AM93: 0 | AN93: 0 | AO93: 0 | AP93: 0 | AQ93: 0 | AR93: 0 | AS93: 0 | AT93: 0 | AU93: 0 | AV93: 0 | AW93: 0 | AX93: 0 | AZ93: 求和 | BA93: 计算 | BB93: 0 | BC93: 0 | BD93: 0 | BE93: 0 | BF93: 0 | BG93: 0 | BH93: 0 | BI93: 0 | BJ93: 0 | BK93: 0 | BL93: 0 | BM93: 0
G94: 求和 | H94: 计算 | I94: 0 | J94: 0 | K94: 0 | L94: 0 | M94: 0 | N94: 0 | O94: 0 | P94: 0 | Q94: 0 | R94: 0 | S94: 0 | T94: 0 | V94: 求和 | W94: 计算 | X94: 0 | Y94: 0 | Z94: 0 | AA94: 0 | AB94: 0 | AC94: 0 | AD94: 0 | AE94: 0 | AF94: 0 | AG94: 0 | AH94: 0 | AI94: 0 | AK94: 求和 | AL94: 计算 | AM94: 0 | AN94: 0 | AO94: 0 | AP94: 0 | AQ94: 0 | AR94: 0 | AS94: 0 | AT94: 0 | AU94: 0 | AV94: 0 | AW94: 0 | AX94: 0 | AZ94: 求和 | BA94: 计算 | BB94: 0 | BC94: 0 | BD94: 0 | BE94: 0 | BF94: 0 | BG94: 0 | BH94: 0 | BI94: 0 | BJ94: 0 | BK94: 0 | BL94: 0 | BM94: 0
G95: 求和 | H95: 计算 | I95: 0 | J95: 0 | K95: 0 | L95: 0 | M95: 0 | N95: 0 | O95: 0 | P95: 0 | Q95: 0 | R95: 0 | S95: 0 | T95: 0 | V95: 求和 | W95: 计算 | X95: 0 | Y95: 0 | Z95: 0 | AA95: 0 | AB95: 0 | AC95: 0 | AD95: 0 | AE95: 0 | AF95: 0 | AG95: 0 | AH95: 0 | AI95: 0 | AK95: 求和 | AL95: 计算 | AM95: 0 | AN95: 0 | AO95: 0 | AP95: 0 | AQ95: 0 | AR95: 0 | AS95: 0 | AT95: 0 | AU95: 0 | AV95: 0 | AW95: 0 | AX95: 0 | AZ95: 求和 | BA95: 计算 | BB95: 0 | BC95: 0 | BD95: 0 | BE95: 0 | BF95: 0 | BG95: 0 | BH95: 0 | BI95: 0 | BJ95: 0 | BK95: 0 | BL95: 0 | BM95: 0
G96: 求和 | H96: 计算 | I96: 0 | J96: 0 | K96: 0 | L96: 0 | M96: 0 | N96: 0 | O96: 0 | P96: 0 | Q96: 0 | R96: 0 | S96: 0 | T96: 0 | V96: 求和 | W96: 计算 | X96: 0 | Y96: 0 | Z96: 0 | AA96: 0 | AB96: 0 | AC96: 0 | AD96: 0 | AE96: 0 | AF96: 0 | AG96: 0 | AH96: 0 | AI96: 0 | AK96: 求和 | AL96: 计算 | AM96: 0 | AN96: 0 | AO96: 0 | AP96: 0 | AQ96: 0 | AR96: 0 | AS96: 0 | AT96: 0 | AU96: 0 | AV96: 0 | AW96: 0 | AX96: 0 | AZ96: 求和 | BA96: 计算 | BB96: 0 | BC96: 0 | BD96: 0 | BE96: 0 | BF96: 0 | BG96: 0 | BH96: 0 | BI96: 0 | BJ96: 0 | BK96: 0 | BL96: 0 | BM96: 0
G97: 求和 | H97: 计算 | I97: 0 | J97: 0 | K97: 0 | L97: 0 | M97: 0 | N97: 0 | O97: 0 | P97: 0 | Q97: 0 | R97: 0 | S97: 0 | T97: 0 | V97: 求和 | W97: 计算 | X97: 0 | Y97: 0 | Z97: 0 | AA97: 0 | AB97: 0 | AC97: 0 | AD97: 0 | AE97: 0 | AF97: 0 | AG97: 0 | AH97: 0 | AI97: 0 | AK97: 求和 | AL97: 计算 | AM97: 0 | AN97: 0 | AO97: 0 | AP97: 0 | AQ97: 0 | AR97: 0 | AS97: 0 | AT97: 0 | AU97: 0 | AV97: 0 | AW97: 0 | AX97: 0 | AZ97: 求和 | BA97: 计算 | BB97: 0 | BC97: 0 | BD97: 0 | BE97: 0 | BF97: 0 | BG97: 0 | BH97: 0 | BI97: 0 | BJ97: 0 | BK97: 0 | BL97: 0 | BM97: 0
G98: 求和 | H98: 计算 | I98: 0 | J98: 0 | K98: 0 | L98: 0 | M98: 0 | N98: 0 | O98: 0 | P98: 0 | Q98: 0 | R98: 0 | S98: 0 | T98: 0 | V98: 求和 | W98: 计算 | X98: 0 | Y98: 0 | Z98: 0 | AA98: 0 | AB98: 0 | AC98: 0 | AD98: 0 | AE98: 0 | AF98: 0 | AG98: 0 | AH98: 0 | AI98: 0 | AK98: 求和 | AL98: 计算 | AM98: 0 | AN98: 0 | AO98: 0 | AP98: 0 | AQ98: 0 | AR98: 0 | AS98: 0 | AT98: 0 | AU98: 0 | AV98: 0 | AW98: 0 | AX98: 0 | AZ98: 求和 | BA98: 计算 | BB98: 0 | BC98: 0 | BD98: 0 | BE98: 0 | BF98: 0 | BG98: 0 | BH98: 0 | BI98: 0 | BJ98: 0 | BK98: 0 | BL98: 0 | BM98: 0
G99: 求和 | H99: 计算 | I99: 0 | J99: 0 | K99: 0 | L99: 0 | M99: 0 | N99: 0 | O99: 0 | P99: 0 | Q99: 0 | R99: 0 | S99: 0 | T99: 0 | V99: 求和 | W99: 计算 | X99: 0 | Y99: 0 | Z99: 0 | AA99: 0 | AB99: 0 | AC99: 0 | AD99: 0 | AE99: 0 | AF99: 0 | AG99: 0 | AH99: 0 | AI99: 0 | AK99: 求和 | AL99: 计算 | AM99: 0 | AN99: 0 | AO99: 0 | AP99: 0 | AQ99: 0 | AR99: 0 | AS99: 0 | AT99: 0 | AU99: 0 | AV99: 0 | AW99: 0 | AX99: 0 | AZ99: 求和 | BA99: 计算 | BB99: 0 | BC99: 0 | BD99: 0 | BE99: 0 | BF99: 0 | BG99: 0 | BH99: 0 | BI99: 0 | BJ99: 0 | BK99: 0 | BL99: 0 | BM99: 0
... G119: 求和 | H119: 计算 | I119: 0 | J119: 0 | K119: 0 | L119: 0 | M119: 0 | N119: 0 | O119: 0 | P119: 0 | Q119: 0 | R119: 0 | S119: 0 | T119: 0 | V119: 求和 | W119: 计算 | X119: 0 | Y119: 0 | Z119: 0 | AA119: 0 | AB119: 0 | AC119: 0 | AD119: 0 | AE119: 0 | AF119: 0 | AG119: 0 | AH119: 0 | AI119: 0 | AK119: 求和 | AL119: 计算 | AM119: 0 | AN119: 0 | AO119: 0 | AP119: 0 | AQ119: 0 | AR119: 0 | AS119: 0 | AT119: 0 | AU119: 0 | AV119: 0 | AW119: 0 | AX119: 0 | AZ119: 求和 | BA119: 计算 | BB119: 0 | BC119: 0 | BD119: 0 | BE119: 0 | BF119: 0 | BG119: 0 | BH119: 0 | BI119: 0 | BJ119: 0 | BK119: 0 | BL119: 0 | BM119: 0

Sheet 填写-内部代工（需求方）-营业部
A1: ← 返回目录 | B1: CUBE: | C1: TONGWEI:02外销量（按客户）-导入
B2: 币种 | C2: Local
B3: 新老客户 | C3: 老客户
B4: 备用维1 | C4: 备用1不区分
B5: 备用维2 | C5: 备用2不区分
B6: 科目 | C6: 外销量
B7: 输入项 | C7: 值
B11: F0100xxx饲料内部代工录入表（需求方） | F11: 填录说明： | G11: 第一步，选择年、公司、版本、场景；
G12: 第二步，下拉选择代工公司、产品系列；
G13: 第三步，系统将显示上年吨数，按照产品系列分月填录吨数数据；
G14: 第四步，填制数据完成后，单击【提交】按钮，将数据提交至系统。
B15: 责任部门：营业部
F16: 单位：吨
G17: 0
J18: 如：江门找惠州代工
B19: 年 | C19: 2026年 | D19: 公司 | E19: 江门澳华 | F19: 版本 | G19: V1 | H19: 场景 | I19: 年度
B21: 行 | C21: 客户编码 | D21: 代工公司 | E21: 大类 | F21: 小类 | G21: 产品系列编码 | H21: 产品系列 | I21: 战略产品系列 | J21: 2025年合计 | K21: 2026年合计 | L21: 同比增减额 | M21: 同比增减率 | N21: 2026年预算数
N22: 1月 | O22: 2月 | P22: 3月 | Q22: 4月 | R22: 5月 | S22: 6月 | T22: 7月 | U22: 8月 | V22: 9月 | W22: 10月 | X22: 11月 | Y22: 12月
C23: 自动生成 | D23: 选择（惠州） | E23: 自动生成 | F23: 自动生成 | G23: 自动生成 | H23: 选择 | I23: 自动生成 | J23: 自动生成 | K23: 求和 | L23: 计算 | M23: 计算 | N23: 填入 | O23: 填入 | P23: 填入 | Q23: 填入 | R23: 填入 | S23: 填入 | T23: 填入 | U23: 填入 | V23: 填入 | W23: 填入 | X23: 填入 | Y23: 填入
B24: 合计 | C24: / | D24: / | E24: / | F24: / | G24: / | H24: / | I24: / | K24: 求和 | L24: 计算 | M24: 计算 | N24: 求和 | O24: 求和 | P24: 求和 | Q24: 求和 | R24: 求和 | S24: 求和 | T24: 求和 | U24: 求和 | V24: 求和 | W24: 求和 | X24: 求和 | Y24: 求和
B25: 行1 | E25: 虾料 | F25: 虾安康 | H25: 铂金版虾安康 | K25: 求和 | L25: 计算 | M25: 计算
B26: 行2 | H26: 金刚安康 | K26: 求和 | L26: 计算 | M26: 计算
B27: 行3 | H27: 虾奶粉 | K27: 求和 | L27: 计算 | M27: 计算
B28: 行4 | H28: 虾安康 | K28: 求和 | L28: 计算 | M28: 计算
B29: 行5 | K29: 求和 | L29: 计算 | M29: 计算
B30: 行6 | K30: 求和 | L30: 计算 | M30: 计算
B31: 行8 | K31: 求和 | L31: 计算 | M31: 计算
B32: 行9 | K32: 求和 | L32: 计算 | M32: 计算
B33: 行10 | K33: 求和 | L33: 计算 | M33: 计算
B34: 行11 | K34: 求和 | L34: 计算 | M34: 计算
B35: 行12 | K35: 求和 | L35: 计算 | M35: 计算
B36: 行13 | K36: 求和 | L36: 计算 | M36: 计算
B37: 行16 | K37: 求和 | L37: 计算 | M37: 计算
B38: 行17 | K38: 求和 | L38: 计算 | M38: 计算
B39: 行18 | K39: 求和 | L39: 计算 | M39: 计算
B40: 行19 | K40: 求和 | L40: 计算 | M40: 计算
... B87: 行68 | K87: 求和 | L87: 计算 | M87: 计算
B88: 行69 | K88: 求和 | L88: 计算 | M88: 计算 | N88: 0 | O88: 0 | P88: 0 | Q88: 0 | R88: 0 | S88: 0 | T88: 0 | U88: 0 | V88: 0 | W88: 0 | X88: 0 | Y88: 0
B89: 行70 | K89: 求和 | L89: 计算 | M89: 计算 | N89: 0 | O89: 0 | P89: 0 | Q89: 0 | R89: 0 | S89: 0 | T89: 0 | U89: 0 | V89: 0 | W89: 0 | X89: 0 | Y89: 0
B90: 行71 | K90: 求和 | L90: 计算 | M90: 计算 | N90: 0 | O90: 0 | P90: 0 | Q90: 0 | R90: 0 | S90: 0 | T90: 0 | U90: 0 | V90: 0 | W90: 0 | X90: 0 | Y90: 0
B91: 行72 | K91: 求和 | L91: 计算 | M91: 计算 | N91: 0 | O91: 0 | P91: 0 | Q91: 0 | R91: 0 | S91: 0 | T91: 0 | U91: 0 | V91: 0 | W91: 0 | X91: 0 | Y91: 0
B92: 行73 | K92: 求和 | L92: 计算 | M92: 计算 | N92: 0 | O92: 0 | P92: 0 | Q92: 0 | R92: 0 | S92: 0 | T92: 0 | U92: 0 | V92: 0 | W92: 0 | X92: 0 | Y92: 0
B93: 行74 | K93: 求和 | L93: 计算 | M93: 计算 | N93: 0 | O93: 0 | P93: 0 | Q93: 0 | R93: 0 | S93: 0 | T93: 0 | U93: 0 | V93: 0 | W93: 0 | X93: 0 | Y93: 0
B94: 行75 | K94: 求和 | L94: 计算 | M94: 计算 | N94: 0 | O94: 0 | P94: 0 | Q94: 0 | R94: 0 | S94: 0 | T94: 0 | U94: 0 | V94: 0 | W94: 0 | X94: 0 | Y94: 0
B95: 行76 | K95: 求和 | L95: 计算 | M95: 计算 | N95: 0 | O95: 0 | P95: 0 | Q95: 0 | R95: 0 | S95: 0 | T95: 0 | U95: 0 | V95: 0 | W95: 0 | X95: 0 | Y95: 0
B96: 行77 | K96: 求和 | L96: 计算 | M96: 计算 | N96: 0 | O96: 0 | P96: 0 | Q96: 0 | R96: 0 | S96: 0 | T96: 0 | U96: 0 | V96: 0 | W96: 0 | X96: 0 | Y96: 0
B97: 行78 | K97: 求和 | L97: 计算 | M97: 计算 | N97: 0 | O97: 0 | P97: 0 | Q97: 0 | R97: 0 | S97: 0 | T97: 0 | U97: 0 | V97: 0 | W97: 0 | X97: 0 | Y97: 0
B98: 行79 | K98: 求和 | L98: 计算 | M98: 计算 | N98: 0 | O98: 0 | P98: 0 | Q98: 0 | R98: 0 | S98: 0 | T98: 0 | U98: 0 | V98: 0 | W98: 0 | X98: 0 | Y98: 0
B99: 行80 | K99: 求和 | L99: 计算 | M99: 计算 | N99: 0 | O99: 0 | P99: 0 | Q99: 0 | R99: 0 | S99: 0 | T99: 0 | U99: 0 | V99: 0 | W99: 0 | X99: 0 | Y99: 0
... B119: 行100 | K119: 求和 | L119: 计算 | M119: 计算 | N119: 0 | O119: 0 | P119: 0 | Q119: 0 | R119: 0 | S119: 0 | T119: 0 | U119: 0 | V119: 0 | W119: 0 | X119: 0 | Y119: 0

Sheet 填写-内部代工（生产方）-财务
A1: ← 返回目录 | B1: CUBE: | C1: TONGWEI:02外销量（按客户）-导入
B2: 币种 | C2: Local
B3: 新老客户 | C3: 老客户
B4: 备用维1 | C4: 备用1不区分
B5: 备用维2 | C5: 备用2不区分
B6: 科目 | C6: 外销量
B7: 输入项 | C7: 值
B11: F0100xxx饲料内部代工录入表（生产方） | F11: 填录说明： | G11: 第一步，选择年、公司、版本、场景；
G12: 第二步，系统将自动生成需求方填报的产品及吨数数据；
G13: 第三步，分月填录单吨售价、单吨配方、单吨包装物、单吨制造费用数据；
G14: 第四步，填制数据完成后，单击【提交】按钮，将数据提交至系统。
B15: 责任部门：财务部
F16: 单位：元/吨
G17: 0
K18: 江门找惠州代工
B19: 年 | C19: 2026年 | D19: 公司 | E19: 惠州澳华 | F19: 版本 | G19: V1 | H19: 场景 | I19: 年度
AA20: 用于参考 | AR20: 用于参考 | BI20: 用于参考 | BZ20: 用于参考
B21: 行 | C21: 客户编码 | D21: 内部客户 | E21: 大类 | F21: 小类 | G21: 产品系列编码 | H21: 产品系列 | I21: 战略产品 | J21: 检查消息 | K21: 销量 | AA21: 最新售价 | AB21: 单吨售价 | AR21: 最新配方 | AS21: 单吨配方成本 | BI21: 最新包材 | BJ21: 单吨包装物 | BZ21: 最新制费 | CA21: 单吨制造费用
K22: 2025年合计 | L22: 2026年合计 | M22: 同比增减额 | N22: 同比增减率 | O22: 1月 | P22: 2月 | Q22: 3月 | R22: 4月 | S22: 5月 | T22: 6月 | U22: 7月 | V22: 8月 | W22: 9月 | X22: 10月 | Y22: 11月 | Z22: 12月 | AB22: 2025年平均 | AC22: 2026年平均 | AD22: 同比增减额 | AE22: 同比增减率 | AF22: 1月 | AG22: 2月 | AH22: 3月 | AI22: 4月 | AJ22: 5月 | AK22: 6月 | AL22: 7月 | AM22: 8月 | AN22: 9月 | AO22: 10月 | AP22: 11月 | AQ22: 12月 | AS22: 2025年平均 | AT22: 2026年平均 | AU22: 同比增减额 | AV22: 同比增减率 | AW22: 1月 | AX22: 2月 | AY22: 3月 | AZ22: 4月 | BA22: 5月 | BB22: 6月 | BC22: 7月 | BD22: 8月 | BE22: 9月 | BF22: 10月 | BG22: 11月 | BH22: 12月 | BJ22: 2025年平均 | BK22: 2026年平均 | BL22: 同比增减额 | BM22: 同比增减率 | BN22: 1月 | BO22: 2月 | BP22: 3月 | BQ22: 4月 | BR22: 5月 | BS22: 6月 | BT22: 7月 | BU22: 8月 | BV22: 9月 | BW22: 10月 | BX22: 11月 | BY22: 12月 | CA22: 2025年平均 | CB22: 2026年平均 | CC22: 同比增减额 | CD22: 同比增减率 | CE22: 1月 | CF22: 2月 | CG22: 3月 | CH22: 4月 | CI22: 5月 | CJ22: 6月 | CK22: 7月 | CL22: 8月 | CM22: 9月 | CN22: 10月 | CO22: 11月 | CP22: 12月
C23: 自动生成 | D23: 自动生成 | E23: 自动生成 | F23: 自动生成 | G23: 自动生成 | H23: 自动生成 | I23: 自动生成 | K23: 自动生成 | L23: 求和 | M23: 计算 | N23: 计算 | O23: 自动生成 | P23: 自动生成 | Q23: 自动生成 | R23: 自动生成 | S23: 自动生成 | T23: 自动生成 | U23: 自动生成 | V23: 自动生成 | W23: 自动生成 | X23: 自动生成 | Y23: 自动生成 | Z23: 自动生成 | AA23: 自动生成 | AB23: 自动生成 | AC23: 计算 | AD23: 计算 | AE23: 计算 | AF23: 填入 | AG23: 填入 | AH23: 填入 | AI23: 填入 | AJ23: 填入 | AK23: 填入 | AL23: 填入 | AM23: 填入 | AN23: 填入 | AO23: 填入 | AP23: 填入 | AQ23: 填入 | AR23: 自动生成 | AS23: 自动生成 | AT23: 计算 | AU23: 计算 | AV23: 计算 | AW23: 填入 | AX23: 填入 | AY23: 填入 | AZ23: 填入 | BA23: 填入 | BB23: 填入 | BC23: 填入 | BD23: 填入 | BE23: 填入 | BF23: 填入 | BG23: 填入 | BH23: 填入 | BI23: 自动生成 | BJ23: 自动生成 | BK23: 计算 | BL23: 计算 | BM23: 计算 | BN23: 填入 | BO23: 填入 | BP23: 填入 | BQ23: 填入 | BR23: 填入 | BS23: 填入 | BT23: 填入 | BU23: 填入 | BV23: 填入 | BW23: 填入 | BX23: 填入 | BY23: 填入 | BZ23: 自动生成 | CA23: 自动生成 | CB23: 计算 | CC23: 计算 | CD23: 计算 | CE23: 填入 | CF23: 填入 | CG23: 填入 | CH23: 填入 | CI23: 填入 | CJ23: 填入 | CK23: 填入 | CL23: 填入 | CM23: 填入 | CN23: 填入 | CO23: 填入 | CP23: 填入
B24: 合计 | C24: / | D24: / | E24: / | F24: / | G24: / | H24: / | I24: / | J24: / | L24: 求和 | M24: 计算 | N24: 计算 | O24: 求和 | P24: 求和 | Q24: 求和 | R24: 求和 | S24: 求和 | T24: 求和 | U24: 求和 | V24: 求和 | W24: 求和 | X24: 求和 | Y24: 求和 | Z24: 求和 | AC24: 计算 | AD24: 计算 | AE24: 计算 | AF24: 求和 | AG24: 求和 | AH24: 求和 | AI24: 求和 | AJ24: 求和 | AK24: 求和 | AL24: 求和 | AM24: 求和 | AN24: 求和 | AO24: 求和 | AP24: 求和 | AQ24: 求和 | AT24: 计算 | AU24: 计算 | AV24: 计算 | AW24: 求和 | AX24: 求和 | AY24: 求和 | AZ24: 求和 | BA24: 求和 | BB24: 求和 | BC24: 求和 | BD24: 求和 | BE24: 求和 | BF24: 求和 | BG24: 求和 | BH24: 求和 | BK24: 计算 | BL24: 计算 | BM24: 计算 | BN24: 求和 | BO24: 求和 | BP24: 求和 | BQ24: 求和 | BR24: 求和 | BS24: 求和 | BT24: 求和 | BU24: 求和 | BV24: 求和 | BW24: 求和 | BX24: 求和 | BY24: 求和 | CB24: 计算 | CC24: 计算 | CD24: 计算 | CE24: 求和 | CF24: 求和 | CG24: 求和 | CH24: 求和 | CI24: 求和 | CJ24: 求和 | CK24: 求和 | CL24: 求和 | CM24: 求和 | CN24: 求和 | CO24: 求和 | CP24: 求和
B25: 行1 | D25: 江门 | E25: 虾料 | F25: 虾安康 | H25: 铂金版虾安康 | L25: 求和 | M25: 计算 | N25: 计算 | AC25: 计算 | AD25: 计算 | AE25: 计算 | AT25: 计算 | AU25: 计算 | AV25: 计算 | BK25: 计算 | BL25: 计算 | BM25: 计算 | CB25: 计算 | CC25: 计算 | CD25: 计算
B26: 行2 | H26: 金刚安康 | L26: 求和 | M26: 计算 | N26: 计算 | AC26: 计算 | AD26: 计算 | AE26: 计算 | AT26: 计算 | AU26: 计算 | AV26: 计算 | BK26: 计算 | BL26: 计算 | BM26: 计算 | CB26: 计算 | CC26: 计算 | CD26: 计算
B27: 行3 | H27: 虾奶粉 | L27: 求和 | M27: 计算 | N27: 计算 | AC27: 计算 | AD27: 计算 | AE27: 计算 | AT27: 计算 | AU27: 计算 | AV27: 计算 | BK27: 计算 | BL27: 计算 | BM27: 计算 | CB27: 计算 | CC27: 计算 | CD27: 计算
B28: 行4 | H28: 虾安康 | L28: 求和 | M28: 计算 | N28: 计算 | AC28: 计算 | AD28: 计算 | AE28: 计算 | AT28: 计算 | AU28: 计算 | AV28: 计算 | BK28: 计算 | BL28: 计算 | BM28: 计算 | CB28: 计算 | CC28: 计算 | CD28: 计算
B29: 行5 | L29: 求和 | M29: 计算 | N29: 计算 | AC29: 计算 | AD29: 计算 | AE29: 计算 | AT29: 计算 | AU29: 计算 | AV29: 计算 | BK29: 计算 | BL29: 计算 | BM29: 计算 | CB29: 计算 | CC29: 计算 | CD29: 计算
B30: 行6 | L30: 求和 | M30: 计算 | N30: 计算 | AC30: 计算 | AD30: 计算 | AE30: 计算 | AT30: 计算 | AU30: 计算 | AV30: 计算 | BK30: 计算 | BL30: 计算 | BM30: 计算 | CB30: 计算 | CC30: 计算 | CD30: 计算
B31: 行8 | L31: 求和 | M31: 计算 | N31: 计算 | AC31: 计算 | AD31: 计算 | AE31: 计算 | AT31: 计算 | AU31: 计算 | AV31: 计算 | BK31: 计算 | BL31: 计算 | BM31: 计算 | CB31: 计算 | CC31: 计算 | CD31: 计算
B32: 行9 | L32: 求和 | M32: 计算 | N32: 计算 | AC32: 计算 | AD32: 计算 | AE32: 计算 | AT32: 计算 | AU32: 计算 | AV32: 计算 | BK32: 计算 | BL32: 计算 | BM32: 计算 | CB32: 计算 | CC32: 计算 | CD32: 计算
B33: 行10 | L33: 求和 | M33: 计算 | N33: 计算 | AC33: 计算 | AD33: 计算 | AE33: 计算 | AT33: 计算 | AU33: 计算 | AV33: 计算 | BK33: 计算 | BL33: 计算 | BM33: 计算 | CB33: 计算 | CC33: 计算 | CD33: 计算
B34: 行11 | L34: 求和 | M34: 计算 | N34: 计算 | AC34: 计算 | AD34: 计算 | AE34: 计算 | AT34: 计算 | AU34: 计算 | AV34: 计算 | BK34: 计算 | BL34: 计算 | BM34: 计算 | CB34: 计算 | CC34: 计算 | CD34: 计算
B35: 行12 | L35: 求和 | M35: 计算 | N35: 计算 | AC35: 计算 | AD35: 计算 | AE35: 计算 | AT35: 计算 | AU35: 计算 | AV35: 计算 | BK35: 计算 | BL35: 计算 | BM35: 计算 | CB35: 计算 | CC35: 计算 | CD35: 计算
B36: 行13 | L36: 求和 | M36: 计算 | N36: 计算 | AC36: 计算 | AD36: 计算 | AE36: 计算 | AT36: 计算 | AU36: 计算 | AV36: 计算 | BK36: 计算 | BL36: 计算 | BM36: 计算 | CB36: 计算 | CC36: 计算 | CD36: 计算
B37: 行16 | L37: 求和 | M37: 计算 | N37: 计算 | AC37: 计算 | AD37: 计算 | AE37: 计算 | AT37: 计算 | AU37: 计算 | AV37: 计算 | BK37: 计算 | BL37: 计算 | BM37: 计算 | CB37: 计算 | CC37: 计算 | CD37: 计算
B38: 行17 | L38: 求和 | M38: 计算 | N38: 计算 | AC38: 计算 | AD38: 计算 | AE38: 计算 | AT38: 计算 | AU38: 计算 | AV38: 计算 | BK38: 计算 | BL38: 计算 | BM38: 计算 | CB38: 计算 | CC38: 计算 | CD38: 计算
B39: 行18 | L39: 求和 | M39: 计算 | N39: 计算 | AC39: 计算 | AD39: 计算 | AE39: 计算 | AT39: 计算 | AU39: 计算 | AV39: 计算 | BK39: 计算 | BL39: 计算 | BM39: 计算 | CB39: 计算 | CC39: 计算 | CD39: 计算
B40: 行19 | L40: 求和 | M40: 计算 | N40: 计算 | AC40: 计算 | AD40: 计算 | AE40: 计算 | AT40: 计算 | AU40: 计算 | AV40: 计算 | BK40: 计算 | BL40: 计算 | BM40: 计算 | CB40: 计算 | CC40: 计算 | CD40: 计算
... B87: 行68 | L87: 求和 | M87: 计算 | N87: 计算 | AC87: 计算 | AD87: 计算 | AE87: 计算 | AT87: 计算 | AU87: 计算 | AV87: 计算 | BK87: 计算 | BL87: 计算 | BM87: 计算 | CB87: 计算 | CC87: 计算 | CD87: 计算
B88: 行69 | L88: 求和 | M88: 计算 | N88: 计算 | O88: 0 | P88: 0 | Q88: 0 | R88: 0 | S88: 0 | T88: 0 | U88: 0 | V88: 0 | W88: 0 | X88: 0 | Y88: 0 | Z88: 0 | AC88: 计算 | AD88: 计算 | AE88: 计算 | AF88: 0 | AG88: 0 | AH88: 0 | AI88: 0 | AJ88: 0 | AK88: 0 | AL88: 0 | AM88: 0 | AN88: 0 | AO88: 0 | AP88: 0 | AQ88: 0 | AT88: 计算 | AU88: 计算 | AV88: 计算 | AW88: 0 | AX88: 0 | AY88: 0 | AZ88: 0 | BA88: 0 | BB88: 0 | BC88: 0 | BD88: 0 | BE88: 0 | BF88: 0 | BG88: 0 | BH88: 0 | BK88: 计算 | BL88: 计算 | BM88: 计算 | BN88: 0 | BO88: 0 | BP88: 0 | BQ88: 0 | BR88: 0 | BS88: 0 | BT88: 0 | BU88: 0 | BV88: 0 | BW88: 0 | BX88: 0 | BY88: 0 | CB88: 计算 | CC88: 计算 | CD88: 计算 | CE88: 0 | CF88: 0 | CG88: 0 | CH88: 0 | CI88: 0 | CJ88: 0 | CK88: 0 | CL88: 0 | CM88: 0 | CN88: 0 | CO88: 0 | CP88: 0
B89: 行70 | L89: 求和 | M89: 计算 | N89: 计算 | O89: 0 | P89: 0 | Q89: 0 | R89: 0 | S89: 0 | T89: 0 | U89: 0 | V89: 0 | W89: 0 | X89: 0 | Y89: 0 | Z89: 0 | AC89: 计算 | AD89: 计算 | AE89: 计算 | AF89: 0 | AG89: 0 | AH89: 0 | AI89: 0 | AJ89: 0 | AK89: 0 | AL89: 0 | AM89: 0 | AN89: 0 | AO89: 0 | AP89: 0 | AQ89: 0 | AT89: 计算 | AU89: 计算 | AV89: 计算 | AW89: 0 | AX89: 0 | AY89: 0 | AZ89: 0 | BA89: 0 | BB89: 0 | BC89: 0 | BD89: 0 | BE89: 0 | BF89: 0 | BG89: 0 | BH89: 0 | BK89: 计算 | BL89: 计算 | BM89: 计算 | BN89: 0 | BO89: 0 | BP89: 0 | BQ89: 0 | BR89: 0 | BS89: 0 | BT89: 0 | BU89: 0 | BV89: 0 | BW89: 0 | BX89: 0 | BY89: 0 | CB89: 计算 | CC89: 计算 | CD89: 计算 | CE89: 0 | CF89: 0 | CG89: 0 | CH89: 0 | CI89: 0 | CJ89: 0 | CK89: 0 | CL89: 0 | CM89: 0 | CN89: 0 | CO89: 0 | CP89: 0
B90: 行71 | L90: 求和 | M90: 计算 | N90: 计算 | O90: 0 | P90: 0 | Q90: 0 | R90: 0 | S90: 0 | T90: 0 | U90: 0 | V90: 0 | W90: 0 | X90: 0 | Y90: 0 | Z90: 0 | AC90: 计算 | AD90: 计算 | AE90: 计算 | AF90: 0 | AG90: 0 | AH90: 0 | AI90: 0 | AJ90: 0 | AK90: 0 | AL90: 0 | AM90: 0 | AN90: 0 | AO90: 0 | AP90: 0 | AQ90: 0 | AT90: 计算 | AU90: 计算 | AV90: 计算 | AW90: 0 | AX90: 0 | AY90: 0 | AZ90: 0 | BA90: 0 | BB90: 0 | BC90: 0 | BD90: 0 | BE90: 0 | BF90: 0 | BG90: 0 | BH90: 0 | BK90: 计算 | BL90: 计算 | BM90: 计算 | BN90: 0 | BO90: 0 | BP90: 0 | BQ90: 0 | BR90: 0 | BS90: 0 | BT90: 0 | BU90: 0 | BV90: 0 | BW90: 0 | BX90: 0 | BY90: 0 | CB90: 计算 | CC90: 计算 | CD90: 计算 | CE90: 0 | CF90: 0 | CG90: 0 | CH90: 0 | CI90: 0 | CJ90: 0 | CK90: 0 | CL90: 0 | CM90: 0 | CN90: 0 | CO90: 0 | CP90: 0
B91: 行72 | L91: 求和 | M91: 计算 | N91: 计算 | O91: 0 | P91: 0 | Q91: 0 | R91: 0 | S91: 0 | T91: 0 | U91: 0 | V91: 0 | W91: 0 | X91: 0 | Y91: 0 | Z91: 0 | AC91: 计算 | AD91: 计算 | AE91: 计算 | AF91: 0 | AG91: 0 | AH91: 0 | AI91: 0 | AJ91: 0 | AK91: 0 | AL91: 0 | AM91: 0 | AN91: 0 | AO91: 0 | AP91: 0 | AQ91: 0 | AT91: 计算 | AU91: 计算 | AV91: 计算 | AW91: 0 | AX91: 0 | AY91: 0 | AZ91: 0 | BA91: 0 | BB91: 0 | BC91: 0 | BD91: 0 | BE91: 0 | BF91: 0 | BG91: 0 | BH91: 0 | BK91: 计算 | BL91: 计算 | BM91: 计算 | BN91: 0 | BO91: 0 | BP91: 0 | BQ91: 0 | BR91: 0 | BS91: 0 | BT91: 0 | BU91: 0 | BV91: 0 | BW91: 0 | BX91: 0 | BY91: 0 | CB91: 计算 | CC91: 计算 | CD91: 计算 | CE91: 0 | CF91: 0 | CG91: 0 | CH91: 0 | CI91: 0 | CJ91: 0 | CK91: 0 | CL91: 0 | CM91: 0 | CN91: 0 | CO91: 0 | CP91: 0
B92: 行73 | L92: 求和 | M92: 计算 | N92: 计算 | O92: 0 | P92: 0 | Q92: 0 | R92: 0 | S92: 0 | T92: 0 | U92: 0 | V92: 0 | W92: 0 | X92: 0 | Y92: 0 | Z92: 0 | AC92: 计算 | AD92: 计算 | AE92: 计算 | AF92: 0 | AG92: 0 | AH92: 0 | AI92: 0 | AJ92: 0 | AK92: 0 | AL92: 0 | AM92: 0 | AN92: 0 | AO92: 0 | AP92: 0 | AQ92: 0 | AT92: 计算 | AU92: 计算 | AV92: 计算 | AW92: 0 | AX92: 0 | AY92: 0 | AZ92: 0 | BA92: 0 | BB92: 0 | BC92: 0 | BD92: 0 | BE92: 0 | BF92: 0 | BG92: 0 | BH92: 0 | BK92: 计算 | BL92: 计算 | BM92: 计算 | BN92: 0 | BO92: 0 | BP92: 0 | BQ92: 0 | BR92: 0 | BS92: 0 | BT92: 0 | BU92: 0 | BV92: 0 | BW92: 0 | BX92: 0 | BY92: 0 | CB92: 计算 | CC92: 计算 | CD92: 计算 | CE92: 0 | CF92: 0 | CG92: 0 | CH92: 0 | CI92: 0 | CJ92: 0 | CK92: 0 | CL92: 0 | CM92: 0 | CN92: 0 | CO92: 0 | CP92: 0
B93: 行74 | L93: 求和 | M93: 计算 | N93: 计算 | O93: 0 | P93: 0 | Q93: 0 | R93: 0 | S93: 0 | T93: 0 | U93: 0 | V93: 0 | W93: 0 | X93: 0 | Y93: 0 | Z93: 0 | AC93: 计算 | AD93: 计算 | AE93: 计算 | AF93: 0 | AG93: 0 | AH93: 0 | AI93: 0 | AJ93: 0 | AK93: 0 | AL93: 0 | AM93: 0 | AN93: 0 | AO93: 0 | AP93: 0 | AQ93: 0 | AT93: 计算 | AU93: 计算 | AV93: 计算 | AW93: 0 | AX93: 0 | AY93: 0 | AZ93: 0 | BA93: 0 | BB93: 0 | BC93: 0 | BD93: 0 | BE93: 0 | BF93: 0 | BG93: 0 | BH93: 0 | BK93: 计算 | BL93: 计算 | BM93: 计算 | BN93: 0 | BO93: 0 | BP93: 0 | BQ93: 0 | BR93: 0 | BS93: 0 | BT93: 0 | BU93: 0 | BV93: 0 | BW93: 0 | BX93: 0 | BY93: 0 | CB93: 计算 | CC93: 计算 | CD93: 计算 | CE93: 0 | CF93: 0 | CG93: 0 | CH93: 0 | CI93: 0 | CJ93: 0 | CK93: 0 | CL93: 0 | CM93: 0 | CN93: 0 | CO93: 0 | CP93: 0
B94: 行75 | L94: 求和 | M94: 计算 | N94: 计算 | O94: 0 | P94: 0 | Q94: 0 | R94: 0 | S94: 0 | T94: 0 | U94: 0 | V94: 0 | W94: 0 | X94: 0 | Y94: 0 | Z94: 0 | AC94: 计算 | AD94: 计算 | AE94: 计算 | AF94: 0 | AG94: 0 | AH94: 0 | AI94: 0 | AJ94: 0 | AK94: 0 | AL94: 0 | AM94: 0 | AN94: 0 | AO94: 0 | AP94: 0 | AQ94: 0 | AT94: 计算 | AU94: 计算 | AV94: 计算 | AW94: 0 | AX94: 0 | AY94: 0 | AZ94: 0 | BA94: 0 | BB94: 0 | BC94: 0 | BD94: 0 | BE94: 0 | BF94: 0 | BG94: 0 | BH94: 0 | BK94: 计算 | BL94: 计算 | BM94: 计算 | BN94: 0 | BO94: 0 | BP94: 0 | BQ94: 0 | BR94: 0 | BS94: 0 | BT94: 0 | BU94: 0 | BV94: 0 | BW94: 0 | BX94: 0 | BY94: 0 | CB94: 计算 | CC94: 计算 | CD94: 计算 | CE94: 0 | CF94: 0 | CG94: 0 | CH94: 0 | CI94: 0 | CJ94: 0 | CK94: 0 | CL94: 0 | CM94: 0 | CN94: 0 | CO94: 0 | CP94: 0
B95: 行76 | L95: 求和 | M95: 计算 | N95: 计算 | O95: 0 | P95: 0 | Q95: 0 | R95: 0 | S95: 0 | T95: 0 | U95: 0 | V95: 0 | W95: 0 | X95: 0 | Y95: 0 | Z95: 0 | AC95: 计算 | AD95: 计算 | AE95: 计算 | AF95: 0 | AG95: 0 | AH95: 0 | AI95: 0 | AJ95: 0 | AK95: 0 | AL95: 0 | AM95: 0 | AN95: 0 | AO95: 0 | AP95: 0 | AQ95: 0 | AT95: 计算 | AU95: 计算 | AV95: 计算 | AW95: 0 | AX95: 0 | AY95: 0 | AZ95: 0 | BA95: 0 | BB95: 0 | BC95: 0 | BD95: 0 | BE95: 0 | BF95: 0 | BG95: 0 | BH95: 0 | BK95: 计算 | BL95: 计算 | BM95: 计算 | BN95: 0 | BO95: 0 | BP95: 0 | BQ95: 0 | BR95: 0 | BS95: 0 | BT95: 0 | BU95: 0 | BV95: 0 | BW95: 0 | BX95: 0 | BY95: 0 | CB95: 计算 | CC95: 计算 | CD95: 计算 | CE95: 0 | CF95: 0 | CG95: 0 | CH95: 0 | CI95: 0 | CJ95: 0 | CK95: 0 | CL95: 0 | CM95: 0 | CN95: 0 | CO95: 0 | CP95: 0
B96: 行77 | L96: 求和 | M96: 计算 | N96: 计算 | O96: 0 | P96: 0 | Q96: 0 | R96: 0 | S96: 0 | T96: 0 | U96: 0 | V96: 0 | W96: 0 | X96: 0 | Y96: 0 | Z96: 0 | AC96: 计算 | AD96: 计算 | AE96: 计算 | AF96: 0 | AG96: 0 | AH96: 0 | AI96: 0 | AJ96: 0 | AK96: 0 | AL96: 0 | AM96: 0 | AN96: 0 | AO96: 0 | AP96: 0 | AQ96: 0 | AT96: 计算 | AU96: 计算 | AV96: 计算 | AW96: 0 | AX96: 0 | AY96: 0 | AZ96: 0 | BA96: 0 | BB96: 0 | BC96: 0 | BD96: 0 | BE96: 0 | BF96: 0 | BG96: 0 | BH96: 0 | BK96: 计算 | BL96: 计算 | BM96: 计算 | BN96: 0 | BO96: 0 | BP96: 0 | BQ96: 0 | BR96: 0 | BS96: 0 | BT96: 0 | BU96: 0 | BV96: 0 | BW96: 0 | BX96: 0 | BY96: 0 | CB96: 计算 | CC96: 计算 | CD96: 计算 | CE96: 0 | CF96: 0 | CG96: 0 | CH96: 0 | CI96: 0 | CJ96: 0 | CK96: 0 | CL96: 0 | CM96: 0 | CN96: 0 | CO96: 0 | CP96: 0
B97: 行78 | L97: 求和 | M97: 计算 | N97: 计算 | O97: 0 | P97: 0 | Q97: 0 | R97: 0 | S97: 0 | T97: 0 | U97: 0 | V97: 0 | W97: 0 | X97: 0 | Y97: 0 | Z97: 0 | AC97: 计算 | AD97: 计算 | AE97: 计算 | AF97: 0 | AG97: 0 | AH97: 0 | AI97: 0 | AJ97: 0 | AK97: 0 | AL97: 0 | AM97: 0 | AN97: 0 | AO97: 0 | AP97: 0 | AQ97: 0 | AT97: 计算 | AU97: 计算 | AV97: 计算 | AW97: 0 | AX97: 0 | AY97: 0 | AZ97: 0 | BA97: 0 | BB97: 0 | BC97: 0 | BD97: 0 | BE97: 0 | BF97: 0 | BG97: 0 | BH97: 0 | BK97: 计算 | BL97: 计算 | BM97: 计算 | BN97: 0 | BO97: 0 | BP97: 0 | BQ97: 0 | BR97: 0 | BS97: 0 | BT97: 0 | BU97: 0 | BV97: 0 | BW97: 0 | BX97: 0 | BY97: 0 | CB97: 计算 | CC97: 计算 | CD97: 计算 | CE97: 0 | CF97: 0 | CG97: 0 | CH97: 0 | CI97: 0 | CJ97: 0 | CK97: 0 | CL97: 0 | CM97: 0 | CN97: 0 | CO97: 0 | CP97: 0
B98: 行79 | L98: 求和 | M98: 计算 | N98: 计算 | O98: 0 | P98: 0 | Q98: 0 | R98: 0 | S98: 0 | T98: 0 | U98: 0 | V98: 0 | W98: 0 | X98: 0 | Y98: 0 | Z98: 0 | AC98: 计算 | AD98: 计算 | AE98: 计算 | AF98: 0 | AG98: 0 | AH98: 0 | AI98: 0 | AJ98: 0 | AK98: 0 | AL98: 0 | AM98: 0 | AN98: 0 | AO98: 0 | AP98: 0 | AQ98: 0 | AT98: 计算 | AU98: 计算 | AV98: 计算 | AW98: 0 | AX98: 0 | AY98: 0 | AZ98: 0 | BA98: 0 | BB98: 0 | BC98: 0 | BD98: 0 | BE98: 0 | BF98: 0 | BG98: 0 | BH98: 0 | BK98: 计算 | BL98: 计算 | BM98: 计算 | BN98: 0 | BO98: 0 | BP98: 0 | BQ98: 0 | BR98: 0 | BS98: 0 | BT98: 0 | BU98: 0 | BV98: 0 | BW98: 0 | BX98: 0 | BY98: 0 | CB98: 计算 | CC98: 计算 | CD98: 计算 | CE98: 0 | CF98: 0 | CG98: 0 | CH98: 0 | CI98: 0 | CJ98: 0 | CK98: 0 | CL98: 0 | CM98: 0 | CN98: 0 | CO98: 0 | CP98: 0
B99: 行80 | L99: 求和 | M99: 计算 | N99: 计算 | O99: 0 | P99: 0 | Q99: 0 | R99: 0 | S99: 0 | T99: 0 | U99: 0 | V99: 0 | W99: 0 | X99: 0 | Y99: 0 | Z99: 0 | AC99: 计算 | AD99: 计算 | AE99: 计算 | AF99: 0 | AG99: 0 | AH99: 0 | AI99: 0 | AJ99: 0 | AK99: 0 | AL99: 0 | AM99: 0 | AN99: 0 | AO99: 0 | AP99: 0 | AQ99: 0 | AT99: 计算 | AU99: 计算 | AV99: 计算 | AW99: 0 | AX99: 0 | AY99: 0 | AZ99: 0 | BA99: 0 | BB99: 0 | BC99: 0 | BD99: 0 | BE99: 0 | BF99: 0 | BG99: 0 | BH99: 0 | BK99: 计算 | BL99: 计算 | BM99: 计算 | BN99: 0 | BO99: 0 | BP99: 0 | BQ99: 0 | BR99: 0 | BS99: 0 | BT99: 0 | BU99: 0 | BV99: 0 | BW99: 0 | BX99: 0 | BY99: 0 | CB99: 计算 | CC99: 计算 | CD99: 计算 | CE99: 0 | CF99: 0 | CG99: 0 | CH99: 0 | CI99: 0 | CJ99: 0 | CK99: 0 | CL99: 0 | CM99: 0 | CN99: 0 | CO99: 0 | CP99: 0
... B119: 行100 | L119: 求和 | M119: 计算 | N119: 计算 | O119: 0 | P119: 0 | Q119: 0 | R119: 0 | S119: 0 | T119: 0 | U119: 0 | V119: 0 | W119: 0 | X119: 0 | Y119: 0 | Z119: 0 | AC119: 计算 | AD119: 计算 | AE119: 计算 | AF119: 0 | AG119: 0 | AH119: 0 | AI119: 0 | AJ119: 0 | AK119: 0 | AL119: 0 | AM119: 0 | AN119: 0 | AO119: 0 | AP119: 0 | AQ119: 0 | AT119: 计算 | AU119: 计算 | AV119: 计算 | AW119: 0 | AX119: 0 | AY119: 0 | AZ119: 0 | BA119: 0 | BB119: 0 | BC119: 0 | BD119: 0 | BE119: 0 | BF119: 0 | BG119: 0 | BH119: 0 | BK119: 计算 | BL119: 计算 | BM119: 计算 | BN119: 0 | BO119: 0 | BP119: 0 | BQ119: 0 | BR119: 0 | BS119: 0 | BT119: 0 | BU119: 0 | BV119: 0 | BW119: 0 | BX119: 0 | BY119: 0 | CB119: 计算 | CC119: 计算 | CD119: 计算 | CE119: 0 | CF119: 0 | CG119: 0 | CH119: 0 | CI119: 0 | CJ119: 0 | CK119: 0 | CL119: 0 | CM119: 0 | CN119: 0 | CO119: 0 | CP119: 0

Sheet 填写-产品价目表-财务部
A1: ← 返回目录 | E1: 填录说明： | F1: 第一步，选择年、公司、版本、场景；
F2: 第二步，下拉选择产品系列；
F3: 第三步，分月填录单吨牌价数据；
F4: 第四步，填制数据完成后，单击【提交】按钮，将数据提交至系统。
A5: 责任部门：财务部 | E5: 单位：元/吨
A7: 年 | B7: 2026年 | C7: 公司 | D7: xx澳华 | E7: 版本 | F7: V1 | G7: 场景 | H7: 年度
A9: 大类 | B9: 小类 | C9: 产品系列编码 | D9: 产品系列 | E9: 25年最新牌价 | F9: 25年平均牌价 | G9: 26年平均牌价 | H9: 平均牌价同比 | I9: 1月 | J9: 2月 | K9: 3月 | L9: 4月 | M9: 5月 | N9: 6月 | O9: 7月 | P9: 8月 | Q9: 9月 | R9: 10月 | S9: 11月 | T9: 12月 | U9: 备注
A10: 自动生成 | B10: 自动生成 | C10: 自动生成 | D10: 选择 | E10: 自动生成 | F10: 自动生成 | G10: 计算 | H10: 计算 | I10: 填入 | J10: 填入 | K10: 填入 | L10: 填入 | M10: 填入 | N10: 填入 | O10: 填入 | P10: 填入 | Q10: 填入 | R10: 填入 | S10: 填入 | T10: 填入 | U10: 填入
E11: 按sku最新一个月销量加权平均 | F11: 按sku年销量加权平均 | G11: 计算 | H11: 计算
G12: 计算 | H12: 计算
G13: 计算 | H13: 计算
G14: 计算 | H14: 计算
G15: 计算 | H15: 计算
G16: 计算 | H16: 计算
G17: 计算 | H17: 计算
G18: 计算 | H18: 计算
G19: 计算 | H19: 计算
G20: 计算 | H20: 计算
G21: 计算 | H21: 计算
G22: 计算 | H22: 计算
G23: 计算 | H23: 计算
... G81: 计算 | H81: 计算

Sheet 填写-配方成本-配方师
A1: ← 返回目录 | E1: 填录说明： | F1: 第一步，选择年、公司、版本、场景；
F2: 第二步，下拉选择产品系列；
F3: 第三步，分月填录单吨配方成本数据；
F4: 第四步，填制数据完成后，单击【提交】按钮，将数据提交至系统。
A5: 责任部门：配方师 | E5: 单位：元/吨
A7: 年 | B7: 2026年 | C7: 公司 | D7: xx澳华 | E7: 版本 | F7: V1 | G7: 场景 | H7: 年度
A9: 大类 | B9: 小类 | C9: 产品系列编码 | D9: 产品系列 | E9: 25年最新配方成本 | F9: 25年平均配方成本 | G9: 26年平均配方成本 | H9: 平均配方成本同比 | I9: 1月 | J9: 2月 | K9: 3月 | L9: 4月 | M9: 5月 | N9: 6月 | O9: 7月 | P9: 8月 | Q9: 9月 | R9: 10月 | S9: 11月 | T9: 12月 | U9: 备注
A10: 自动生成 | B10: 自动生成 | C10: 自动生成 | D10: 选择 | E10: 自动生成 | F10: 自动生成 | G10: 计算 | H10: 计算 | I10: 填入 | J10: 填入 | K10: 填入 | L10: 填入 | M10: 填入 | N10: 填入 | O10: 填入 | P10: 填入 | Q10: 填入 | R10: 填入 | S10: 填入 | T10: 填入 | U10: 填入
E11: 取NC核算的配方成本 | G11: 计算 | H11: 计算
G12: 计算 | H12: 计算
G13: 计算 | H13: 计算
G14: 计算 | H14: 计算
G15: 计算 | H15: 计算
G16: 计算 | H16: 计算
G17: 计算 | H17: 计算
G18: 计算 | H18: 计算
G19: 计算 | H19: 计算
G20: 计算 | H20: 计算
G21: 计算 | H21: 计算
G22: 计算 | H22: 计算
G23: 计算 | H23: 计算
... G81: 计算 | H81: 计算

Sheet 填写-产品折扣-财务部
A1: ← 返回目录 | E1: 填录说明： | F1: 第一步，选择年、公司、版本、场景；
F2: 第二步，下拉选择客户名称、产品系列；
F3: 第三步，分月填录单吨折扣数据（含基本折扣、临时促销、年奖、月奖、买赠等所有折扣）；
F4: 第四步，填制数据完成后，单击【提交】按钮，将数据提交至系统。
A6: 责任部门：财务部 | E6: 单位：元/吨
A8: 年 | B8: 2026年 | C8: 公司 | D8: xx澳华 | E8: 版本 | F8: V1 | G8: 场景 | H8: 年度
A10: 聚焦镇 | B10: 客户编码 | C10: 客户 | D10: 是否大客户 | E10: 大类 | F10: 大类 | G10: 产品系列编码 | H10: 产品系列 | I10: 战略产品 | J10: 25年最新单吨折扣 | K10: 25年平均单吨折扣 | L10: 26年平均单吨折扣 | M10: 平均单吨折扣同比 | N10: 单吨折扣（含基本折扣、临时促销、年奖、月奖、买赠等所有折扣） | AA10: 25年平均单吨配销差 | AB10: 26年平均单吨配销差 | AC10: 平均单吨配销差同比 | AD10: 单吨配销差
N11: 1月 | O11: 2月 | P11: 3月 | Q11: 4月 | R11: 5月 | S11: 6月 | T11: 7月 | U11: 8月 | V11: 9月 | W11: 10月 | X11: 11月 | Y11: 12月 | Z11: 备注 | AD11: 1月 | AE11: 2月 | AF11: 3月 | AG11: 4月 | AH11: 5月 | AI11: 6月 | AJ11: 7月 | AK11: 8月 | AL11: 9月 | AM11: 10月 | AN11: 11月 | AO11: 12月 | AP11: 备注
A12: 自动生成 | B12: 自动生成 | C12: 选择 | D12: 自动生成 | E12: 自动生成 | F12: 自动生成 | G12: 自动生成 | H12: 选择 | I12: 自动生成 | J12: 自动生成 | K12: 自动生成 | L12: 填入 | M12: 填入 | N12: 填入 | O12: 填入 | P12: 填入 | Q12: 填入 | R12: 填入 | S12: 填入 | T12: 填入 | U12: 填入 | V12: 填入 | W12: 填入 | X12: 填入 | Y12: 填入 | Z12: 填入 | AA12: 自动生成 | AB12: 计算 | AC12: 计算 | AD12: 计算 | AE12: 计算 | AF12: 计算 | AG12: 计算 | AH12: 计算 | AI12: 计算 | AJ12: 计算 | AK12: 计算 | AL12: 计算 | AM12: 计算 | AN12: 计算 | AO12: 计算 | AP12: 填入
L13: 计算
L14: 计算
L15: 计算
L16: 计算
L17: 计算
L18: 计算
L19: 计算
L20: 计算
L21: 计算
L22: 计算
L23: 计算
L24: 计算
... L83: 计算

Sheet 填写-包材成本-采购、财务
A1: ← 返回目录 | E1: 填录说明： | F1: 第一步，选择年、公司、版本、场景；
F2: 第二步，下拉选择产品系列；
F3: 第三步，分月填录单吨包装物成本数据；
F4: 第四步，填制数据完成后，单击【提交】按钮，将数据提交至系统。
A5: 责任部门：采购部、财务部 | E5: 单位：元/吨
A7: 年 | B7: 2026年 | C7: 公司 | D7: xx澳华 | E7: 版本 | F7: V1 | G7: 场景 | H7: 年度 | J7: 单吨消耗包材的采购加权口径
A9: 大类 | B9: 小类 | C9: 产品系列编码 | D9: 产品系列 | E9: 25年平均包材成本 | F9: 26年平均包材成本 | G9: 平均包材成本同比 | H9: 1月 | I9: 2月 | J9: 3月 | K9: 4月 | L9: 5月 | M9: 6月 | N9: 7月 | O9: 8月 | P9: 9月 | Q9: 10月 | R9: 11月 | S9: 12月 | T9: 备注
A10: 自动生成 | B10: 自动生成 | C10: 自动生成 | D10: 选择 | E10: 自动生成 | F10: 计算 | G10: 计算 | H10: 填入 | I10: 填入 | J10: 填入 | K10: 填入 | L10: 填入 | M10: 填入 | N10: 填入 | O10: 填入 | P10: 填入 | Q10: 填入 | R10: 填入 | S10: 填入 | T10: 填入
F11: 计算 | G11: 计算
F12: 计算 | G12: 计算
F13: 计算 | G13: 计算
F14: 计算 | G14: 计算
F15: 计算 | G15: 计算
F16: 计算 | G16: 计算
F17: 计算 | G17: 计算
F18: 计算 | G18: 计算
F19: 计算 | G19: 计算
F20: 计算 | G20: 计算
F21: 计算 | G21: 计算
F22: 计算 | G22: 计算
... F81: 计算 | G81: 计算

Sheet 填写-主要原料价格-采购
A1: ← 返回目录 | E1: 填录说明： | F1: 第一步，选择年、公司、版本、场景； | G1: 第一步，选择年、公司、版本、场景； | H1: 第一步，选择年、公司、版本、场景； | I1: 第一步，选择年、公司、版本、场景； | J1: 第一步，选择年、公司、版本、场景； | K1: 第一步，选择年、公司、版本、场景；
F2: 第二步，分月填录其他销售费用数据； | G2: 第二步，分月填录其他销售费用数据； | H2: 第二步，分月填录其他销售费用数据； | I2: 第二步，分月填录其他销售费用数据； | J2: 第二步，分月填录其他销售费用数据； | K2: 第二步，分月填录其他销售费用数据；
F3: 第三步，填制数据完成后，单击【提交】按钮，将数据提交至系统。 | G3: 第三步，填制数据完成后，单击【提交】按钮，将数据提交至系统。 | H3: 第三步，填制数据完成后，单击【提交】按钮，将数据提交至系统。 | I3: 第三步，填制数据完成后，单击【提交】按钮，将数据提交至系统。 | J3: 第三步，填制数据完成后，单击【提交】按钮，将数据提交至系统。 | K3: 第三步，填制数据完成后，单击【提交】按钮，将数据提交至系统。
A5: 责任部门：各公司 | E5: 单位：元
A7: 年 | B7: 2026年 | C7: 公司 | D7: xx澳华 | E7: 版本 | F7: V1 | G7: 场景 | H7: 年度
A9: 序号 | B9: 原料名称 | C9: 单价/元/吨 | D9: 1月 | E9: 2月 | F9: 3月 | G9: 4月 | H9: 5月 | I9: 6月 | J9: 7月 | K9: 8月 | L9: 9月 | M9: 10月 | N9: 11月 | O9: 12月
B11: 动物蛋白 | C11: 单价/元/吨 | D11: 填 | E11: 填 | F11: 填 | G11: 填 | H11: 填 | I11: 填 | J11: 填 | K11: 填 | L11: 填 | M11: 填 | N11: 填 | O11: 填
B12: 猪肉粉
B13: 鱼粉-进口日本级 | C13: 单价/元/吨
B14: 鱼粉-进口普通级
B15: 鱼粉-进口超级 | C15: 单价/元/吨
B16: 鱼粉-国产半脱脂-65%
B17: 鱼粉-二级 | C17: 单价/元/吨
B18: 鱼粉-半脱脂-67%
B19: 鸡肉粉-美国-饲料级 | C19: 单价/元/吨
B20: 鸡肉粉
B21: 国产鸡肉粉-65% | C21: 单价/元/吨
B22: 鱼排粉-白鲢
B23: 鱼排粉-罗非鱼 | C23: 单价/元/吨
B24: 植物蛋白
B25: 豆油-四级 | C25: 单价/元/吨
B26: 豆粕-46%
B27: 豆粕-43% | C27: 单价/元/吨
B28: 菜粕-36%
B29: 棉粕-50% | C29: 单价/元/吨
B30: 棉籽蛋白
B31: 植物能量 | C31: 单价/元/吨
B32: 玉米-猪料
B33: 玉米-普通 | C33: 单价/元/吨
B34: 玉米-进口
B35: 小麦 | C35: 单价/元/吨
B36: 玉米DDGS-国产
B37: 面粉 | C37: 单价/元/吨
B38: 面粉-普通
B39: 添加剂 | C39: 单价/元/吨
B40: (PDX-01)虾蟹微量元素预混料
B41: 啤酒酵母粉-破壁喷雾干燥 | C41: 单价/元/吨
B42: 叶黄素-1.5%-玉米黄质
B43: 水产通用多维 | C43: 单价/元/吨
B44: 磷酸二氢钙
B45: 其他 | C45: 单价/元/吨
B46: 包装物

Sheet 表3 产量-生产产量填报表
A1: ← 返回目录 | G1: 填录说明： | H1: 第一步，选择年、公司、版本、场景；
H2: 第二步，分月填写各项目数据
H3: 第三步，填制数据完成后，单击【提交】按钮，将数据提交至系统。
A5: 责任部门：生产部门 | G5: 单位：元
A7: 年 | B7: 2026年 | C7: 公司 | D7: xx澳华 | E7: 版本 | F7: V1 | G7: 场景 | H7: 年度
A10: 大区 | B10: 公司简称 | C10: 产品线 | D10: 销售大类 | E10: 小类 | F10: 产品名称 | G10: 物料编码 | H10: 型号 | I10: 战略产品 | J10: 生产工艺大类分类 | K10: 产量用途（外销、内销） | L10: 产量对外销售公司 | M10: 25年产量 | N10: 26年产量 | O10: 同比增加额 | P10: 同比增长率 | Q10: 46023 | R10: 46054 | S10: 46082 | T10: 46113 | U10: 46143 | V10: 46174 | W10: 46204 | X10: 46235 | Y10: 46266 | Z10: 46296 | AA10: 46327 | AB10: 46357 | AC10: 检验
A11: 华中 | B11: 武汉 | C11: 海特料线 | D11: 高档膨化鱼料 | E11: 黄颡鱼料 | F11: 铂金黄颡安康Φ1.5 | G11: 2202040128 | H11: WUH1-BJHSAK-1.5 | I11: 海特料-黄颡安康 | J11: 浮水膨化鱼料 | K11: 内销 | L11: 武汉 | M11: 49.66 | N11: 127 | O11: 77.34 | P11: =O11/M11 -> 1.5573903 | Q11: 0 | R11: 0 | S11: 7 | T11: 19 | U11: 22 | V11: 16 | W11: 20 | X11: 19 | Y11: 14 | Z11: 7 | AA11: 3 | AB11: 0 | AC11: =N11-SUM(Q11:AB11) -> 0
A12: 华中 | B12: 武汉 | C12: 海特料线 | D12: 高档膨化鱼料 | E12: 黄颡鱼料 | F12: 铂金黄颡安康Φ2.0 | G12: 2202040129 | H12: WUH1-BJHSAK-2.0 | I12: 海特料-黄颡安康 | J12: 浮水膨化鱼料 | K12: 内销 | L12: 武汉 | M12: 125.2 | N12: 184 | O12: 58.8 | P12: =O12/M12 -> 0.46964856 | Q12: 0 | R12: 0 | S12: 9 | T12: 10 | U12: 13 | V12: 28 | W12: 37 | X12: 32 | Y12: 31 | Z12: 18 | AA12: 6 | AB12: 0 | AC12: =N12-SUM(Q12:AB12) -> 0
A13: 华中 | B13: 武汉 | C13: 海特料线 | D13: 高档膨化鱼料 | E13: 加州鲈鱼料 | F13: 铂金加州鲈安康0号Φ1.0 | G13: 2202030176 | H13: WUH1-BJJZLAK0-1.0 | I13: 海特料-铂金版加州安康 | J13: 浮水膨化鱼料 | K13: 内销 | L13: 武汉 | M13: 13.9 | N13: 2 | O13: -11.9 | P13: =O13/M13 -> -0.85611511 | Q13: 0 | R13: 0 | S13: 1 | T13: 1 | U13: 0 | V13: 0 | W13: 0 | X13: 0 | Y13: 0 | Z13: 0 | AA13: 0 | AB13: 0 | AC13: =N13-SUM(Q13:AB13) -> 0
A14: 华中 | B14: 武汉 | C14: 海特料线 | D14: 高档膨化鱼料 | E14: 加州鲈鱼料 | F14: 铂金加州鲈安康1号Φ1.5 | G14: 2202030181 | H14: WUH1-BJJZLAK1-1.5 | I14: 海特料-铂金版加州安康 | J14: 浮水膨化鱼料 | K14: 内销 | L14: 武汉 | M14: 18.52 | N14: 2 | O14: -16.52 | P14: =O14/M14 -> -0.89200864 | Q14: 0 | R14: 0 | S14: 1 | T14: 1 | U14: 0 | V14: 0 | W14: 0 | X14: 0 | Y14: 0 | Z14: 0 | AA14: 0 | AB14: 0 | AC14: =N14-SUM(Q14:AB14) -> 0
A15: 华中 | B15: 武汉 | C15: 海特料线 | D15: 高档膨化鱼料 | E15: 加州鲈鱼料 | F15: 铂金加州鲈安康2号Φ2.0 | G15: 2202030131 | H15: WUH1-BJJZLAK2-2.0 | I15: 海特料-铂金版加州安康 | J15: 浮水膨化鱼料 | K15: 内销 | L15: 武汉 | M15: 29.64 | N15: 26 | O15: -3.64 | P15: =O15/M15 -> -0.12280702 | Q15: 0 | R15: 5 | S15: 6 | T15: 3 | U15: 6 | V15: 4 | W15: 2 | X15: 0 | Y15: 0 | Z15: 0 | AA15: 0 | AB15: 0 | AC15: =N15-SUM(Q15:AB15) -> 0
A16: 华中 | B16: 武汉 | C16: 海特料线 | D16: 高档膨化鱼料 | E16: 加州鲈鱼料 | F16: 铂金加州鲈安康3号Φ3.0 | G16: 2202030132 | H16: WUH1-BJJZLAK3-3.0 | I16: 海特料-铂金版加州安康 | J16: 浮水膨化鱼料 | K16: 内销 | L16: 武汉 | M16: 69.94 | N16: 67 | O16: -2.94 | P16: =O16/M16 -> -0.042036031 | Q16: 0 | R16: 0 | S16: 5 | T16: 13 | U16: 18 | V16: 15 | W16: 7 | X16: 7 | Y16: 2 | Z16: 0 | AA16: 0 | AB16: 0 | AC16: =N16-SUM(Q16:AB16) -> 0
A17: 华中 | B17: 武汉 | C17: 海特料线 | D17: 高档膨化鱼料 | E17: 加州鲈鱼料 | F17: 铂金加州鲈安康4号Φ4.0 | G17: 2202030133 | H17: WUH1-BJJZLAK4-4.0 | I17: 海特料-铂金版加州安康 | J17: 浮水膨化鱼料 | K17: 内销 | L17: 武汉 | M17: 108.3 | N17: 174 | O17: 65.7 | P17: =O17/M17 -> 0.6066482 | Q17: 0 | R17: 20 | S17: 13 | T17: 15 | U17: 12 | V17: 25 | W17: 18 | X17: 17 | Y17: 16 | Z17: 17 | AA17: 16 | AB17: 5 | AC17: =N17-SUM(Q17:AB17) -> 0
A18: 华中 | B18: 武汉 | C18: 海特料线 | D18: 高档膨化鱼料 | E18: 加州鲈鱼料 | F18: 铂金加州鲈安康5号Φ5.0 | G18: 2202030134 | H18: WUH1-BJJZLAK5-5.0 | I18: 海特料-铂金版加州安康 | J18: 浮水膨化鱼料 | K18: 内销 | L18: 武汉 | M18: 192.48 | N18: 450 | O18: 257.52 | P18: =O18/M18 -> 1.3379052 | Q18: 0 | R18: 0 | S18: 13 | T18: 27 | U18: 70 | V18: 75 | W18: 68 | X18: 78 | Y18: 45 | Z18: 38 | AA18: 26 | AB18: 10 | AC18: =N18-SUM(Q18:AB18) -> 0
A19: 华中 | B19: 武汉 | C19: 海特料线 | D19: 高档膨化鱼料 | E19: 加州鲈鱼料 | F19: 铂金加州鲈安康6号Φ6.0 | G19: 2202030135 | H19: WUH1-BJJZLAK6-6.0 | I19: 海特料-铂金版加州安康 | J19: 浮水膨化鱼料 | K19: 内销 | L19: 武汉 | M19: 406.36 | N19: 556 | O19: 149.64 | P19: =O19/M19 -> 0.36824491 | Q19: 0 | R19: 0 | S19: 30 | T19: 68 | U19: 69 | V19: 63 | W19: 99 | X19: 91 | Y19: 60 | Z19: 43 | AA19: 19 | AB19: 14 | AC19: =N19-SUM(Q19:AB19) -> 0
A20: 华中 | B20: 武汉 | C20: 海特料线 | D20: 高档膨化鱼料 | E20: 加州鲈鱼料 | F20: 铂金加州鲈安康7号Φ7.0 | G20: 2202030136 | H20: WUH1-BJJZLAK7-7.0 | I20: 海特料-铂金版加州安康 | J20: 浮水膨化鱼料 | K20: 内销 | L20: 武汉 | M20: 117.4 | N20: 243 | O20: 125.6 | P20: =O20/M20 -> 1.0698467 | Q20: 0 | R20: 0 | S20: 0 | T20: 7 | U20: 25 | V20: 41 | W20: 42 | X20: 33 | Y20: 36 | Z20: 36 | AA20: 13 | AB20: 10 | AC20: =N20-SUM(Q20:AB20) -> 0
A21: 华中 | B21: 武汉 | C21: 海特料线 | D21: 高档膨化鱼料 | E21: 翘嘴料 | F21: 鲌鱼2号Φ2.0 | G21: 2201050012 | H21: WUH1-BY2H-2.0 | I21: 0 | J21: 浮水膨化鱼料 | K21: 内销 | L21: 武汉 | M21: 13.42 | N21: 12 | O21: -1.42 | P21: =O21/M21 -> -0.10581222 | Q21: 0 | R21: 0 | S21: 0 | T21: 0 | U21: 10 | V21: 2 | W21: 0 | X21: 0 | Y21: 0 | Z21: 0 | AA21: 0 | AB21: 0 | AC21: =N21-SUM(Q21:AB21) -> 0

Sheet 表3 产量-汇总表（按大类）
A1: ← 返回目录 | G1: 填录说明： | H1: 第一步，选择年、公司、版本、场景；
H2: 第二步，分月填写各项目数据
H3: 第三步，填制数据完成后，单击【提交】按钮，将数据提交至系统。
A5: 责任部门：生产部门 | G5: 单位：元
A7: 年 | B7: 2026年 | C7: 公司 | D7: xx澳华 | E7: 版本 | F7: V1 | G7: 场景 | H7: 年度
A9: 大区 | B9: 公司简称 | C9: 生产大类 | D9: 46023 | E9: 46054 | F9: 46082 | G9: 46113 | H9: 46143 | I9: 46174 | J9: 46204 | K9: 46235 | L9: 46266 | M9: 46296 | N9: 46327 | O9: 46357
A10: 华中 | B10: 武汉 | C10: 沉水鱼料 | D10: 0 | E10: 0 | F10: 7 | G10: 19 | H10: 22 | I10: 16 | J10: 20 | K10: 19 | L10: 14 | M10: 7 | N10: 3 | O10: 0
A11: 华中 | B11: 武汉 | C11: 膨化鱼料 | D11: 0 | E11: 0 | F11: 9 | G11: 10 | H11: 13 | I11: 28 | J11: 37 | K11: 32 | L11: 31 | M11: 18 | N11: 6 | O11: 0
A12: 华中 | B12: 武汉 | C12: 虾料 | D12: 0 | E12: 0 | F12: 1 | G12: 1 | H12: 0 | I12: 0 | J12: 0 | K12: 0 | L12: 0 | M12: 0 | N12: 0 | O12: 0
A13: 华中 | B13: 武汉 | C13: 膨化虾料 | D13: 0 | E13: 0 | F13: 1 | G13: 1 | H13: 0 | I13: 0 | J13: 0 | K13: 0 | L13: 0 | M13: 0 | N13: 0 | O13: 0

Sheet 制造费用-填报生产部
A1: ← 返回目录 | G1: 填录说明： | H1: 第一步，选择年、公司、版本、场景；
H2: 第二步，分月填写各项目数据
H3: 第三步，填制数据完成后，单击【提交】按钮，将数据提交至系统。
A5: 责任部门：生产部门 | G5: 单位：元
A7: 年 | B7: 2026年 | C7: 公司 | D7: xx澳华 | E7: 版本 | F7: V1 | G7: 场景 | H7: 年度
A9: 费用属性 | B9: 科目名称 | C9: 费用归属 | D9: 2026年 | E9: 2025年 | F9: 增减额 | G9: 增减率 | H9: 2026年预算 | U9: 2025年实际数（公式取A8 考核利润表-月度）
H10: 1月 | I10: 2月 | J10: 3月 | K10: 4月 | L10: 5月 | M10: 6月 | N10: 7月 | O10: 8月 | P10: 9月 | Q10: 10月 | R10: 11月 | S10: 12月 | T10: 合计 | U10: 1 | V10: 2 | W10: 3 | X10: 4 | Y10: 5 | Z10: 6 | AA10: 7 | AB10: 8 | AC10: 9 | AD10: 10 | AE10: 11 | AF10: 12 | AG10: 均值
B11: 生产人数 | C11: /
B12: 生产吨数 | C12: /
A13: =VLOOKUP(B13,'[4]B1-基础资料'!$A$108:$B$135,2,0) -> 固定 | B13: 工资和薪金生产工资 | C13: =VLOOKUP(B13,'[4]B1-基础资料'!$A$108:$C$135,3,0) -> 车间人工薪酬（工资、五险一金）
A14: =VLOOKUP(B14,'[4]B1-基础资料'!$A$108:$B$135,2,0) -> 固定 | B14: 工资和薪金仓储工资 | C14: =VLOOKUP(B14,'[4]B1-基础资料'!$A$108:$C$135,3,0) -> 车间人工薪酬（工资、五险一金）
A15: =VLOOKUP(B15,'[4]B1-基础资料'!$A$108:$B$135,2,0) -> 固定 | B15: 工资和薪金叉车工资 | C15: =VLOOKUP(B15,'[4]B1-基础资料'!$A$108:$C$135,3,0) -> 车间人工薪酬（工资、五险一金）
A16: =VLOOKUP(B16,'[4]B1-基础资料'!$A$108:$B$135,2,0) -> 固定 | B16: 工资和薪金劳务工资 | C16: =VLOOKUP(B16,'[4]B1-基础资料'!$A$108:$C$135,3,0) -> 车间人工薪酬（工资、五险一金）
A17: =VLOOKUP(B17,'[4]B1-基础资料'!$A$108:$B$135,2,0) -> 变动 | B17: 绩效工资及奖金生产绩效 | C17: =VLOOKUP(B17,'[4]B1-基础资料'!$A$108:$C$135,3,0) -> 车间人工提成奖金、绩效
A18: =VLOOKUP(B18,'[4]B1-基础资料'!$A$108:$B$135,2,0) -> 变动 | B18: 绩效工资及奖金仓储绩效 | C18: =VLOOKUP(B18,'[4]B1-基础资料'!$A$108:$C$135,3,0) -> 车间人工提成奖金、绩效
A19: =VLOOKUP(B19,'[4]B1-基础资料'!$A$108:$B$135,2,0) -> 变动 | B19: 绩效工资及奖金叉车绩效 | C19: =VLOOKUP(B19,'[4]B1-基础资料'!$A$108:$C$135,3,0) -> 车间人工提成奖金、绩效
A20: =VLOOKUP(B20,'[4]B1-基础资料'!$A$108:$B$135,2,0) -> 变动 | B20: 绩效工资及奖金劳务绩效 | C20: =VLOOKUP(B20,'[4]B1-基础资料'!$A$108:$C$135,3,0) -> 车间人工提成奖金、绩效
A21: =VLOOKUP(B21,'[4]B1-基础资料'!$A$108:$B$135,2,0) -> 固定 | B21: 社保费 | C21: =VLOOKUP(B21,'[4]B1-基础资料'!$A$108:$C$135,3,0) -> 车间人工薪酬（工资、五险一金）
A22: =VLOOKUP(B22,'[4]B1-基础资料'!$A$108:$B$135,2,0) -> 固定 | B22: 住房公积金 | C22: =VLOOKUP(B22,'[4]B1-基础资料'!$A$108:$C$135,3,0) -> 车间人工薪酬（工资、五险一金）
A23: =VLOOKUP(B23,'[4]B1-基础资料'!$A$108:$B$135,2,0) -> 固定 | B23: 职工福利金 | C23: =VLOOKUP(B23,'[4]B1-基础资料'!$A$108:$C$135,3,0) -> 车间人工薪酬（工资、五险一金）
A24: =VLOOKUP(B24,'[4]B1-基础资料'!$A$108:$B$135,2,0) -> 变动 | B24: 水费 | C24: =VLOOKUP(B24,'[4]B1-基础资料'!$A$108:$C$135,3,0) -> 能耗—水电费
... A40: =VLOOKUP(B40,'[4]B1-基础资料'!$A$108:$B$135,2,0) -> 固定 | B40: 使用权资产折旧费 | C40: =VLOOKUP(B40,'[4]B1-基础资料'!$A$108:$C$135,3,0) -> 资产折旧摊销费
B41: 合计
B42: 吨费用
B43: 每吨变动费用
B44: 每吨固定费用
B45: 人均成本 | H45: =IFERROR(SUM(H13:H23,H33)/H11,0) -> 0 | I45: =IFERROR(SUM(I13:I23,I33)/I11,0) -> 0 | J45: =IFERROR(SUM(J13:J23,J33)/J11,0) -> 0 | K45: =IFERROR(SUM(K13:K23,K33)/K11,0) -> 0 | L45: =IFERROR(SUM(L13:L23,L33)/L11,0) -> 0 | M45: =IFERROR(SUM(M13:M23,M33)/M11,0) -> 0 | N45: =IFERROR(SUM(N13:N23,N33)/N11,0) -> 0 | O45: =IFERROR(SUM(O13:O23,O33)/O11,0) -> 0 | ... AG45: =IFERROR(SUM(AG13:AG23,AG33)/AG11,0) -> 0
B47: 生产大类 | C47: NC大类系数
B48: 沉水鱼料 | C48: 0.97548263
B49: 膨化鱼料 | C49: 2.6566335
B50: 虾料 | C50: 1.8264356
B51: 膨化虾料 | C51: 3.3553835

Sheet 单吨制费计算表
A1: ← 返回目录 | G1: 填录说明： | H1: 第一步，选择年、公司、版本、场景；
H2: 第二步，分月填写各项目数据
H3: 第三步，填制数据完成后，单击【提交】按钮，将数据提交至系统。
A5: 责任部门：生产部门 | G5: 单位：元
A7: 年 | B7: 2026年 | C7: 公司 | D7: xx澳华 | E7: 版本 | F7: V1 | G7: 场景 | H7: 年度
F8: 单吨制造费用参考值
B9: 属性 | C9: 指标 | D9: 生产大类（引用） | E9: 2026年预算 | R9: 2025年 | S9: 同比额 | T9: 同比率
E10: 1月 | F10: 2月 | G10: 3月 | H10: 4月 | I10: 5月 | J10: 6月 | K10: 7月 | L10: 8月 | M10: 9月 | N10: 10月 | O10: 11月 | P10: 12月 | Q10: 合计 | R10: 合计 | S10: 合计 | T10: 合计
B11: 变动 | C11: 人工费 | D11: /
B12: 变动 | C12: 能耗-电耗 | D12: /
B13: 变动 | C13: 能耗-汽耗 | D13: /
B14: 变动 | C14: 机物料费 | D14: /
B15: 变动 | C15: 其他变动费用 | D15: /
B16: 固定 | C16: 固定费用 | D16: /
B17: 合计
B18: 单吨变动费用 | C18: 单吨人工费 | D18: 沉水鱼料
C19: 单吨能耗-电耗 | D19: 沉水鱼料
C20: 单吨能耗-汽耗 | D20: 沉水鱼料
C21: 单吨机物料费 | D21: 沉水鱼料
C22: 单吨其他变动费用 | D22: 沉水鱼料
B23: 单吨固定费用 | C23: 单吨固定费用 | D23: 沉水鱼料
B24: 单吨费用小计 | D24: 沉水鱼料
B25: 单吨变动费用 | C25: 单吨人工费 | D25: 膨化鱼料
C26: 单吨能耗-电耗 | D26: 膨化鱼料
C27: 单吨能耗-汽耗 | D27: 膨化鱼料
C28: 单吨机物料费 | D28: 膨化鱼料
C29: 单吨其他变动费用 | D29: 膨化鱼料
B30: 单吨固定费用 | C30: 单吨固定费用 | D30: 膨化鱼料
B31: 单吨费用小计 | D31: 膨化鱼料
B32: 单吨变动费用 | C32: 单吨人工费 | D32: 虾料
C33: 单吨能耗-电耗 | D33: 虾料
C34: 单吨能耗-汽耗 | D34: 虾料
C35: 单吨机物料费 | D35: 虾料
C36: 单吨其他变动费用 | D36: 虾料
B37: 单吨固定费用 | C37: 单吨固定费用 | D37: 虾料
B38: 单吨费用小计 | D38: 虾料
B39: 单吨变动费用 | C39: 单吨人工费 | D39: 膨化虾料
C40: 单吨能耗-电耗 | D40: 膨化虾料
C41: 单吨能耗-汽耗 | D41: 膨化虾料
C42: 单吨机物料费 | D42: 膨化虾料
C43: 单吨其他变动费用 | D43: 膨化虾料
B44: 单吨固定费用 | C44: 单吨固定费用 | D44: 膨化虾料
B45: 单吨费用小计 | D45: 膨化虾料

Sheet 表4.1 人员定编表（四定表）明细- 人资
A1: ← 返回目录 | E1: 填录说明： | F1: 第一步，选择年、公司、版本、场景；
F2: 第二步，分月填录其他销售费用数据；
F3: 第三步，填制数据完成后，单击【提交】按钮，将数据提交至系统。
A5: 责任部门：人力资源部 | E5: 单位：元
A7: 年 | B7: 2026年 | C7: 公司 | D7: xx澳华 | E7: 版本 | F7: V1 | G7: 场景 | H7: 年度
A9: 大区 | B9: 公司 | C9: 一级部门 | D9: 二级部门 | E9: 岗位 | F9: 序列 | G9: 职级 | H9: 说明 | I9: 2026年预算 | V9: 最新人数
I10: 1 | J10: 2 | K10: 3 | L10: 4 | M10: 5 | N10: 6 | O10: 7 | P10: 8 | Q10: 9 | R10: 10 | S10: 11 | T10: 12 | U10: 月均
A11: 华东一区 | B11: 福建 | C11: 办公室 | E11: 总经理（兼职） | F11: 自动生成 | G11: M3-1 | I11: 0 | J11: 0 | K11: 0 | L11: 0 | M11: 0 | N11: 0 | O11: 0 | P11: 0 | Q11: 0 | R11: 0 | S11: 0 | T11: 0 | U11: =AVERAGE(I11:T11) -> 0 | V11: 0
A12: 华东一区 | B12: 福建 | C12: 办公室 | E12: 厂长 | G12: M2-1 | I12: 1 | J12: 1 | K12: 1 | L12: 1 | M12: 1 | N12: 1 | O12: 1 | P12: 1 | Q12: 1 | R12: 1 | S12: 1 | T12: 1 | U12: =AVERAGE(I12:T12) -> 1 | V12: 1
A13: 华东一区 | B13: 福建 | C13: 财务部 | E13: 财务经理 | G13: M1-2 | I13: 1 | J13: 1 | K13: 1 | L13: 1 | M13: 1 | N13: 1 | O13: 1 | P13: 1 | Q13: 1 | R13: 1 | S13: 1 | T13: 1 | U13: =AVERAGE(I13:T13) -> 1 | V13: 1
A14: 华东一区 | B14: 福建 | C14: 财务部 | E14: 财务主任 | G14: P2-1 | I14: 1 | J14: 1 | K14: 1 | L14: 1 | M14: 1 | N14: 1 | O14: 1 | P14: 1 | Q14: 1 | R14: 1 | S14: 1 | T14: 1 | U14: =AVERAGE(I14:T14) -> 1 | V14: 1
A15: 华东一区 | B15: 福建 | C15: 财务部 | E15: 成本会计 | G15: P1-2 | I15: 1 | J15: 1 | K15: 1 | L15: 1 | M15: 1 | N15: 1 | O15: 1 | P15: 1 | Q15: 1 | R15: 1 | S15: 1 | T15: 1 | U15: =AVERAGE(I15:T15) -> 1 | V15: 1
A16: 华东一区 | B16: 福建 | C16: 财务部 | E16: 出纳 | G16: P1-1 | I16: 1 | J16: 1 | K16: 1 | L16: 1 | M16: 1 | N16: 1 | O16: 1 | P16: 1 | Q16: 1 | R16: 1 | S16: 1 | T16: 1 | U16: =AVERAGE(I16:T16) -> 1 | V16: 1
A17: 华东一区 | B17: 福建 | C17: 财务部 | E17: 销售会计 | G17: P1-1 | I17: 2 | J17: 2 | K17: 2 | L17: 2 | M17: 2 | N17: 2 | O17: 2 | P17: 2 | Q17: 2 | R17: 2 | S17: 2 | T17: 2 | U17: =AVERAGE(I17:T17) -> 2 | V17: 2
A18: 华东一区 | B18: 福建 | C18: 采购部 | E18: 采购经理 | G18: M1-2 | I18: 1 | J18: 1 | K18: 1 | L18: 1 | M18: 1 | N18: 1 | O18: 1 | P18: 1 | Q18: 1 | R18: 1 | S18: 1 | T18: 1 | U18: =AVERAGE(I18:T18) -> 1 | V18: 1
A19: 华东一区 | B19: 福建 | C19: 采购部 | E19: 采购员 | G19: P1-1 | I19: 2 | J19: 2 | K19: 2 | L19: 2 | M19: 2 | N19: 2 | O19: 2 | P19: 2 | Q19: 2 | R19: 2 | S19: 2 | T19: 2 | U19: =AVERAGE(I19:T19) -> 2 | V19: 2
A20: 华东一区 | B20: 福建 | C20: 品管部 | E20: 副经理 | G20: M1-1 | I20: 1 | J20: 1 | K20: 1 | L20: 1 | M20: 1 | N20: 1 | O20: 1 | P20: 1 | Q20: 1 | R20: 1 | S20: 1 | T20: 1 | U20: =AVERAGE(I20:T20) -> 1 | V20: 1
A21: 华东一区 | B21: 福建 | C21: 品管部 | E21: 原料质检员 | G21: P1-1 | I21: 1 | J21: 1 | K21: 1 | L21: 1 | M21: 1 | N21: 1 | O21: 1 | P21: 1 | Q21: 1 | R21: 1 | S21: 1 | T21: 1 | U21: =AVERAGE(I21:T21) -> 1 | V21: 1
A22: 华东一区 | B22: 福建 | C22: 品管部 | E22: 跟班质检员 | G22: P1-2 | I22: 2 | J22: 2 | K22: 2 | L22: 2 | M22: 2 | N22: 2 | O22: 2 | P22: 2 | Q22: 2 | R22: 2 | S22: 2 | T22: 2 | U22: =AVERAGE(I22:T22) -> 2 | V22: 2
A23: 华东一区 | B23: 福建 | C23: 品管部 | E23: 化验员 | G23: P1-1 | I23: 1 | J23: 1 | K23: 1 | L23: 1 | M23: 1 | N23: 1 | O23: 1 | P23: 1 | Q23: 1 | R23: 1 | S23: 1 | T23: 1 | U23: =AVERAGE(I23:T23) -> 1 | V23: 1
... A30: 华东一区 | B30: 福建 | C30: 人资部 | E30: 人资助理 | G30: P1-1 | I30: 1 | J30: 1 | K30: 1 | L30: 1 | M30: 1 | N30: 1 | O30: 1 | P30: 1 | Q30: 1 | R30: 1 | S30: 1 | T30: 1 | U30: =AVERAGE(I30:T30) -> 1 | V30: 1
A31: 华东一区 | B31: 福建 | C31: 人资部 | D31: 行政部 | E31: 地磅员 | G31: O1 | I31: 1 | J31: 1 | K31: 1 | L31: 1 | M31: 1 | N31: 1 | O31: 1 | P31: 1 | Q31: 1 | R31: 1 | S31: 1 | T31: 1 | U31: =AVERAGE(I31:T31) -> 1 | V31: 1
A32: 华东一区 | B32: 福建 | C32: 人资部 | D32: 行政部 | E32: 清洁工 | G32: O1 | I32: 1 | J32: 1 | K32: 1 | L32: 1 | M32: 1 | N32: 1 | O32: 1 | P32: 1 | Q32: 1 | R32: 1 | S32: 1 | T32: 1 | U32: =AVERAGE(I32:T32) -> 1 | V32: 1
A33: 华东一区 | B33: 福建 | C33: 人资部 | D33: 行政部 | E33: 厨师 | G33: O1 | I33: 1 | J33: 1 | K33: 1 | L33: 1 | M33: 1 | N33: 1 | O33: 1 | P33: 1 | Q33: 1 | R33: 1 | S33: 1 | T33: 1 | U33: =AVERAGE(I33:T33) -> 1 | V33: 1
A34: 华东一区 | B34: 福建 | C34: 人资部 | D34: 行政部 | E34: 厨工 | G34: O1 | I34: 2 | J34: 2 | K34: 2 | L34: 2 | M34: 2 | N34: 2 | O34: 2 | P34: 2 | Q34: 2 | R34: 2 | S34: 2 | T34: 2 | U34: =AVERAGE(I34:T34) -> 2 | V34: 2
A35: 华东一区 | B35: 福建 | C35: 人资部 | D35: 行政部 | E35: 保安 | G35: O1 | I35: 2 | J35: 2 | K35: 2 | L35: 2 | M35: 2 | N35: 2 | O35: 2 | P35: 2 | Q35: 2 | R35: 2 | S35: 2 | T35: 2 | U35: =AVERAGE(I35:T35) -> 2 | V35: 2
A36: 华东一区 | B36: 福建 | C36: 仓储部 | D36: 仓储部 | E36: 主任 | G36: O2 | I36: 1 | J36: 1 | K36: 1 | L36: 1 | M36: 1 | N36: 1 | O36: 1 | P36: 1 | Q36: 1 | R36: 1 | S36: 1 | T36: 1 | U36: =AVERAGE(I36:T36) -> 1 | V36: 1
A37: 华东一区 | B37: 福建 | C37: 仓储部 | D37: 仓储部 | E37: 仓管员 | G37: O1 | I37: 9 | J37: 9 | K37: 9 | L37: 9 | M37: 9 | N37: 9 | O37: 9 | P37: 9 | Q37: 9 | R37: 9 | S37: 9 | T37: 9 | U37: =AVERAGE(I37:T37) -> 9 | V37: 8
A38: 华东一区 | B38: 福建 | C38: 仓储部 | D38: 仓储部 | E38: 叉车 | G38: O1 | I38: 2 | J38: 2 | K38: 2 | L38: 2 | M38: 2 | N38: 2 | O38: 2 | P38: 2 | Q38: 2 | R38: 2 | S38: 2 | T38: 2 | U38: =AVERAGE(I38:T38) -> 2 | V38: 1
A39: 华东一区 | B39: 福建 | C39: 生产部 | D39: 生产车间 | E39: 经理 | G39: M1-3 | I39: 1 | J39: 1 | K39: 1 | L39: 1 | M39: 1 | N39: 1 | O39: 1 | P39: 1 | Q39: 1 | R39: 1 | S39: 1 | T39: 1 | U39: =AVERAGE(I39:T39) -> 1 | V39: 1
A40: 华东一区 | B40: 福建 | C40: 生产部 | D40: 生产车间 | E40: 高级班长 | G40: O2 | I40: 1 | J40: 1 | K40: 1 | L40: 1 | M40: 1 | N40: 1 | O40: 1 | P40: 1 | Q40: 1 | R40: 1 | S40: 1 | T40: 1 | U40: =AVERAGE(I40:T40) -> 1 | V40: 1
A41: 华东一区 | B41: 福建 | C41: 生产部 | D41: 生产车间 | E41: 班长 | G41: O2 | I41: 2 | J41: 2 | K41: 2 | L41: 2 | M41: 2 | N41: 2 | O41: 2 | P41: 2 | Q41: 2 | R41: 2 | S41: 2 | T41: 2 | U41: =AVERAGE(I41:T41) -> 2 | V41: 2
A42: 华东一区 | B42: 福建 | C42: 生产部 | D42: 生产车间 | E42: 中控员 | G42: O1 | I42: 8 | J42: 8 | K42: 8 | L42: 8 | M42: 8 | N42: 8 | O42: 8 | P42: 8 | Q42: 8 | R42: 8 | S42: 8 | T42: 8 | U42: =AVERAGE(I42:T42) -> 8 | V42: 6
... A84: 华东一区 | B84: 福建 | C84: 虾蟹销售部 | D84: 虾蟹料部 | E84: 业务员 | G84: S1 | I84: 4 | J84: 4 | K84: 4 | L84: 4 | M84: 4 | N84: 4 | O84: 4 | P84: 4 | Q84: 4 | R84: 4 | S84: 4 | T84: 4 | U84: =AVERAGE(I84:T84) -> 4 | V84: 4
A85: 华东一区 | B85: 福建 | C85: 虾蟹销售部 | D85: 虾蟹料部 | E85: 区域经理 | G85: S2 | U85: 0
A86: 华东一区 | B86: 福建 | C86: 虾蟹销售部 | D86: 虾蟹料部 | E86: 业务员 | G86: S1 | I86: 1 | J86: 1 | K86: 1 | L86: 1 | M86: 1 | N86: 1 | O86: 1 | P86: 1 | Q86: 1 | R86: 1 | S86: 1 | T86: 1 | U86: =AVERAGE(I86:T86) -> 1 | V86: 1
A87: 华东一区 | B87: 福建 | C87: 虾蟹销售部 | D87: 虾蟹料部 | E87: 区域经理 | G87: S2 | I87: 1 | J87: 1 | K87: 1 | L87: 1 | M87: 1 | N87: 1 | O87: 1 | P87: 1 | Q87: 1 | R87: 1 | S87: 1 | T87: 1 | U87: =AVERAGE(I87:T87) -> 1 | V87: 1
A88: 华东一区 | B88: 福建 | C88: 虾蟹销售部 | D88: 虾蟹料部 | E88: 业务员 | G88: S1 | U88: 0
A89: 华东一区 | B89: 福建 | C89: 虾蟹销售部 | D89: 虾蟹料部 | E89: 销售经理及以上 | G89: S3 | I89: 1 | J89: 1 | K89: 1 | L89: 1 | M89: 1 | N89: 1 | O89: 1 | P89: 1 | Q89: 1 | R89: 1 | S89: 1 | T89: 1 | U89: =AVERAGE(I89:T89) -> 1 | V89: 1
A90: 华东一区 | B90: 福建 | C90: 虾蟹销售部 | D90: 虾蟹料部 | E90: 镇长 | G90: S2 | I90: 1 | J90: 1 | K90: 1 | L90: 1 | M90: 1 | N90: 1 | O90: 1 | P90: 1 | Q90: 1 | R90: 1 | S90: 1 | T90: 1 | U90: =AVERAGE(I90:T90) -> 1 | V90: 1
A91: 华东一区 | B91: 福建 | C91: 虾蟹销售部 | D91: 虾蟹料部 | E91: 业务员 | G91: S1 | I91: 3 | J91: 3 | K91: 3 | L91: 3 | M91: 3 | N91: 3 | O91: 3 | P91: 3 | Q91: 3 | R91: 3 | S91: 3 | T91: 3 | U91: =AVERAGE(I91:T91) -> 3 | V91: 3
A92: 华东一区 | B92: 福建 | C92: 虾蟹销售部 | D92: 虾蟹料部 | E92: 镇长 | G92: S2 | I92: 1 | J92: 1 | K92: 1 | L92: 1 | M92: 1 | N92: 1 | O92: 1 | P92: 1 | Q92: 1 | R92: 1 | S92: 1 | T92: 1 | U92: =AVERAGE(I92:T92) -> 1 | V92: 1
A93: 华东一区 | B93: 福建 | C93: 虾蟹销售部 | D93: 虾蟹料部 | E93: 业务员 | G93: S1 | I93: 3 | J93: 3 | K93: 3 | L93: 3 | M93: 3 | N93: 3 | O93: 3 | P93: 3 | Q93: 3 | R93: 3 | S93: 3 | T93: 3 | U93: =AVERAGE(I93:T93) -> 3 | V93: 3
A94: 华东一区 | B94: 福建 | C94: 虾蟹销售部 | D94: 虾蟹料部 | E94: 销售经理及以上 | G94: S3 | I94: 1 | J94: 1 | K94: 1 | L94: 1 | M94: 1 | N94: 1 | O94: 1 | P94: 1 | Q94: 1 | R94: 1 | S94: 1 | T94: 1 | U94: =AVERAGE(I94:T94) -> 1
A95: 华东一区 | B95: 福建 | C95: 虾蟹销售部 | D95: 虾蟹料部 | E95: 区域经理 | G95: S2 | U95: 0
A96: 华东一区 | B96: 福建 | C96: 虾蟹销售部 | D96: 虾蟹料部 | E96: 业务员 | G96: S1 | I96: 1 | J96: 1 | K96: 1 | L96: 1 | M96: 1 | N96: 1 | O96: 1 | P96: 1 | Q96: 1 | R96: 1 | S96: 1 | T96: 1 | U96: =AVERAGE(I96:T96) -> 1 | V96: 1
A97: 华东一区 | B97: 福建 | C97: 虾蟹销售部 | D97: 虾蟹料部 | E97: 区域经理 | G97: S2 | I97: 1 | J97: 1 | K97: 1 | L97: 1 | M97: 1 | N97: 1 | O97: 1 | P97: 1 | Q97: 1 | R97: 1 | S97: 1 | T97: 1 | U97: =AVERAGE(I97:T97) -> 1
A98: 华东一区 | B98: 福建 | C98: 虾蟹销售部 | D98: 虾蟹料部 | E98: 业务员 | G98: S1 | U98: 0
A99: 华东一区 | B99: 福建 | C99: 普鱼销售部 | D99: 鱼料部 | E99: 销售经理及以上 | G99: S3 | U99: 0
A100: 华东一区 | B100: 福建 | C100: 普鱼销售部 | D100: 鱼料部 | E100: 区域经理 | G100: S2 | I100: 1 | J100: 1 | K100: 1 | L100: 1 | M100: 1 | N100: 1 | O100: 1 | P100: 1 | Q100: 1 | R100: 1 | S100: 1 | T100: 1 | U100: =AVERAGE(I100:T100) -> 1 | V100: 1
A101: 华东一区 | B101: 福建 | C101: 普鱼销售部 | D101: 鱼料部 | E101: 业务员 | G101: S1 | I101: 2 | J101: 2 | K101: 2 | L101: 2 | M101: 2 | N101: 2 | O101: 2 | P101: 2 | Q101: 2 | R101: 2 | S101: 2 | T101: 2 | U101: =AVERAGE(I101:T101) -> 2 | V101: 2
A102: 华东一区 | B102: 福建 | C102: 普鱼销售部 | D102: 鱼料部 | E102: 区域经理 | G102: S2 | I102: 1 | J102: 1 | K102: 1 | L102: 1 | M102: 1 | N102: 1 | O102: 1 | P102: 1 | Q102: 1 | R102: 1 | S102: 1 | T102: 1 | U102: =AVERAGE(I102:T102) -> 1 | V102: 0
A103: 华东一区 | B103: 福建 | C103: 普鱼销售部 | D103: 鱼料部 | E103: 业务员 | G103: S1 | I103: 1 | J103: 1 | K103: 1 | L103: 1 | M103: 1 | N103: 1 | O103: 1 | P103: 1 | Q103: 1 | R103: 1 | S103: 1 | T103: 1 | U103: =AVERAGE(I103:T103) -> 1 | V103: 2
A104: 华东一区 | B104: 福建 | C104: 普鱼销售部 | D104: 鱼料部 | E104: 销售经理及以上 | G104: S3 | I104: 1 | J104: 1 | K104: 1 | L104: 1 | M104: 1 | N104: 1 | O104: 1 | P104: 1 | Q104: 1 | R104: 1 | S104: 1 | T104: 1 | U104: =AVERAGE(I104:T104) -> 1 | V104: 1
A105: 华东一区 | B105: 福建 | C105: 普鱼销售部 | D105: 鱼料部 | E105: 镇长 | G105: S2 | I105: 1 | J105: 1 | K105: 1 | L105: 1 | M105: 1 | N105: 1 | O105: 1 | P105: 1 | Q105: 1 | R105: 1 | S105: 1 | T105: 1 | U105: =AVERAGE(I105:T105) -> 1 | V105: 1
A106: 华东一区 | B106: 福建 | C106: 普鱼销售部 | D106: 鱼料部 | E106: 业务员 | G106: S1 | I106: 2 | J106: 2 | K106: 2 | L106: 2 | M106: 2 | N106: 2 | O106: 2 | P106: 2 | Q106: 2 | R106: 2 | S106: 2 | T106: 2 | U106: =AVERAGE(I106:T106) -> 2 | V106: 2
A107: 华东一区 | B107: 福建 | C107: 普鱼销售部 | D107: 鱼料部 | E107: 镇长 | G107: S2 | I107: 1 | J107: 1 | K107: 1 | L107: 1 | M107: 1 | N107: 1 | O107: 1 | P107: 1 | Q107: 1 | R107: 1 | S107: 1 | T107: 1 | U107: =AVERAGE(I107:T107) -> 1 | V107: 1
A108: 华东一区 | B108: 福建 | C108: 普鱼销售部 | D108: 鱼料部 | E108: 业务员 | G108: S1 | I108: 2 | J108: 2 | K108: 2 | L108: 2 | M108: 2 | N108: 2 | O108: 2 | P108: 2 | Q108: 2 | R108: 2 | S108: 2 | T108: 2 | U108: =AVERAGE(I108:T108) -> 2 | V108: 2
A109: 华东一区 | B109: 福建 | C109: 普鱼销售部 | D109: 鱼料部 | E109: 区域经理 | G109: S2 | I109: 1 | J109: 1 | K109: 1 | L109: 1 | M109: 1 | N109: 1 | O109: 1 | P109: 1 | Q109: 1 | R109: 1 | S109: 1 | T109: 1 | U109: =AVERAGE(I109:T109) -> 1
A110: 华东一区 | B110: 福建 | C110: 普鱼销售部 | D110: 鱼料部 | E110: 业务员 | G110: S1 | I110: 1 | J110: 1 | K110: 1 | L110: 1 | M110: 1 | N110: 1 | O110: 1 | P110: 1 | Q110: 1 | R110: 1 | S110: 1 | T110: 1 | U110: =AVERAGE(I110:T110) -> 1 | V110: 1
A111: 华东一区 | B111: 福建 | C111: 普鱼销售部 | D111: 鱼料部 | E111: 销售经理及以上 | G111: S3 | I111: 1 | J111: 1 | K111: 1 | L111: 1 | M111: 1 | N111: 1 | O111: 1 | P111: 1 | Q111: 1 | R111: 1 | S111: 1 | T111: 1 | U111: =AVERAGE(I111:T111) -> 1 | V111: 1
A112: 华东一区 | B112: 福建 | C112: 普鱼销售部 | D112: 鱼料部 | E112: 区域经理 | G112: S2 | I112: 1 | J112: 1 | K112: 1 | L112: 1 | M112: 1 | N112: 1 | O112: 1 | P112: 1 | Q112: 1 | R112: 1 | S112: 1 | T112: 1 | U112: =AVERAGE(I112:T112) -> 1 | V112: 1
A113: 华东一区 | B113: 福建 | C113: 普鱼销售部 | D113: 鱼料部 | E113: 业务员 | G113: S1 | I113: 1 | J113: 1 | K113: 1 | L113: 1 | M113: 1 | N113: 1 | O113: 1 | P113: 1 | Q113: 1 | R113: 1 | S113: 1 | T113: 1 | U113: =AVERAGE(I113:T113) -> 1 | V113: 1
A114: 华东一区 | B114: 福建 | C114: 普鱼销售部 | D114: 鱼料部 | E114: 区域经理 | G114: S2 | U114: 0
A115: 华东一区 | B115: 福建 | C115: 普鱼销售部 | D115: 鱼料部 | E115: 业务员 | G115: S1 | I115: 2 | J115: 2 | K115: 2 | L115: 2 | M115: 2 | N115: 2 | O115: 2 | P115: 2 | Q115: 2 | R115: 2 | S115: 2 | T115: 2 | U115: =AVERAGE(I115:T115) -> 2 | V115: 2
A116: 华东一区 | B116: 福建 | C116: 普鱼销售部 | D116: 鱼料部 | E116: 区域经理 | G116: S2 | U116: 0
A117: 华东一区 | B117: 福建 | C117: 普鱼销售部 | D117: 鱼料部 | E117: 业务员 | G117: S1 | I117: 1 | J117: 1 | K117: 1 | L117: 1 | M117: 1 | N117: 1 | O117: 1 | P117: 1 | Q117: 1 | R117: 1 | S117: 1 | T117: 1 | U117: =AVERAGE(I117:T117) -> 1 | V117: 1
A118: 华东一区 | B118: 福建 | C118: 海特销售部 | D118: 海特料部 | E118: 销售经理及以上 | G118: S3 | I118: 1 | J118: 1 | K118: 1 | L118: 1 | M118: 1 | N118: 1 | O118: 1 | P118: 1 | Q118: 1 | R118: 1 | S118: 1 | T118: 1 | U118: =AVERAGE(I118:T118) -> 1 | V118: 1
A119: 华东一区 | B119: 福建 | C119: 海特销售部 | D119: 海特料部 | E119: 区域经理 | G119: S2 | U119: 0
A120: 华东一区 | B120: 福建 | C120: 海特销售部 | D120: 海特料部 | E120: 业务员 | G120: S1 | I120: 3 | J120: 3 | K120: 3 | L120: 3 | M120: 3 | N120: 3 | O120: 3 | P120: 3 | Q120: 3 | R120: 3 | S120: 3 | T120: 3 | U120: =AVERAGE(I120:T120) -> 3 | V120: 2
A121: 华东一区 | B121: 福建 | C121: 海特销售部 | D121: 海特料部 | E121: 销售经理及以上 | G121: S3 | I121: 1 | J121: 1 | K121: 1 | L121: 1 | M121: 1 | N121: 1 | O121: 1 | P121: 1 | Q121: 1 | R121: 1 | S121: 1 | T121: 1 | U121: =AVERAGE(I121:T121) -> 1 | V121: 1
A122: 华东一区 | B122: 福建 | C122: 海特销售部 | D122: 海特料部 | E122: 区域经理 | G122: S2 | I122: 1 | J122: 1 | K122: 1 | L122: 1 | M122: 1 | N122: 1 | O122: 1 | P122: 1 | Q122: 1 | R122: 1 | S122: 1 | T122: 1 | U122: =AVERAGE(I122:T122) -> 1 | V122: 1
A123: 华东一区 | B123: 福建 | C123: 海特销售部 | D123: 海特料部 | E123: 业务员 | G123: S1 | I123: 3 | J123: 3 | K123: 3 | L123: 3 | M123: 3 | N123: 3 | O123: 3 | P123: 3 | Q123: 3 | R123: 3 | S123: 3 | T123: 3 | U123: =AVERAGE(I123:T123) -> 3 | V123: 3
A124: 华东一区 | B124: 福建 | C124: 海特销售部 | D124: 海特料部 | E124: 区域经理 | G124: S2 | I124: 1 | J124: 1 | K124: 1 | L124: 1 | M124: 1 | N124: 1 | O124: 1 | P124: 1 | Q124: 1 | R124: 1 | S124: 1 | T124: 1 | U124: =AVERAGE(I124:T124) -> 1 | V124: 1
A125: 华东一区 | B125: 福建 | C125: 海特销售部 | D125: 海特料部 | E125: 业务员 | G125: S1 | I125: 2 | J125: 2 | K125: 2 | L125: 2 | M125: 2 | N125: 2 | O125: 2 | P125: 2 | Q125: 2 | R125: 2 | S125: 2 | T125: 2 | U125: =AVERAGE(I125:T125) -> 2 | V125: 1
A126: 华东一区 | B126: 福建 | C126: 海特销售部 | D126: 海特料部 | E126: 销售经理及以上 | G126: S3 | U126: 0
A127: 华东一区 | B127: 福建 | C127: 海特销售部 | D127: 海特料部 | E127: 区域经理 | G127: S2 | I127: 1 | J127: 1 | K127: 1 | L127: 1 | M127: 1 | N127: 1 | O127: 1 | P127: 1 | Q127: 1 | R127: 1 | S127: 1 | T127: 1 | U127: =AVERAGE(I127:T127) -> 1
A128: 华东一区 | B128: 福建 | C128: 海特销售部 | D128: 海特料部 | E128: 业务员 | G128: S1 | I128: 1 | J128: 1 | K128: 1 | L128: 1 | M128: 1 | N128: 1 | O128: 1 | P128: 1 | Q128: 1 | R128: 1 | S128: 1 | T128: 1 | U128: =AVERAGE(I128:T128) -> 1 | V128: 1
A129: 华东一区 | B129: 福建 | C129: 海特销售部 | D129: 海特料部 | E129: 销售经理及以上 | G129: S4 | I129: 1 | J129: 1 | K129: 1 | L129: 1 | M129: 1 | N129: 1 | O129: 1 | P129: 1 | Q129: 1 | R129: 1 | S129: 1 | T129: 1 | U129: =AVERAGE(I129:T129) -> 1 | V129: 1
A130: 华东一区 | B130: 福建 | C130: 海特销售部 | D130: 海特料部 | E130: 区域经理 | G130: S2 | U130: 0
A131: 华东一区 | B131: 福建 | C131: 海特销售部 | D131: 海特料部 | E131: 业务员 | G131: S1 | I131: 1 | J131: 1 | K131: 1 | L131: 1 | M131: 1 | N131: 1 | O131: 1 | P131: 1 | Q131: 1 | R131: 1 | S131: 1 | T131: 1 | U131: =AVERAGE(I131:T131) -> 1
A132: 华东一区 | B132: 福建 | C132: 价值交付部 | E132: 经理 | G132: M1-1 | I132: 1 | J132: 1 | K132: 1 | L132: 1 | M132: 1 | N132: 1 | O132: 1 | P132: 1 | Q132: 1 | R132: 1 | S132: 1 | T132: 1 | U132: =AVERAGE(I132:T132) -> 1 | V132: 1
A133: 华东一区 | B133: 福建 | C133: 价值交付部 | E133: 价值交付工程师 | G133: P2-1 | I133: 12 | J133: 12 | K133: 12 | L133: 12 | M133: 12 | N133: 12 | O133: 12 | P133: 12 | Q133: 12 | R133: 12 | S133: 12 | T133: 12 | U133: =AVERAGE(I133:T133) -> 12 | V133: 9
A134: 华东一区 | B134: 福建 | C134: 价值交付部 | E134: 养殖工程师 | G134: P2-1 | I134: 22 | J134: 22 | K134: 22 | L134: 22 | M134: 22 | N134: 22 | O134: 22 | P134: 22 | Q134: 22 | R134: 22 | S134: 22 | T134: 22 | U134: =AVERAGE(I134:T134) -> 22 | V134: 6
A135: 华东一区 | B135: 福建 | C135: 价值交付部 | E135: 经理 | G135: M1-1 | U135: 0
A136: 华东一区 | B136: 福建 | C136: 价值交付部 | E136: 价值交付工程师 | G136: P2-1 | I136: 4 | J136: 4 | K136: 4 | L136: 4 | M136: 4 | N136: 4 | O136: 4 | P136: 4 | Q136: 4 | R136: 4 | S136: 4 | T136: 4 | U136: =AVERAGE(I136:T136) -> 4 | V136: 2
A137: 华东一区 | B137: 福建 | C137: 价值交付部 | E137: 价值交付工程师 | G137: P2-1 | I137: 3 | J137: 3 | K137: 3 | L137: 3 | M137: 3 | N137: 3 | O137: 3 | P137: 3 | Q137: 3 | R137: 3 | S137: 3 | T137: 3 | U137: =AVERAGE(I137:T137) -> 3 | V137: 2
A138: 华东一区 | B138: 福建 | C138: 25届应届生 | D138: 应届生 | E138: 技术服务 | G138: S1 | O138: 8 | P138: 8 | Q138: 8 | R138: 8 | S138: 8 | T138: 8 | U138: =AVERAGE(I138:T138) -> 8

Sheet 人工成本明细-人资
A1: ← 返回目录 | E1: 填录说明： | F1: 第一步，选择年、公司、版本、场景；
F2: 第二步，分月填录其他销售费用数据；
F3: 第三步，填制数据完成后，单击【提交】按钮，将数据提交至系统。
A5: 责任部门：人力资源部 | E5: 单位：元
A7: 年 | B7: 2026年 | C7: 公司 | D7: xx澳华 | E7: 版本 | F7: V1 | G7: 场景 | H7: 年度 | J7: 直接导入
A9: 1、应届生费用拆分出来工资和社保，不单独列示
A10: 2、公司专项奖金主要用于大部分都用于销售和月度评优，预算放在销售部的绩效奖金。
A11: 辅助列-不改 | B11: 费用归类 | C11: 项目 | D11: 科目 （对应财务科目） | E11: 科目 （人资预算科目） | F11: 金额 | J11: 预算明细
F12: 25年实际 | G12: 26年预算合计 | H12: 同比额 | I12: 同比率 | J12: 1月 | K12: 2月 | L12: 3月 | M12: 4月 | N12: 5月 | O12: 6月 | P12: 7月 | Q12: 8月 | R12: 9月 | S12: 10月 | T12: 11月 | U12: 12月
A13: 工资和薪金 | B13: 销售费用 | C13: 固定类薪资 | D13: 工资和薪金 | E13: 标准月薪 | G13: =SUM(J13:U13) -> 0
A14: 工资和薪金 | B14: 销售费用 | D14: 差旅费 | E14: 差旅费 | G14: =SUM(J14:U14) -> 0
A15: 工资和薪金 | B15: 销售费用 | D15: 工资和薪金 | E15: 季度绩效工资 | G15: =SUM(J15:U15) -> 0
A16: 工资和薪金 | B16: 销售费用 | D16: 工资和薪金 | E16: 过节费 | G16: =SUM(J16:U16) -> 0
A17: 工资和薪金 | B17: 销售费用 | D17: 车辆使用费 | E17: 车辆使用费
A18: 工资和薪金 | B18: 销售费用 | C18: 调薪包 | D18: 工资和薪金 | E18: 调薪包 | G18: =SUM(J18:U18) -> 0
A19: 提成奖励 | B19: 销售费用 | C19: 提成奖金类 | D19: 提成奖励 | E19: 月度提成 | F19: 计算 | G19: =SUM(J19:U19) -> 0
E20: -饲料提成
E21: -动保提成
A22: 年终提成 | B22: 销售费用 | D22: 年终提成 | E22: 营销年奖 | G22: =SUM(J22:U22) -> 0
A23: 工资和薪金 | B23: 销售费用 | C23: 浮动薪酬 | D23: 工资和薪金 | E23: 加班费 | G23: =SUM(J23:U23) -> 0
A24: 工资和薪金 | B24: 销售费用 | E24: 其他变动项 | G24: =SUM(J24:U24) -> 0
A25: 社保费 | B25: 销售费用 | C25: 社保公积金 | D25: 社保费 | E25: 社保费 | G25: =SUM(J25:U25) -> 0
A26: 住房公积金 | B26: 销售费用 | D26: 住房公积金 | E26: 住房公积金 | G26: =SUM(J26:U26) -> 0
A27: 职工福利金 | B27: 销售费用 | C27: 职工福利金 | D27: 职工福利金 | E27: 职工福利金 | G27: =SUM(J27:U27) -> 0
A28: 劳务费 | B28: 销售费用 | C28: 其他薪酬 | D28: 劳务费 | E28: 劳务费 | G28: =SUM(J28:U28) -> 0
A29: 成长分享 | B29: 销售费用 | C29: 成长分享 | D29: 成长分享 | E29: 成长分享 | G29: =SUM(J29:U29) -> 0
B30: 销售费用 | C30: 销售费用-E值 | F30: =SUM(F13:F29) -> 0 | G30: =SUM(J30:U30) -> 0 | J30: =SUM(J13:J29) -> 0 | K30: =SUM(K13:K29) -> 0 | L30: =SUM(L13:L29) -> 0 | M30: =SUM(M13:M29) -> 0 | N30: =SUM(N13:N29) -> 0 | O30: =SUM(O13:O29) -> 0 | P30: =SUM(P13:P29) -> 0 | Q30: =SUM(Q13:Q29) -> 0 | ... U30: =SUM(U13:U29) -> 0
A31: 工资和薪金 | B31: 管理费用 | C31: 固定类薪资 | D31: 工资和薪金 | E31: 标准月薪 | G31: =SUM(J31:U31) -> 0
A32: 车辆使用费 | B32: 管理费用 | D32: 车辆使用费 | E32: 车辆补贴 | G32: =SUM(J32:U32) -> 0
A33: 工资和薪金 | B33: 管理费用 | D33: 绩效工资 | E33: 绩效工资 | G33: =SUM(J33:U33) -> 0
A34: 专项及后勤年终奖 | B34: 管理费用 | D34: 专项及后勤年终奖 | E34: 年终奖 | G34: =SUM(J34:U34) -> 0
A35: 工资和薪金 | B35: 管理费用 | D35: 工资和薪金 | E35: 过节费 | G35: =SUM(J35:U35) -> 0
A36: 工资和薪金 | B36: 管理费用 | C36: 调薪包 | D36: 工资和薪金 | E36: 调薪包 | G36: =SUM(J36:U36) -> 0
A37: 工资和薪金 | B37: 管理费用 | C37: 浮动薪酬 | D37: 工资和薪金 | E37: 加班费 | G37: =SUM(J37:U37) -> 0
A38: 工资和薪金 | B38: 管理费用 | D38: 工资和薪金 | E38: 其他变动项 | G38: =SUM(J38:U38) -> 0
A39: 社保费 | B39: 管理费用 | C39: 社保公积金 | D39: 社保费 | E39: 社保费 | G39: =SUM(J39:U39) -> 0
A40: 住房公积金 | B40: 管理费用 | D40: 住房公积金 | E40: 住房公积金 | G40: =SUM(J40:U40) -> 0
A41: 职工福利金 | B41: 管理费用 | C41: 职工福利金 | D41: 职工福利金 | E41: 职工福利金 | G41: =SUM(J41:U41) -> 0
A42: 劳务外包 | B42: 管理费用 | C42: 其他薪酬 | D42: 劳务外包 | E42: 劳务费 | G42: =SUM(J42:U42) -> 0
A43: 成长分享 | B43: 管理费用 | C43: 成长分享 | D43: 成长分享 | E43: 成长分享 | G43: =SUM(J43:U43) -> 0
A44: 员工意外保险 | B44: 管理费用 | C44: 商业险 | D44: 员工意外保险 | E44: 员工意外保险 | G44: =SUM(J44:U44) -> 0
B45: 管理费用 | C45: 管理费用-E值 | F45: =SUM(F31:F44) -> 0 | G45: =SUM(J45:U45) -> 0 | J45: =SUM(J31:J44) -> 0 | K45: =SUM(K31:K44) -> 0 | L45: =SUM(L31:L44) -> 0 | M45: =SUM(M31:M44) -> 0 | N45: =SUM(N31:N44) -> 0 | O45: =SUM(O31:O44) -> 0 | P45: =SUM(P31:P44) -> 0 | Q45: =SUM(Q31:Q44) -> 0 | ... U45: =SUM(U31:U44) -> 0
A46: 工资和薪金 | B46: 制造费用 | C46: 固定类薪资 | D46: 工资和薪金 | E46: 标准月薪 | G46: =SUM(J46:U46) -> 0
A47: 提成奖励 | B47: 制造费用 | D47: 绩效工资及奖金生产绩效 | E47: 绩效工资 | G47: =SUM(J47:U47) -> 0
A48: 工资和薪金 | B48: 制造费用 | D48: 工资和薪金 | E48: 年终奖 | G48: =SUM(J48:U48) -> 0
A49: 工资和薪金 | B49: 制造费用 | D49: 工资和薪金 | E49: 过节费 | G49: =SUM(J49:U49) -> 0
A50: 工资和薪金 | B50: 制造费用 | C50: 调薪包 | D50: 工资和薪金 | E50: 调薪包 | G50: =SUM(J50:U50) -> 0
A51: 提成奖励 | B51: 制造费用 | C51: 提成奖金类 | D51: 绩效工资及奖金生产绩效 | E51: 生产奖金 | G51: =SUM(J51:U51) -> 0
A52: 工资和薪金 | B52: 制造费用 | C52: 浮动薪酬 | D52: 工资和薪金 | E52: 加班费 | G52: =SUM(J52:U52) -> 0
A53: 工资和薪金 | B53: 制造费用 | D53: 工资和薪金 | E53: 其他变动项 | G53: =SUM(J53:U53) -> 0
A54: 社保费 | B54: 制造费用 | C54: 社保公积金 | D54: 社保费 | E54: 社保费 | G54: =SUM(J54:U54) -> 0
A55: 住房公积金 | B55: 制造费用 | D55: 住房公积金 | E55: 住房公积金 | G55: =SUM(J55:U55) -> 0
A56: 职工福利金 | B56: 制造费用 | C56: 职工福利金 | D56: 职工福利金 | E56: 职工福利金 | G56: =SUM(J56:U56) -> 0
A57: 劳务费 | B57: 制造费用 | C57: 其他薪酬 | D57: 劳务费 | E57: 劳务费 | G57: =SUM(J57:U57) -> 0
A58: 工资和薪金 | B58: 制造费用 | C58: 成长分享 | D58: 工资和薪金 | E58: 成长分享 | G58: =SUM(J58:U58) -> 0
B59: 制造费用 | C59: 制造费用-E值 | F59: =SUM(F46:F58) -> 0 | G59: =SUM(J59:U59) -> 0 | J59: =SUM(J46:J58) -> 0 | K59: =SUM(K46:K58) -> 0 | L59: =SUM(L46:L58) -> 0 | M59: =SUM(M46:M58) -> 0 | N59: =SUM(N46:N58) -> 0 | O59: =SUM(O46:O58) -> 0 | P59: =SUM(P46:P58) -> 0 | Q59: =SUM(Q46:Q58) -> 0 | ... U59: =SUM(U46:U58) -> 0

Sheet 表7 表样-销费
A1: ← 返回目录
B2: 预算项目 | C2: 2026年 | L2: 2025年 | U2: 同比增长额 | V2: 同比增长率 | W2: 2026年预算 | AJ2: 2025年实际数
C3: 合计 | D3: 虾蟹料部 | E3: 海特料部 | F3: 普鱼料部 | G3: 畜禽料部 | H3: 反刍料部 | I3: 价值交付部 | J3: 学生 | K3: 其他公共费用 | L3: 合计 | M3: 虾蟹料部 | N3: 海特料部 | O3: 普鱼料部 | P3: 畜禽料部 | Q3: 反刍料部 | R3: 价值交付部 | S3: 学生 | T3: 其他公共费用 | W3: 1月 | X3: 2月 | Y3: 3月 | Z3: 4月 | AA3: 5月 | AB3: 6月 | AC3: 7月 | AD3: 8月 | AE3: 9月 | AF3: 10月 | AG3: 11月 | AH3: 12月 | AI3: 合计 | AJ3: 1月 | AK3: 2月 | AL3: 3月 | AM3: 4月 | AN3: 5月 | AO3: 6月 | AP3: 7月 | AQ3: 8月 | AR3: 9月 | AS3: 10月 | AT3: 11月 | AU3: 12月 | AV3: 合计
B4: 变动费用小计 | C4: 计算 | D4: 计算 | E4: 计算 | F4: 计算 | G4: 计算 | H4: 计算 | I4: 计算 | J4: 计算 | K4: 计算 | L4: 计算 | M4: 计算 | N4: 计算 | O4: 计算 | P4: 计算 | Q4: 计算 | R4: 计算 | S4: 计算 | T4: 计算 | U4: 计算 | V4: 计算 | W4: 计算 | X4: 计算 | Y4: 计算 | Z4: 计算 | AA4: 计算 | AB4: 计算 | AC4: 计算 | AD4: 计算 | AE4: 计算 | AF4: 计算 | AG4: 计算 | AH4: 计算 | AI4: 计算 | AJ4: 计算 | AK4: 计算 | AL4: 计算 | AM4: 计算 | AN4: 计算 | AO4: 计算 | AP4: 计算 | AQ4: 计算 | AR4: 计算 | AS4: 计算 | AT4: 计算 | AU4: 计算 | AV4: 计算
B5: 提成奖励
B6: 饲料提成
B7: 动保提成
B8: 年终提成
B9: 成长分享
B10: 运输费
B11: 技术服务费
B12: 推广、会务
B13: 固定费用小计
B14: 人力费用（固定工资、五险一金、职工福利）
B15: 差旅费
B16: 业务招待费
... B25: 销售费用率
C26: 摊销逻辑：能划分到产线的费用到产线，不能到产线的公共费用按自然吨平均摊销。
C29: 动保的提成*** NC 核算没有拆分

Sheet 表7.1 表样-销费科目明细
A1: ← 返回目录
A2: 行号 | B2: 费用分类 | C2: 科目名称 | D2: 费用归属 | E2: 2026年 | H2: 2025年 | K2: 2026年预算 | X2: 2025年实际数
E3: 全年 | F3: 增长额 | G3: 增长率 | H3: 全年 | I3: 增长额 | J3: 增长率 | K3: 1月 | L3: 2月 | M3: 3月 | N3: 4月 | O3: 5月 | P3: 6月 | Q3: 7月 | R3: 8月 | S3: 9月 | T3: 10月 | U3: 11月 | V3: 12月 | W3: 合计 | X3: 1 | Y3: 2 | Z3: 3 | AA3: 4 | AB3: 5 | AC3: 6 | AD3: 7 | AE3: 8 | AF3: 9 | AG3: 10 | AH3: 11 | AI3: 12 | AJ3: 合计
A4: 59 | B4: / | C4: 销售吨数 | D4: / | E4: 计算 | F4: 计算 | G4: 计算 | H4: 计算 | I4: 计算 | J4: 计算 | K4: 计算 | L4: 计算 | M4: 计算 | N4: 计算 | O4: 计算 | P4: 计算 | Q4: 计算 | R4: 计算 | S4: 计算 | T4: 计算 | U4: 计算 | V4: 计算 | W4: 计算 | X4: 计算 | Y4: 计算 | Z4: 计算 | AA4: 计算 | AB4: 计算 | AC4: 计算 | AD4: 计算 | AE4: 计算 | AF4: 计算 | AG4: 计算 | AH4: 计算 | AI4: 计算 | AJ4: 计算
A5: 60 | B5: / | C5: 销售标准吨数 | D5: /
A6: 61 | B6: / | C6: 销售人数 | D6: /
A7: 62 | B7: 固定 | C7: 工资和薪金 | D7: 人力费用（固定工资、五险一金、职工福利）
A8: 63 | B8: 变动 | C8: 提成奖励 | D8: 提成奖励
C9: 饲料提成
C10: 动保提成
A11: 64 | B11: 变动 | C11: 年终提成 | D11: 年终提成
A12: 65 | B12: 变动 | C12: 成长分享 | D12: 成长分享
A13: 66 | B13: 固定 | C13: 劳务费 | D13: 人力费用（固定工资、五险一金、职工福利）
A14: 67 | B14: 固定 | C14: 社保费 | D14: 人力费用（固定工资、五险一金、职工福利）
A15: 68 | B15: 固定 | C15: 住房公积金 | D15: 人力费用（固定工资、五险一金、职工福利）
A16: 69 | B16: 固定 | C16: 职工福利金 | D16: 人力费用（固定工资、五险一金、职工福利）
A17: 70 | B17: 固定 | C17: 差旅补助 | D17: 差旅费
A18: 71 | B18: 固定 | C18: 差旅费 | D18: 差旅费
A19: 72 | B19: 固定 | C19: 车辆使用费 | D19: 人力费用（固定工资、五险一金、职工福利）
A20: 73 | B20: 固定 | C20: 业务招待费 | D20: 应酬费
A21: 74 | B21: 变动 | C21: 销售推广费 | D21: 推广、会务
A22: 75 | B22: 固定 | C22: 会务费 | D22: 推广、会务
... A33: 86 | B33: 固定 | C33: 长期待摊费用摊销 | D33: 固定资产折旧费
A34: 87 | C34: 合计
A35: 88 | C35: 单吨变动销售费用
A36: 89 | C36: 单吨固定销售费用
A37: 90 | C37: 单吨销售费用
A38: 91 | C38: E值

Sheet 填写-职工福利费
A1: ← 返回目录 | E1: 填录说明： | F1: 第一步，选择年、公司、版本、场景；
F2: 第二步，下拉选择部门、类型，填写项目、人均费用标准（若有）；
F3: 第三步，分月填录各月职工福利费数据；
F4: 第四步，填制数据完成后，单击【提交】按钮，将数据提交至系统。
A5: 责任部门：营销部 | E5: 单位：元
A7: 年 | B7: 2026年 | C7: 公司 | D7: xx澳华 | E7: 版本 | F7: V1 | G7: 场景 | H7: 年度
A9: 部门 | B9: 年份 | C9: 合计
D10: 1月 | E10: 2月 | F10: 3月 | G10: 4月 | H10: 5月 | I10: 6月 | J10: 7月 | K10: 8月 | L10: 9月 | M10: 10月 | N10: 11月 | O10: 12月
A11: 选择 | B11: 2025 | C11: 计算 | D11: 自动生成 | E11: 自动生成 | F11: 自动生成 | G11: 自动生成 | H11: 自动生成 | I11: 自动生成 | J11: 自动生成 | K11: 自动生成 | L11: 自动生成 | M11: 自动生成 | N11: 自动生成 | O11: 自动生成
B12: 2026
B13: 同比
A16: 部门 | B16: 类型 | C16: 项目 | D16: 费用标准（元/人） | E16: 说明 | F16: 2026年合计 | G16: 2026年预算数
G17: 1月 | H17: 2月 | I17: 3月 | J17: 4月 | K17: 5月 | L17: 6月 | M17: 7月 | N17: 8月 | O17: 9月 | P17: 10月 | Q17: 11月 | R17: 12月
A18: 选择 | B18: 选择 | C18: 填入 | D18: 填入 | E18: 填入 | F18: 计算 | G18: 填入 | H18: 填入 | I18: 填入 | J18: 填入 | K18: 填入 | L18: 填入 | M18: 填入 | N18: 填入 | O18: 填入 | P18: 填入 | Q18: 填入 | R18: 填入
B19: 节日礼品 | C19: 春节 | D19: 150
C20: 妇女节 | D20: 150
C21: 端午节
C22: xxx
B23: 团建费
B26: 食堂费用
B29: 宿舍费用
A34: 合计

Sheet 填写-销售推广费 (广告)
A1: ← 返回目录 | E1: 填录说明： | F1: 第一步，选择年、公司、版本、场景；
F2: 第二步，下拉选择部门、类型，填写项目；
F3: 第三步，分月填录各月广告费数据；
F4: 第四步，填制数据完成后，单击【提交】按钮，将数据提交至系统。
A5: 责任部门：营销部 | E5: 单位：元
A7: 年 | B7: 2026年 | C7: 公司 | D7: xx澳华 | E7: 版本 | F7: V1 | G7: 场景 | H7: 年度
A9: 部门 | B9: 年份 | C9: 合计
D10: 1月 | E10: 2月 | F10: 3月 | G10: 4月 | H10: 5月 | I10: 6月 | J10: 7月 | K10: 8月 | L10: 9月 | M10: 10月 | N10: 11月 | O10: 12月
A11: 选择 | B11: 2025 | C11: 计算 | D11: 自动生成 | E11: 自动生成 | F11: 自动生成 | G11: 自动生成 | H11: 自动生成 | I11: 自动生成 | J11: 自动生成 | K11: 自动生成 | L11: 自动生成 | M11: 自动生成 | N11: 自动生成 | O11: 自动生成
B12: 2026
B13: 同比
A15: 部门 | B15: 类型 | C15: 项目 | D15: 说明 | E15: 2026年合计 | F15: 2026年预算数
F16: 1月 | G16: 2月 | H16: 3月 | I16: 4月 | J16: 5月 | K16: 6月 | L16: 7月 | M16: 8月 | N16: 9月 | O16: 10月 | P16: 11月 | Q16: 12月
A17: 选择 | B17: 选择 | C17: 填入 | D17: 填入 | E17: 计算 | F17: 填入 | G17: 填入 | H17: 填入 | I17: 填入 | J17: 填入 | K17: 填入 | L17: 填入 | M17: 填入 | N17: 填入 | O17: 填入 | P17: 填入 | Q17: 填入
B18: 广告发布 | C18: 公众号广告
C19: 网站广告
C20: 电视广告
C21: 报纸杂志
B22: 公关赞助费 | C22: xxx会议
C23: xxx协会
B24: 设计策划费 | C24: 传单设计
A33: 合计

Sheet 填写-业务招待费
A1: ← 返回目录 | E1: 填录说明： | F1: 第一步，选择年、公司、版本、场景；
F2: 第二步，填写姓名、招待事由；
F3: 第三步，分月填录各月业务招待费数据；
F4: 第四步，填制数据完成后，单击【提交】按钮，将数据提交至系统。
A5: 责任部门：营销部 | E5: 单位：元
A7: 年 | B7: 2026年 | C7: 公司 | D7: xx澳华 | E7: 版本 | F7: V1 | G7: 场景 | H7: 年度
A9: 部门 | B9: 年份 | C9: 合计
D10: 1月 | E10: 2月 | F10: 3月 | G10: 4月 | H10: 5月 | I10: 6月 | J10: 7月 | K10: 8月 | L10: 9月 | M10: 10月 | N10: 11月 | O10: 12月
A11: 选择 | B11: 2025 | C11: 计算 | D11: 自动生成 | E11: 自动生成 | F11: 自动生成 | G11: 自动生成 | H11: 自动生成 | I11: 自动生成 | J11: 自动生成 | K11: 自动生成 | L11: 自动生成 | M11: 自动生成 | N11: 自动生成 | O11: 自动生成
B12: 2026
B13: 同比
A16: 部门 | B16: 姓名 | C16: 岗位 | D16: 招待事由 | E16: 2026年合计 | F16: 2026年预算数
F17: 1月 | G17: 2月 | H17: 3月 | I17: 4月 | J17: 5月 | K17: 6月 | L17: 7月 | M17: 8月 | N17: 9月 | O17: 10月 | P17: 11月 | Q17: 12月
A18: 自动生成 | B18: 填入 | C18: 自动生成 | D18: 填入 | E18: 计算 | F18: 填入 | G18: 填入 | H18: 填入 | I18: 填入 | J18: 填入 | K18: 填入 | L18: 填入 | M18: 填入 | N18: 填入 | O18: 填入 | P18: 填入 | Q18: 填入
C19: 总经理
C20: 销售副经理
A34: 合计

Sheet 填写-销售推广费 (物资推广) 
A1: ← 返回目录 | E1: 填录说明： | F1: 第一步，选择年、公司、版本、场景；
F2: 第二步，下拉选择部门、类型，填写项目、数量、单价；
F3: 第三步，分月填录各月物资推广费用数据；
F4: 第四步，填制数据完成后，单击【提交】按钮，将数据提交至系统。
A5: 责任部门：营销部 | E5: 单位：元
A7: 年 | B7: 2026年 | C7: 公司 | D7: xx澳华 | E7: 版本 | F7: V1 | G7: 场景 | H7: 年度
A9: 部门 | B9: 年份 | C9: 合计
D10: 1月 | E10: 2月 | F10: 3月 | G10: 4月 | H10: 5月 | I10: 6月 | J10: 7月 | K10: 8月 | L10: 9月 | M10: 10月 | N10: 11月 | O10: 12月
A11: 选择 | B11: 2025 | C11: 计算 | D11: 自动生成 | E11: 自动生成 | F11: 自动生成 | G11: 自动生成 | H11: 自动生成 | I11: 自动生成 | J11: 自动生成 | K11: 自动生成 | L11: 自动生成 | M11: 自动生成 | N11: 自动生成 | O11: 自动生成
B12: 2026 | D12: 自动生成金额
B13: 同比
H14: 取数量乘以单价 | Q14: 填写分月金额，最后校验左方单价乘以数量与合计数是否一致
A15: 部门 | B15: 类型 | C15: 项目 | D15: 说明 | E15: 2026年合计 | F15: 2026年预算金额
F16: 1月 | G16: 2月 | H16: 3月 | I16: 4月 | J16: 5月 | K16: 6月 | L16: 7月 | M16: 8月 | N16: 9月 | O16: 10月 | P16: 11月 | Q16: 12月
A17: 选择 | B17: 选择 | C17: 填入 | D17: 填入 | E17: 计算 | F17: 填入 | G17: 填入 | H17: 填入 | I17: 填入 | J17: 填入 | K17: 填入 | L17: 填入 | M17: 填入 | N17: 填入 | O17: 填入 | P17: 填入 | Q17: 填入
B18: 养殖机械类 | C18: 增氧机
C19: 投料机
C20: xxx
B21: 服饰 | C21: 广告衫
C22: 蓝大褂
C23: xxx
B24: 节日礼品 | C24: 春节
C25: xxx
B26: 其他 | C26: xxx
A34: 合计

Sheet 填写-会务费
A1: ← 返回目录 | E1: 填录说明： | F1: 第一步，选择年、公司、版本、场景；
F2: 第二步，下拉选择部门、会议类型，填写人均费用标准；
F3: 第三步，分月填录各月会议场次、涉及人数、总费用数据；
F4: 第四步，填制数据完成后，单击【提交】按钮，将数据提交至系统。
A5: 责任部门：营销部 | E5: 单位：元
A7: 年 | B7: 2026年 | C7: 公司 | D7: xx澳华 | E7: 版本 | F7: V1 | G7: 场景 | H7: 年度
A9: 部门 | B9: 年份 | C9: 合计
D10: 1月 | E10: 2月 | F10: 3月 | G10: 4月 | H10: 5月 | I10: 6月 | J10: 7月 | K10: 8月 | L10: 9月 | M10: 10月 | N10: 11月 | O10: 12月
A11: 选择 | B11: 2025 | C11: 计算 | D11: 自动生成 | E11: 自动生成 | F11: 自动生成 | G11: 自动生成 | H11: 自动生成 | I11: 自动生成 | J11: 自动生成 | K11: 自动生成 | L11: 自动生成 | M11: 自动生成 | N11: 自动生成 | O11: 自动生成
B12: 2026 | D12: 自动生成金额
B13: 同比
